Workbook

Sheet aggregate_level
J1: Repayment schedule with an income of 20000 pounds
A2: Starting parameters | E2: Starting salary | F2: PV loan | G2: k | H2: Elasticity | J2: Year | K2: Income | L2: raw repayment | M2: Opening balance | N2: actual repayment | O2: discounted payment | P2: Closing balance
A3: L | B3: 9250 | E3: 20000 | F3: =MAX(SUM(O3:O32),1) -> 2366.6928 | G3: =LN($B$4)-LN(F3) -> 2.2385988 | H3: =-$B$10/G3 -> 0.48244465 | J3: 1 | K3: =$E$3*(1+$B$7)^(J3-1) -> 20000 | L3: =$B$5*MAX(0,K3-$B$6) -> 0 | M3: =$B$3 -> 9250 | N3: =MIN(L3,M3) -> 0 | O3: =N3/(1+$B$8)^J3 -> 0 | P3: =M3-N3 -> 9250
A4: Ppost | B4: 22200 | E4: 26000 | F4: =MAX(SUM(O37:O66),1) -> 5835.482 | G4: =LN($B$4)-LN(F4) -> 1.3361354 | H4: =-$B$10/G4 -> 0.8083013 | J4: =J3+1 -> 2 | K4: =$E$3*(1+$B$7)^(J4-1) -> 20400 | L4: =$B$5*MAX(0,K4-$B$6) -> 0 | M4: =P3 -> 9250 | N4: =IF(M4<=0,0,MIN(L4,M4)) -> 0 | O4: =N4/(1+$B$8)^J4 -> 0 | P4: =MAX(0,M4-N4) -> 9250
A5: alpha | B5: 0.09 | E5: 32000 | F5: =MAX(SUM(O72:O101),1) -> 7435.2478 | G5: =LN($B$4)-LN(F5) -> 1.0938604 | H5: =-$B$10/G5 -> 0.98732892 | J5: =J4+1 -> 3 | K5: =$E$3*(1+$B$7)^(J5-1) -> 20808 | L5: =$B$5*MAX(0,K5-$B$6) -> 0 | M5: =P4 -> 9250 | N5: =IF(M5<=0,0,MIN(L5,M5)) -> 0 | O5: =N5/(1+$B$8)^J5 -> 0 | P5: =MAX(0,M5-N5) -> 9250
A6: tau | B6: 27295 | E6: 35000 | F6: =MAX(SUM(O107:O137),1) -> 7822.4386 | G6: =LN($B$4)-LN(F6) -> 1.0430959 | H6: =-$B$10/G6 -> 1.0353793 | J6: =J5+1 -> 4 | K6: =$E$3*(1+$B$7)^(J6-1) -> 21224.16 | L6: =$B$5*MAX(0,K6-$B$6) -> 0 | M6: =P5 -> 9250 | N6: =IF(M6<=0,0,MIN(L6,M6)) -> 0 | O6: =N6/(1+$B$8)^J6 -> 0 | P6: =MAX(0,M6-N6) -> 9250
A7: g | B7: 0.02 | E7: 42000 | F7: =MAX(SUM(O142:O172),1) -> 8301.8075 | G7: =LN($B$4)-LN(F7) -> 0.98361902 | H7: =-$B$10/G7 -> 1.0979861 | J7: =J6+1 -> 5 | K7: =$E$3*(1+$B$7)^(J7-1) -> 21648.643 | L7: =$B$5*MAX(0,K7-$B$6) -> 0 | M7: =P6 -> 9250 | N7: =IF(M7<=0,0,MIN(L7,M7)) -> 0 | O7: =N7/(1+$B$8)^J7 -> 0 | P7: =MAX(0,M7-N7) -> 9250
A8: r | B8: 0.03 | E8: 50000 | F8: =MAX(SUM(O177:O207),1) -> 8547.9214 | G8: =LN($B$4)-LN(F8) -> 0.95440414 | H8: =-$B$10/G8 -> 1.1315961 | J8: =J7+1 -> 6 | K8: =$E$3*(1+$B$7)^(J8-1) -> 22081.616 | L8: =$B$5*MAX(0,K8-$B$6) -> 0 | M8: =P7 -> 9250 | N8: =IF(M8<=0,0,MIN(L8,M8)) -> 0 | O8: =N8/(1+$B$8)^J8 -> 0 | P8: =MAX(0,M8-N8) -> 9250
A9: T | B9: 30 | J9: =J8+1 -> 7 | K9: =$E$3*(1+$B$7)^(J9-1) -> 22523.248 | L9: =$B$5*MAX(0,K9-$B$6) -> 0 | M9: =P8 -> 9250 | N9: =IF(M9<=0,0,MIN(L9,M9)) -> 0 | O9: =N9/(1+$B$8)^J9 -> 0 | P9: =MAX(0,M9-N9) -> 9250
A10: beta_pooled | B10: -1.08 | J10: =J9+1 -> 8 | K10: =$E$3*(1+$B$7)^(J10-1) -> 22973.713 | L10: =$B$5*MAX(0,K10-$B$6) -> 0 | M10: =P9 -> 9250 | N10: =IF(M10<=0,0,MIN(L10,M10)) -> 0 | O10: =N10/(1+$B$8)^J10 -> 0 | P10: =MAX(0,M10-N10) -> 9250
J11: =J10+1 -> 9 | K11: =$E$3*(1+$B$7)^(J11-1) -> 23433.188 | L11: =$B$5*MAX(0,K11-$B$6) -> 0 | M11: =P10 -> 9250 | N11: =IF(M11<=0,0,MIN(L11,M11)) -> 0 | O11: =N11/(1+$B$8)^J11 -> 0 | P11: =MAX(0,M11-N11) -> 9250
J12: =J11+1 -> 10 | K12: =$E$3*(1+$B$7)^(J12-1) -> 23901.851 | L12: =$B$5*MAX(0,K12-$B$6) -> 0 | M12: =P11 -> 9250 | N12: =IF(M12<=0,0,MIN(L12,M12)) -> 0 | O12: =N12/(1+$B$8)^J12 -> 0 | P12: =MAX(0,M12-N12) -> 9250
J13: =J12+1 -> 11 | K13: =$E$3*(1+$B$7)^(J13-1) -> 24379.888 | L13: =$B$5*MAX(0,K13-$B$6) -> 0 | M13: =P12 -> 9250 | N13: =IF(M13<=0,0,MIN(L13,M13)) -> 0 | O13: =N13/(1+$B$8)^J13 -> 0 | P13: =MAX(0,M13-N13) -> 9250
J14: =J13+1 -> 12 | K14: =$E$3*(1+$B$7)^(J14-1) -> 24867.486 | L14: =$B$5*MAX(0,K14-$B$6) -> 0 | M14: =P13 -> 9250 | N14: =IF(M14<=0,0,MIN(L14,M14)) -> 0 | O14: =N14/(1+$B$8)^J14 -> 0 | P14: =MAX(0,M14-N14) -> 9250
J15: =J14+1 -> 13 | K15: =$E$3*(1+$B$7)^(J15-1) -> 25364.836 | L15: =$B$5*MAX(0,K15-$B$6) -> 0 | M15: =P14 -> 9250 | N15: =IF(M15<=0,0,MIN(L15,M15)) -> 0 | O15: =N15/(1+$B$8)^J15 -> 0 | P15: =MAX(0,M15-N15) -> 9250
J16: =J15+1 -> 14 | K16: =$E$3*(1+$B$7)^(J16-1) -> 25872.133 | L16: =$B$5*MAX(0,K16-$B$6) -> 0 | M16: =P15 -> 9250 | N16: =IF(M16<=0,0,MIN(L16,M16)) -> 0 | O16: =N16/(1+$B$8)^J16 -> 0 | P16: =MAX(0,M16-N16) -> 9250
J17: =J16+1 -> 15 | K17: =$E$3*(1+$B$7)^(J17-1) -> 26389.575 | L17: =$B$5*MAX(0,K17-$B$6) -> 0 | M17: =P16 -> 9250 | N17: =IF(M17<=0,0,MIN(L17,M17)) -> 0 | O17: =N17/(1+$B$8)^J17 -> 0 | P17: =MAX(0,M17-N17) -> 9250
J18: =J17+1 -> 16 | K18: =$E$3*(1+$B$7)^(J18-1) -> 26917.367 | L18: =$B$5*MAX(0,K18-$B$6) -> 0 | M18: =P17 -> 9250 | N18: =IF(M18<=0,0,MIN(L18,M18)) -> 0 | O18: =N18/(1+$B$8)^J18 -> 0 | P18: =MAX(0,M18-N18) -> 9250
J19: =J18+1 -> 17 | K19: =$E$3*(1+$B$7)^(J19-1) -> 27455.714 | L19: =$B$5*MAX(0,K19-$B$6) -> 14.464269 | M19: =P18 -> 9250 | N19: =IF(M19<=0,0,MIN(L19,M19)) -> 14.464269 | O19: =N19/(1+$B$8)^J19 -> 8.7511207 | P19: =MAX(0,M19-N19) -> 9235.5357
J20: =J19+1 -> 18 | K20: =$E$3*(1+$B$7)^(J20-1) -> 28004.828 | L20: =$B$5*MAX(0,K20-$B$6) -> 63.884555 | M20: =P19 -> 9235.5357 | N20: =IF(M20<=0,0,MIN(L20,M20)) -> 63.884555 | O20: =N20/(1+$B$8)^J20 -> 37.525443 | P20: =MAX(0,M20-N20) -> 9171.6512
J21: =J20+1 -> 19 | K21: =$E$3*(1+$B$7)^(J21-1) -> 28564.925 | L21: =$B$5*MAX(0,K21-$B$6) -> 114.29325 | M21: =P20 -> 9171.6512 | N21: =IF(M21<=0,0,MIN(L21,M21)) -> 114.29325 | O21: =N21/(1+$B$8)^J21 -> 65.179841 | P21: =MAX(0,M21-N21) -> 9057.3579
J22: =J21+1 -> 20 | K22: =$E$3*(1+$B$7)^(J22-1) -> 29136.223 | L22: =$B$5*MAX(0,K22-$B$6) -> 165.71011 | M22: =P21 -> 9057.3579 | N22: =IF(M22<=0,0,MIN(L22,M22)) -> 165.71011 | O22: =N22/(1+$B$8)^J22 -> 91.74967 | P22: =MAX(0,M22-N22) -> 8891.6478
... J32: =J31+1 -> 30 | K32: =$E$3*(1+$B$7)^(J32-1) -> 35516.894 | L32: =$B$5*MAX(0,K32-$B$6) -> 739.97044 | M32: =P31 -> 4909.8413 | N32: =IF(M32<=0,0,MIN(L32,M32)) -> 739.97044 | O32: =N32/(1+$B$8)^J32 -> 304.85802 | P32: =MAX(0,M32-N32) -> 4169.8709
K33: =$E$3*(1+$B$7)^(J33-1) -> 19607.843 | L33: =$B$5*MAX(0,K33-$B$6) -> 0 | M33: =P32 -> 4169.8709 | N33: =IF(M33<=0,0,MIN(L33,M33)) -> 0 | O33: =N33/(1+$B$8)^J33 -> 0 | P33: =MAX(0,M33-N33) -> 4169.8709
J35: Repayment schedule with an income of 26000 pounds
J36: Year | K36: Income | L36: raw repayment | M36: Opening balance | N36: actual repayment | O36: discounted payment | P36: Closing balance
J37: 1 | K37: =$E$4*(1+$B$7)^(J37-1) -> 26000 | L37: =$B$5*MAX(0,K37-$B$6) -> 0 | M37: =$B$3 -> 9250 | N37: =MIN(L37,M37) -> 0 | O37: =N37/(1+$B$8)^J37 -> 0 | P37: =M37-N37 -> 9250
J38: =J37+1 -> 2 | K38: =$E$4*(1+$B$7)^(J38-1) -> 26520 | L38: =$B$5*MAX(0,K38-$B$6) -> 0 | M38: =P37 -> 9250 | N38: =MIN(L38,M38) -> 0 | O38: =N38/(1+$B$8)^J38 -> 0 | P38: =M38-N38 -> 9250
J39: =J38+1 -> 3 | K39: =$E$4*(1+$B$7)^(J39-1) -> 27050.4 | L39: =$B$5*MAX(0,K39-$B$6) -> 0 | M39: =P38 -> 9250 | N39: =MIN(L39,M39) -> 0 | O39: =N39/(1+$B$8)^J39 -> 0 | P39: =M39-N39 -> 9250
J40: =J39+1 -> 4 | K40: =$E$4*(1+$B$7)^(J40-1) -> 27591.408 | L40: =$B$5*MAX(0,K40-$B$6) -> 26.67672 | M40: =P39 -> 9250 | N40: =MIN(L40,M40) -> 26.67672 | O40: =N40/(1+$B$8)^J40 -> 23.70192 | P40: =M40-N40 -> 9223.3233
J41: =J40+1 -> 5 | K41: =$E$4*(1+$B$7)^(J41-1) -> 28143.236 | L41: =$B$5*MAX(0,K41-$B$6) -> 76.341254 | M41: =P40 -> 9223.3233 | N41: =MIN(L41,M41) -> 76.341254 | O41: =N41/(1+$B$8)^J41 -> 65.852637 | P41: =M41-N41 -> 9146.982
J42: =J41+1 -> 6 | K42: =$E$4*(1+$B$7)^(J42-1) -> 28706.101 | L42: =$B$5*MAX(0,K42-$B$6) -> 126.99908 | M42: =P41 -> 9146.982 | N42: =MIN(L42,M42) -> 126.99908 | O42: =N42/(1+$B$8)^J42 -> 106.35973 | P42: =M42-N42 -> 9019.9829
J43: =J42+1 -> 7 | K43: =$E$4*(1+$B$7)^(J43-1) -> 29280.223 | L43: =$B$5*MAX(0,K43-$B$6) -> 178.67006 | M43: =P42 -> 9019.9829 | N43: =MIN(L43,M43) -> 178.67006 | O43: =N43/(1+$B$8)^J43 -> 145.27511 | P43: =M43-N43 -> 8841.3129
J44: =J43+1 -> 8 | K44: =$E$4*(1+$B$7)^(J44-1) -> 29865.827 | L44: =$B$5*MAX(0,K44-$B$6) -> 231.37446 | M44: =P43 -> 8841.3129 | N44: =MIN(L44,M44) -> 231.37446 | O44: =N44/(1+$B$8)^J44 -> 182.64914 | P44: =M44-N44 -> 8609.9384
J45: =J44+1 -> 9 | K45: =$E$4*(1+$B$7)^(J45-1) -> 30463.144 | L45: =$B$5*MAX(0,K45-$B$6) -> 285.13295 | M45: =P44 -> 8609.9384 | N45: =MIN(L45,M45) -> 285.13295 | O45: =N45/(1+$B$8)^J45 -> 218.53067 | P45: =M45-N45 -> 8324.8055
J46: =J45+1 -> 10 | K46: =$E$4*(1+$B$7)^(J46-1) -> 31072.407 | L46: =$B$5*MAX(0,K46-$B$6) -> 339.96661 | M46: =P45 -> 8324.8055 | N46: =MIN(L46,M46) -> 339.96661 | O46: =N46/(1+$B$8)^J46 -> 252.96709 | P46: =M46-N46 -> 7984.8389
J47: =J46+1 -> 11 | K47: =$E$4*(1+$B$7)^(J47-1) -> 31693.855 | L47: =$B$5*MAX(0,K47-$B$6) -> 395.89694 | M47: =P46 -> 7984.8389 | N47: =MIN(L47,M47) -> 395.89694 | O47: =N47/(1+$B$8)^J47 -> 286.00437 | P47: =M47-N47 -> 7588.9419
J48: =J47+1 -> 12 | K48: =$E$4*(1+$B$7)^(J48-1) -> 32327.732 | L48: =$B$5*MAX(0,K48-$B$6) -> 452.94588 | M48: =P47 -> 7588.9419 | N48: =MIN(L48,M48) -> 452.94588 | O48: =N48/(1+$B$8)^J48 -> 317.68713 | P48: =M48-N48 -> 7135.996
J49: =J48+1 -> 13 | K49: =$E$4*(1+$B$7)^(J49-1) -> 32974.287 | L49: =$B$5*MAX(0,K49-$B$6) -> 511.1358 | M49: =P48 -> 7135.996 | N49: =MIN(L49,M49) -> 511.1358 | O49: =N49/(1+$B$8)^J49 -> 348.05861 | P49: =M49-N49 -> 6624.8602
... J66: =J65+1 -> 30 | K66: =$E$4*(1+$B$7)^(J66-1) -> 46171.962 | L66: =$B$5*MAX(0,K66-$B$6) -> 1698.9266 | M66: =P65 -> 0 | N66: =MIN(L66,M66) -> 0 | O66: =N66/(1+$B$8)^J66 -> 0 | P66: =M66-N66 -> 0
K67: =$E$4*(1+$B$7)^(J67-1) -> 25490.196 | L67: =$B$5*MAX(0,K67-$B$6) -> 0 | M67: =P66 -> 0 | N67: =MIN(L67,M67) -> 0 | O67: =N67/(1+$B$8)^J67 -> 0 | P67: =M67-N67 -> 0
P68: =M68-N68 -> 0
J70: Repayment schedule with an income of 32000 pounds
J71: Year | K71: Income | L71: raw repayment | M71: Opening balance | N71: actual repayment | O71: discounted payment | P71: Closing balance
J72: 1 | K72: =$E$5*(1+$B$7)^(J72-1) -> 32000 | L72: =$B$5*MAX(0,K72-$B$6) -> 423.45 | M72: =$B$3 -> 9250 | N72: =MIN(L72,M72) -> 423.45 | O72: =N72/(1+$B$8)^J72 -> 411.1165 | P72: =M72-N72 -> 8826.55
J73: =J72+1 -> 2 | K73: =$E$5*(1+$B$7)^(J73-1) -> 32640 | L73: =$B$5*MAX(0,K73-$B$6) -> 481.05 | M73: =P72 -> 8826.55 | N73: =MIN(L73,M73) -> 481.05 | O73: =N73/(1+$B$8)^J73 -> 453.43576 | P73: =M73-N73 -> 8345.5
J74: =J73+1 -> 3 | K74: =$E$5*(1+$B$7)^(J74-1) -> 33292.8 | L74: =$B$5*MAX(0,K74-$B$6) -> 539.802 | M74: =P73 -> 8345.5 | N74: =MIN(L74,M74) -> 539.802 | O74: =N74/(1+$B$8)^J74 -> 493.9953 | P74: =M74-N74 -> 7805.698
J75: =J74+1 -> 4 | K75: =$E$5*(1+$B$7)^(J75-1) -> 33958.656 | L75: =$B$5*MAX(0,K75-$B$6) -> 599.72904 | M75: =P74 -> 7805.698 | N75: =MIN(L75,M75) -> 599.72904 | O75: =N75/(1+$B$8)^J75 -> 532.85148 | P75: =M75-N75 -> 7205.969
J76: =J75+1 -> 5 | K76: =$E$5*(1+$B$7)^(J76-1) -> 34637.829 | L76: =$B$5*MAX(0,K76-$B$6) -> 660.85462 | M76: =P75 -> 7205.969 | N76: =MIN(L76,M76) -> 660.85462 | O76: =N76/(1+$B$8)^J76 -> 570.059 | P76: =M76-N76 -> 6545.1143
J77: =J76+1 -> 6 | K77: =$E$5*(1+$B$7)^(J77-1) -> 35330.586 | L77: =$B$5*MAX(0,K77-$B$6) -> 723.20271 | M77: =P76 -> 6545.1143 | N77: =MIN(L77,M77) -> 723.20271 | O77: =N77/(1+$B$8)^J77 -> 605.67089 | P77: =M77-N77 -> 5821.9116
J78: =J77+1 -> 7 | K78: =$E$5*(1+$B$7)^(J78-1) -> 36037.197 | L78: =$B$5*MAX(0,K78-$B$6) -> 786.79777 | M78: =P77 -> 5821.9116 | N78: =MIN(L78,M78) -> 786.79777 | O78: =N78/(1+$B$8)^J78 -> 639.73859 | P78: =M78-N78 -> 5035.1139
J79: =J78+1 -> 8 | K79: =$E$5*(1+$B$7)^(J79-1) -> 36757.941 | L79: =$B$5*MAX(0,K79-$B$6) -> 851.66472 | M79: =P78 -> 5035.1139 | N79: =MIN(L79,M79) -> 851.66472 | O79: =N79/(1+$B$8)^J79 -> 672.312 | P79: =M79-N79 -> 4183.4491
J80: =J79+1 -> 9 | K80: =$E$5*(1+$B$7)^(J80-1) -> 37493.1 | L80: =$B$5*MAX(0,K80-$B$6) -> 917.82902 | M80: =P79 -> 4183.4491 | N80: =MIN(L80,M80) -> 917.82902 | O80: =N80/(1+$B$8)^J80 -> 703.43952 | P80: =M80-N80 -> 3265.6201
J81: =J80+1 -> 10 | K81: =$E$5*(1+$B$7)^(J81-1) -> 38242.962 | L81: =$B$5*MAX(0,K81-$B$6) -> 985.3166 | M81: =P80 -> 3265.6201 | N81: =MIN(L81,M81) -> 985.3166 | O81: =N81/(1+$B$8)^J81 -> 733.16808 | P81: =M81-N81 -> 2280.3035
J82: =J81+1 -> 11 | K82: =$E$5*(1+$B$7)^(J82-1) -> 39007.821 | L82: =$B$5*MAX(0,K82-$B$6) -> 1054.1539 | M82: =P81 -> 2280.3035 | N82: =MIN(L82,M82) -> 1054.1539 | O82: =N82/(1+$B$8)^J82 -> 761.54323 | P82: =M82-N82 -> 1226.1496
J83: =J82+1 -> 12 | K83: =$E$5*(1+$B$7)^(J83-1) -> 39787.978 | L83: =$B$5*MAX(0,K83-$B$6) -> 1124.368 | M83: =P82 -> 1226.1496 | N83: =MIN(L83,M83) -> 1124.368 | O83: =N83/(1+$B$8)^J83 -> 788.6091 | P83: =M83-N83 -> 101.78158
J84: =J83+1 -> 13 | K84: =$E$5*(1+$B$7)^(J84-1) -> 40583.737 | L84: =$B$5*MAX(0,K84-$B$6) -> 1195.9864 | M84: =P83 -> 101.78158 | N84: =MIN(L84,M84) -> 101.78158 | O84: =N84/(1+$B$8)^J84 -> 69.308305 | P84: =M84-N84 -> 0
... J101: =J100+1 -> 30 | K101: =$E$5*(1+$B$7)^(J101-1) -> 56827.03 | L101: =$B$5*MAX(0,K101-$B$6) -> 2657.8827 | M101: =P100 -> 0 | N101: =MIN(L101,M101) -> 0 | O101: =N101/(1+$B$8)^J101 -> 0 | P101: =M101-N101 -> 0
K102: =$E$5*(1+$B$7)^(J102-1) -> 31372.549 | L102: =$B$5*MAX(0,K102-$B$6) -> 366.97941 | M102: =P101 -> 0 | N102: =MIN(L102,M102) -> 0 | O102: =N102/(1+$B$8)^J102 -> 0 | P102: =M102-N102 -> 0
P103: =M103-N103 -> 0
J105: Repayment schedule with an income of 35000 pounds
J106: Year | K106: Income | L106: raw repayment | M106: Opening balance | N106: actual repayment | O106: discounted payment | P106: Closing balance
J107: 1 | K107: =$E$6*(1+$B$7)^(J107-1) -> 35000 | L107: =$B$5*MAX(0,K107-$B$6) -> 693.45 | M107: =$B$3 -> 9250 | N107: =MIN(L107,M107) -> 693.45 | O107: =N107/(1+$B$8)^J107 -> 673.25243 | P107: =M107-N107 -> 8556.55
J108: =J107+1 -> 2 | K108: =$E$6*(1+$B$7)^(J108-1) -> 35700 | L108: =$B$5*MAX(0,K108-$B$6) -> 756.45 | M108: =P107 -> 8556.55 | N108: =MIN(L108,M108) -> 756.45 | O108: =N108/(1+$B$8)^J108 -> 713.02668 | P108: =M108-N108 -> 7800.1
J109: =J108+1 -> 3 | K109: =$E$6*(1+$B$7)^(J109-1) -> 36414 | L109: =$B$5*MAX(0,K109-$B$6) -> 820.71 | M109: =P108 -> 7800.1 | N109: =MIN(L109,M109) -> 820.71 | O109: =N109/(1+$B$8)^J109 -> 751.06591 | P109: =M109-N109 -> 6979.39
J110: =J109+1 -> 4 | K110: =$E$6*(1+$B$7)^(J110-1) -> 37142.28 | L110: =$B$5*MAX(0,K110-$B$6) -> 886.2552 | M110: =P109 -> 6979.39 | N110: =MIN(L110,M110) -> 886.2552 | O110: =N110/(1+$B$8)^J110 -> 787.42627 | P110: =M110-N110 -> 6093.1348
J111: =J110+1 -> 5 | K111: =$E$6*(1+$B$7)^(J111-1) -> 37885.126 | L111: =$B$5*MAX(0,K111-$B$6) -> 953.1113 | M111: =P110 -> 6093.1348 | N111: =MIN(L111,M111) -> 953.1113 | O111: =N111/(1+$B$8)^J111 -> 822.16218 | P111: =M111-N111 -> 5140.0235
J112: =J111+1 -> 6 | K112: =$E$6*(1+$B$7)^(J112-1) -> 38642.828 | L112: =$B$5*MAX(0,K112-$B$6) -> 1021.3045 | M112: =P111 -> 5140.0235 | N112: =MIN(L112,M112) -> 1021.3045 | O112: =N112/(1+$B$8)^J112 -> 855.32647 | P112: =M112-N112 -> 4118.719
J113: =J112+1 -> 7 | K113: =$E$6*(1+$B$7)^(J113-1) -> 39415.685 | L113: =$B$5*MAX(0,K113-$B$6) -> 1090.8616 | M113: =P112 -> 4118.719 | N113: =MIN(L113,M113) -> 1090.8616 | O113: =N113/(1+$B$8)^J113 -> 886.97032 | P113: =M113-N113 -> 3027.8573
J114: =J113+1 -> 8 | K114: =$E$6*(1+$B$7)^(J114-1) -> 40203.998 | L114: =$B$5*MAX(0,K114-$B$6) -> 1161.8099 | M114: =P113 -> 3027.8573 | N114: =MIN(L114,M114) -> 1161.8099 | O114: =N114/(1+$B$8)^J114 -> 917.14343 | P114: =M114-N114 -> 1866.0475
J115: =J114+1 -> 9 | K115: =$E$6*(1+$B$7)^(J115-1) -> 41008.078 | L115: =$B$5*MAX(0,K115-$B$6) -> 1234.1771 | M115: =P114 -> 1866.0475 | N115: =MIN(L115,M115) -> 1234.1771 | O115: =N115/(1+$B$8)^J115 -> 945.89394 | P115: =M115-N115 -> 631.87044
J116: =J115+1 -> 10 | K116: =$E$6*(1+$B$7)^(J116-1) -> 41828.24 | L116: =$B$5*MAX(0,K116-$B$6) -> 1307.9916 | M116: =P115 -> 631.87044 | N116: =MIN(L116,M116) -> 631.87044 | O116: =N116/(1+$B$8)^J116 -> 470.17095 | P116: =M116-N116 -> 0
J117: =J116+1 -> 11 | K117: =$E$6*(1+$B$7)^(J117-1) -> 42664.805 | L117: =$B$5*MAX(0,K117-$B$6) -> 1383.2824 | M117: =P116 -> 0 | N117: =MIN(L117,M117) -> 0 | O117: =N117/(1+$B$8)^J117 -> 0 | P117: =M117-N117 -> 0
J118: =J117+1 -> 12 | K118: =$E$6*(1+$B$7)^(J118-1) -> 43518.101 | L118: =$B$5*MAX(0,K118-$B$6) -> 1460.0791 | M118: =P117 -> 0 | N118: =MIN(L118,M118) -> 0 | O118: =N118/(1+$B$8)^J118 -> 0 | P118: =M118-N118 -> 0
J119: =J118+1 -> 13 | K119: =$E$6*(1+$B$7)^(J119-1) -> 44388.463 | L119: =$B$5*MAX(0,K119-$B$6) -> 1538.4117 | M119: =P118 -> 0 | N119: =MIN(L119,M119) -> 0 | O119: =N119/(1+$B$8)^J119 -> 0 | P119: =M119-N119 -> 0
... J136: =J135+1 -> 30 | K136: =$E$6*(1+$B$7)^(J136-1) -> 62154.564 | L136: =$B$5*MAX(0,K136-$B$6) -> 3137.3608 | M136: =P135 -> 0 | N136: =MIN(L136,M136) -> 0 | O136: =N136/(1+$B$8)^J136 -> 0 | P136: =M136-N136 -> 0
K137: =$E$6*(1+$B$7)^(J137-1) -> 34313.725 | L137: =$B$5*MAX(0,K137-$B$6) -> 631.68529 | M137: =P136 -> 0 | N137: =MIN(L137,M137) -> 0 | O137: =N137/(1+$B$8)^J137 -> 0 | P137: =M137-N137 -> 0
P138: =M138-N138 -> 0
J140: Repayment schedule with an income of 35000 pounds
J141: Year | K141: Income | L141: raw repayment | M141: Opening balance | N141: actual repayment | O141: discounted payment | P141: Closing balance
J142: 1 | K142: =$E$7*(1+$B$7)^(J142-1) -> 42000 | L142: =$B$5*MAX(0,K142-$B$6) -> 1323.45 | M142: =$B$3 -> 9250 | N142: =MIN(L142,M142) -> 1323.45 | O142: =N142/(1+$B$8)^J142 -> 1284.9029 | P142: =M142-N142 -> 7926.55
J143: =J142+1 -> 2 | K143: =$E$7*(1+$B$7)^(J143-1) -> 42840 | L143: =$B$5*MAX(0,K143-$B$6) -> 1399.05 | M143: =P142 -> 7926.55 | N143: =MIN(L143,M143) -> 1399.05 | O143: =N143/(1+$B$8)^J143 -> 1318.7388 | P143: =M143-N143 -> 6527.5
J144: =J143+1 -> 3 | K144: =$E$7*(1+$B$7)^(J144-1) -> 43696.8 | L144: =$B$5*MAX(0,K144-$B$6) -> 1476.162 | M144: =P143 -> 6527.5 | N144: =MIN(L144,M144) -> 1476.162 | O144: =N144/(1+$B$8)^J144 -> 1350.8973 | P144: =M144-N144 -> 5051.338
J145: =J144+1 -> 4 | K145: =$E$7*(1+$B$7)^(J145-1) -> 44570.736 | L145: =$B$5*MAX(0,K145-$B$6) -> 1554.8162 | M145: =P144 -> 5051.338 | N145: =MIN(L145,M145) -> 1554.8162 | O145: =N145/(1+$B$8)^J145 -> 1381.4341 | P145: =M145-N145 -> 3496.5218
J146: =J145+1 -> 5 | K146: =$E$7*(1+$B$7)^(J146-1) -> 45462.151 | L146: =$B$5*MAX(0,K146-$B$6) -> 1635.0436 | M146: =P145 -> 3496.5218 | N146: =MIN(L146,M146) -> 1635.0436 | O146: =N146/(1+$B$8)^J146 -> 1410.4029 | P146: =M146-N146 -> 1861.4782
J147: =J146+1 -> 6 | K147: =$E$7*(1+$B$7)^(J147-1) -> 46371.394 | L147: =$B$5*MAX(0,K147-$B$6) -> 1716.8754 | M147: =P146 -> 1861.4782 | N147: =MIN(L147,M147) -> 1716.8754 | O147: =N147/(1+$B$8)^J147 -> 1437.8561 | P147: =M147-N147 -> 144.60276
J148: =J147+1 -> 7 | K148: =$E$7*(1+$B$7)^(J148-1) -> 47298.822 | L148: =$B$5*MAX(0,K148-$B$6) -> 1800.3439 | M148: =P147 -> 144.60276 | N148: =MIN(L148,M148) -> 144.60276 | O148: =N148/(1+$B$8)^J148 -> 117.57528 | P148: =M148-N148 -> 0
J149: =J148+1 -> 8 | K149: =$E$7*(1+$B$7)^(J149-1) -> 48244.798 | L149: =$B$5*MAX(0,K149-$B$6) -> 1885.4818 | M149: =P148 -> 0 | N149: =MIN(L149,M149) -> 0 | O149: =N149/(1+$B$8)^J149 -> 0 | P149: =M149-N149 -> 0
J150: =J149+1 -> 9 | K150: =$E$7*(1+$B$7)^(J150-1) -> 49209.694 | L150: =$B$5*MAX(0,K150-$B$6) -> 1972.3225 | M150: =P149 -> 0 | N150: =MIN(L150,M150) -> 0 | O150: =N150/(1+$B$8)^J150 -> 0 | P150: =M150-N150 -> 0
J151: =J150+1 -> 10 | K151: =$E$7*(1+$B$7)^(J151-1) -> 50193.888 | L151: =$B$5*MAX(0,K151-$B$6) -> 2060.8999 | M151: =P150 -> 0 | N151: =MIN(L151,M151) -> 0 | O151: =N151/(1+$B$8)^J151 -> 0 | P151: =M151-N151 -> 0
J152: =J151+1 -> 11 | K152: =$E$7*(1+$B$7)^(J152-1) -> 51197.766 | L152: =$B$5*MAX(0,K152-$B$6) -> 2151.2489 | M152: =P151 -> 0 | N152: =MIN(L152,M152) -> 0 | O152: =N152/(1+$B$8)^J152 -> 0 | P152: =M152-N152 -> 0
J153: =J152+1 -> 12 | K153: =$E$7*(1+$B$7)^(J153-1) -> 52221.721 | L153: =$B$5*MAX(0,K153-$B$6) -> 2243.4049 | M153: =P152 -> 0 | N153: =MIN(L153,M153) -> 0 | O153: =N153/(1+$B$8)^J153 -> 0 | P153: =M153-N153 -> 0
J154: =J153+1 -> 13 | K154: =$E$7*(1+$B$7)^(J154-1) -> 53266.155 | L154: =$B$5*MAX(0,K154-$B$6) -> 2337.404 | M154: =P153 -> 0 | N154: =MIN(L154,M154) -> 0 | O154: =N154/(1+$B$8)^J154 -> 0 | P154: =M154-N154 -> 0
... J171: =J170+1 -> 30 | K171: =$E$7*(1+$B$7)^(J171-1) -> 74585.477 | L171: =$B$5*MAX(0,K171-$B$6) -> 4256.1429 | M171: =P170 -> 0 | N171: =MIN(L171,M171) -> 0 | O171: =N171/(1+$B$8)^J171 -> 0 | P171: =M171-N171 -> 0
K172: =$E$7*(1+$B$7)^(J172-1) -> 41176.471 | L172: =$B$5*MAX(0,K172-$B$6) -> 1249.3324 | M172: =P171 -> 0 | N172: =MIN(L172,M172) -> 0 | O172: =N172/(1+$B$8)^J172 -> 0 | P172: =M172-N172 -> 0
P173: =M173-N173 -> 0
J175: Repayment schedule with an income of 50000 pounds
J176: Year | K176: Income | L176: raw repayment | M176: Opening balance | N176: actual repayment | O176: discounted payment | P176: Closing balance
J177: 1 | K177: =$E$8*(1+$B$7)^(J177-1) -> 50000 | L177: =$B$5*MAX(0,K177-$B$6) -> 2043.45 | M177: =$B$3 -> 9250 | N177: =MIN(L177,M177) -> 2043.45 | O177: =N177/(1+$B$8)^J177 -> 1983.932 | P177: =M177-N177 -> 7206.55
J178: =J177+1 -> 2 | K178: =$E$8*(1+$B$7)^(J178-1) -> 51000 | L178: =$B$5*MAX(0,K178-$B$6) -> 2133.45 | M178: =P177 -> 7206.55 | N178: =MIN(L178,M178) -> 2133.45 | O178: =N178/(1+$B$8)^J178 -> 2010.9812 | P178: =M178-N178 -> 5073.1
...

Sheet Country_PV
A1: Starting parameters | D1: Country | E1: Wage_EURO | F1: wage_gbp | G1: PV_loan | H1: k_i | I1: k_i from R | V1: Repayment schedule for Belgium
A2: L | B2: 9250 | D2: Belgium | E2: 59632 | F2: =E2*$B$4 -> 51283.52 | G2: =MAX(SUM(AA3:AA32),1) -> 8579.3385 | H2: =LN($B$3)-LN(G2) -> 0.95073548 | I2: 0.95073548 | V2: Year | W2: Income | X2: raw repayment | Y2: Opening balance | Z2: actual repayment | AA2: discounted payment | AB2: Closing balance
A3: Ppost | B3: 22200 | D3: Bulgaria | E3: 15387 | F3: =E3*$B$4 -> 13232.82 | G3: =MAX(SUM(P37:P66),1) -> 1 | H3: =LN($B$3)-LN(G3) -> 10.007848 | I3: 10.007848 | V3: 1 | W3: =$F$2*(1+$B$7)^(V3-1) -> 51283.52 | X3: =$B$5*MAX(0,W3-$B$6) -> 2158.9668 | Y3: =$B$2 -> 9250 | Z3: =MIN(X3,Y3) -> 2158.9668 | AA3: =Z3/(1+$B$8)^V3 -> 2096.0843 | AB3: =Y3-Z3 -> 7091.0332
A4: eur_gbp | B4: 0.86 | D4: Czechia | E4: 23998 | F4: =E4*$B$4 -> 20638.28 | G4: =MAX(SUM(P71:P100),1) -> 3021.0957 | H4: =LN($B$3)-LN(G4) -> 1.9944727 | I4: 1.9944727 | V4: =V3+1 -> 2 | W4: =$F$2*(1+$B$7)^(V4-1) -> 52309.19 | X4: =$B$5*MAX(0,W4-$B$6) -> 2251.2771 | Y4: =AB3 -> 7091.0332 | Z4: =IF(Y4<=0,0,MIN(X4,Y4)) -> 2251.2771 | AA4: =Z4/(1+$B$8)^V4 -> 2122.0446 | AB4: =MAX(0,Y4-Z4) -> 4839.7561
A5: alpha | B5: 0.09 | D5: Denmark | E5: 71565 | F5: =E5*$B$4 -> 61545.9 | G5: =MAX(SUM(X37:X66),1) -> 8724.5305 | H5: =LN($B$3)-LN(G5) -> 0.93395363 | I5: 0.93395363 | V5: =V4+1 -> 3 | W5: =$F$2*(1+$B$7)^(V5-1) -> 53355.374 | X5: =$B$5*MAX(0,W5-$B$6) -> 2345.4337 | Y5: =AB4 -> 4839.7561 | Z5: =IF(Y5<=0,0,MIN(X5,Y5)) -> 2345.4337 | AA5: =Z5/(1+$B$8)^V5 -> 2146.4041 | AB5: =MAX(0,Y5-Z5) -> 2494.3224
A6: tau | B6: 27295 | D6: Germany | E6: 53791 | F6: =E6*$B$4 -> 46260.26 | G6: =MAX(SUM(AF37:AF66),1) -> 8456.3829 | H6: =LN($B$3)-LN(G6) -> 0.96517076 | I6: 0.96517076 | V6: =V5+1 -> 4 | W6: =$F$2*(1+$B$7)^(V6-1) -> 54422.482 | X6: =$B$5*MAX(0,W6-$B$6) -> 2441.4734 | Y6: =AB5 -> 2494.3224 | Z6: =IF(Y6<=0,0,MIN(X6,Y6)) -> 2441.4734 | AA6: =Z6/(1+$B$8)^V6 -> 2169.2175 | AB6: =MAX(0,Y6-Z6) -> 52.849033
A7: g | B7: 0.02 | D7: Estonia | E7: 26546 | F7: =E7*$B$4 -> 22829.56 | G7: =MAX(SUM(AN37:AN66),1) -> 4804.714 | H7: =LN($B$3)-LN(G7) -> 1.5304948 | I7: 1.5304948 | V7: =V6+1 -> 5 | W7: =$F$2*(1+$B$7)^(V7-1) -> 55510.931 | X7: =$B$5*MAX(0,W7-$B$6) -> 2539.4338 | Y7: =AB6 -> 52.849033 | Z7: =IF(Y7<=0,0,MIN(X7,Y7)) -> 52.849033 | AA7: =Z7/(1+$B$8)^V7 -> 45.58804 | AB7: =MAX(0,Y7-Z7) -> 0
A8: r | B8: 0.03 | D8: Ireland | E8: 61051 | F8: =E8*$B$4 -> 52503.86 | G8: N/a | H8: N/a | V8: =V7+1 -> 6 | W8: =$F$2*(1+$B$7)^(V8-1) -> 56621.15 | X8: =$B$5*MAX(0,W8-$B$6) -> 2639.3535 | Y8: =AB7 -> 0 | Z8: =IF(Y8<=0,0,MIN(X8,Y8)) -> 0 | AA8: =Z8/(1+$B$8)^V8 -> 0 | AB8: =MAX(0,Y8-Z8) -> 0
A9: T | B9: 30 | D9: Greece | E9: 17954 | F9: =E9*$B$4 -> 15440.44 | G9: =MAX(SUM(X71:X100),1) -> 4.6283026 | H9: =LN($B$3)-LN(G9) -> 8.4756574 | I9: 8.4756574 | V9: =V8+1 -> 7 | W9: =$F$2*(1+$B$7)^(V9-1) -> 57753.573 | X9: =$B$5*MAX(0,W9-$B$6) -> 2741.2716 | Y9: =AB8 -> 0 | Z9: =IF(Y9<=0,0,MIN(X9,Y9)) -> 0 | AA9: =Z9/(1+$B$8)^V9 -> 0 | AB9: =MAX(0,Y9-Z9) -> 0
D10: Spain | E10: 33700 | F10: =E10*$B$4 -> 28982 | G10: =MAX(SUM(AF71:AF100),1) -> 6801.1286 | H10: =LN($B$3)-LN(G10) -> 1.1830037 | I10: 1.1830037 | V10: =V9+1 -> 8 | W10: =$F$2*(1+$B$7)^(V10-1) -> 58908.644 | X10: =$B$5*MAX(0,W10-$B$6) -> 2845.228 | Y10: =AB9 -> 0 | Z10: =IF(Y10<=0,0,MIN(X10,Y10)) -> 0 | AA10: =Z10/(1+$B$8)^V10 -> 0 | AB10: =MAX(0,Y10-Z10) -> 0
D11: France | E11: 43790 | F11: =E11*$B$4 -> 37659.4 | G11: =MAX(SUM(AN71:AN100),1) -> 8054.806 | H11: =LN($B$3)-LN(G11) -> 1.0138234 | I11: 1.0138234 | V11: =V10+1 -> 9 | W11: =$F$2*(1+$B$7)^(V11-1) -> 60086.817 | X11: =$B$5*MAX(0,W11-$B$6) -> 2951.2636 | Y11: =AB10 -> 0 | Z11: =IF(Y11<=0,0,MIN(X11,Y11)) -> 0 | AA11: =Z11/(1+$B$8)^V11 -> 0 | AB11: =MAX(0,Y11-Z11) -> 0
D12: Croatia | E12: 23446 | F12: =E12*$B$4 -> 20163.56 | G12: =MAX(SUM(P105:P134),1) -> 2527.4656 | H12: =LN($B$3)-LN(G12) -> 2.1728752 | I12: 2.1728752 | V12: =V11+1 -> 10 | W12: =$F$2*(1+$B$7)^(V12-1) -> 61288.554 | X12: =$B$5*MAX(0,W12-$B$6) -> 3059.4198 | Y12: =AB11 -> 0 | Z12: =IF(Y12<=0,0,MIN(X12,Y12)) -> 0 | AA12: =Z12/(1+$B$8)^V12 -> 0 | AB12: =MAX(0,Y12-Z12) -> 0
D13: Italy | E13: 33523 | F13: =E13*$B$4 -> 28829.78 | G13: =MAX(SUM(X105:X134),1) -> 6758.7787 | H13: =LN($B$3)-LN(G13) -> 1.1892501 | I13: 1.1892501 | V13: =V12+1 -> 11 | W13: =$F$2*(1+$B$7)^(V13-1) -> 62514.325 | X13: =$B$5*MAX(0,W13-$B$6) -> 3169.7392 | Y13: =AB12 -> 0 | Z13: =IF(Y13<=0,0,MIN(X13,Y13)) -> 0 | AA13: =Z13/(1+$B$8)^V13 -> 0 | AB13: =MAX(0,Y13-Z13) -> 0
D14: Cyprus | E14: 27611 | F14: =E14*$B$4 -> 23745.46 | G14: =MAX(SUM(AF105:AF134),1) -> 5095.4373 | H14: =LN($B$3)-LN(G14) -> 1.4717468 | I14: 1.4717468 | V14: =V13+1 -> 12 | W14: =$F$2*(1+$B$7)^(V14-1) -> 63764.611 | X14: =$B$5*MAX(0,W14-$B$6) -> 3282.265 | Y14: =AB13 -> 0 | Z14: =IF(Y14<=0,0,MIN(X14,Y14)) -> 0 | AA14: =Z14/(1+$B$8)^V14 -> 0 | AB14: =MAX(0,Y14-Z14) -> 0
D15: Latvia | E15: 22262 | F15: =E15*$B$4 -> 19145.32 | G15: =MAX(SUM(AN105:AN134),1) -> 1607.4555 | H15: =LN($B$3)-LN(G15) -> 2.6254398 | I15: 2.6254398 | V15: =V14+1 -> 13 | W15: =$F$2*(1+$B$7)^(V15-1) -> 65039.903 | X15: =$B$5*MAX(0,W15-$B$6) -> 3397.0413 | Y15: =AB14 -> 0 | Z15: =IF(Y15<=0,0,MIN(X15,Y15)) -> 0 | AA15: =Z15/(1+$B$8)^V15 -> 0 | AB15: =MAX(0,Y15-Z15) -> 0
D16: Lithuania | E16: 29104 | F16: =E16*$B$4 -> 25029.44 | G16: =MAX(SUM(P139:P168),1) -> 5513.5374 | H16: =LN($B$3)-LN(G16) -> 1.3928859 | I16: 1.3928859 | V16: =V15+1 -> 14 | W16: =$F$2*(1+$B$7)^(V16-1) -> 66340.702 | X16: =$B$5*MAX(0,W16-$B$6) -> 3514.1131 | Y16: =AB15 -> 0 | Z16: =IF(Y16<=0,0,MIN(X16,Y16)) -> 0 | AA16: =Z16/(1+$B$8)^V16 -> 0 | AB16: =MAX(0,Y16-Z16) -> 0
D17: Luxembourg | E17: 82969 | F17: =E17*$B$4 -> 71353.34 | G17: =MAX(SUM(X139:X168),1) -> 8798.4413 | H17: =LN($B$3)-LN(G17) -> 0.92551771 | I17: 0.92551771 | V17: =V16+1 -> 15 | W17: =$F$2*(1+$B$7)^(V17-1) -> 67667.516 | X17: =$B$5*MAX(0,W17-$B$6) -> 3633.5264 | Y17: =AB16 -> 0 | Z17: =IF(Y17<=0,0,MIN(X17,Y17)) -> 0 | AA17: =Z17/(1+$B$8)^V17 -> 0 | AB17: =MAX(0,Y17-Z17) -> 0
D18: Hungary | E18: 18461 | F18: =E18*$B$4 -> 15876.46 | G18: =MAX(SUM(AF139:AF168),1) -> 46.564213 | H18: =LN($B$3)-LN(G18) -> 6.1670153 | I18: 6.1670153 | V18: =V17+1 -> 16 | W18: =$F$2*(1+$B$7)^(V18-1) -> 69020.866 | X18: =$B$5*MAX(0,W18-$B$6) -> 3755.3279 | Y18: =AB17 -> 0 | Z18: =IF(Y18<=0,0,MIN(X18,Y18)) -> 0 | AA18: =Z18/(1+$B$8)^V18 -> 0 | AB18: =MAX(0,Y18-Z18) -> 0
D19: Malta | E19: 33499 | F19: =E19*$B$4 -> 28809.14 | G19: =MAX(SUM(AN139:AN168),1) -> 6752.8799 | H19: =LN($B$3)-LN(G19) -> 1.1901232 | I19: 1.1901232 | V19: =V18+1 -> 17 | W19: =$F$2*(1+$B$7)^(V19-1) -> 70401.283 | X19: =$B$5*MAX(0,W19-$B$6) -> 3879.5655 | Y19: =AB18 -> 0 | Z19: =IF(Y19<=0,0,MIN(X19,Y19)) -> 0 | AA19: =Z19/(1+$B$8)^V19 -> 0 | AB19: =MAX(0,Y19-Z19) -> 0
D20: Austria | E20: 58600 | F20: =E20*$B$4 -> 50396 | G20: =MAX(SUM(P173:P202),1) -> 8557.6144 | H20: =LN($B$3)-LN(G20) -> 0.95327083 | I20: 0.95327083 | V20: =V19+1 -> 18 | W20: =$F$2*(1+$B$7)^(V20-1) -> 71809.309 | X20: =$B$5*MAX(0,W20-$B$6) -> 4006.2878 | Y20: =AB19 -> 0 | Z20: =IF(Y20<=0,0,MIN(X20,Y20)) -> 0 | AA20: =Z20/(1+$B$8)^V20 -> 0 | AB20: =MAX(0,Y20-Z20) -> 0
D21: Poland | E21: 21246 | F21: =E21*$B$4 -> 18271.56 | G21: =MAX(SUM(X173:X202),1) -> 980.81535 | H21: =LN($B$3)-LN(G21) -> 3.1194633 | I21: 3.1194633 | V21: =V20+1 -> 19 | W21: =$F$2*(1+$B$7)^(V21-1) -> 73245.495 | X21: =$B$5*MAX(0,W21-$B$6) -> 4135.5446 | Y21: =AB20 -> 0 | Z21: =IF(Y21<=0,0,MIN(X21,Y21)) -> 0 | AA21: =Z21/(1+$B$8)^V21 -> 0 | AB21: =MAX(0,Y21-Z21) -> 0
D22: Portugal | E22: 24818 | F22: =E22*$B$4 -> 21343.48 | G22: =MAX(SUM(P241:P270),1) -> 3836.3558 | H22: =LN($B$3)-LN(G22) -> 1.7555694 | I22: 1.7555694 | V22: =V21+1 -> 20 | W22: =$F$2*(1+$B$7)^(V22-1) -> 74710.405 | X22: =$B$5*MAX(0,W22-$B$6) -> 4267.3864 | Y22: =AB21 -> 0 | Z22: =IF(Y22<=0,0,MIN(X22,Y22)) -> 0 | AA22: =Z22/(1+$B$8)^V22 -> 0 | AB22: =MAX(0,Y22-Z22) -> 0
D23: Romania | E23: 21108 | F23: =E23*$B$4 -> 18152.88 | G23: =MAX(SUM(AN173:AN202),1) -> 907.66157 | H23: =LN($B$3)-LN(G23) -> 3.196976 | I23: 3.196976 | V23: =V22+1 -> 21 | W23: =$F$2*(1+$B$7)^(V23-1) -> 76204.613 | X23: =$B$5*MAX(0,W23-$B$6) -> 4401.8652 | Y23: =AB22 -> 0 | Z23: =IF(Y23<=0,0,MIN(X23,Y23)) -> 0 | AA23: =Z23/(1+$B$8)^V23 -> 0 | AB23: =MAX(0,Y23-Z23) -> 0
D24: Slovenia | E24: 35133 | F24: =E24*$B$4 -> 30214.38 | G24: =MAX(SUM(P207:P236),1) -> 7098.4662 | H24: =LN($B$3)-LN(G24) -> 1.1402136 | I24: 1.1402136 | V24: =V23+1 -> 22 | W24: =$F$2*(1+$B$7)^(V24-1) -> 77728.705 | X24: =$B$5*MAX(0,W24-$B$6) -> 4539.0335 | Y24: =AB23 -> 0 | Z24: =IF(Y24<=0,0,MIN(X24,Y24)) -> 0 | AA24: =Z24/(1+$B$8)^V24 -> 0 | AB24: =MAX(0,Y24-Z24) -> 0
D25: Slovakia | E25: 20287 | F25: =E25*$B$4 -> 17446.82 | G25: =MAX(SUM(X207:X236),1) -> 527.15205 | H25: =LN($B$3)-LN(G25) -> 3.7403585 | I25: 3.7403585 | V25: =V24+1 -> 23 | W25: =$F$2*(1+$B$7)^(V25-1) -> 79283.279 | X25: =$B$5*MAX(0,W25-$B$6) -> 4678.9451 | Y25: =AB24 -> 0 | Z25: =IF(Y25<=0,0,MIN(X25,Y25)) -> 0 | AA25: =Z25/(1+$B$8)^V25 -> 0 | AB25: =MAX(0,Y25-Z25) -> 0
D26: Finland | E26: 49428 | F26: =E26*$B$4 -> 42508.08 | G26: =MAX(SUM(AF207:AF236),1) -> 8323.75 | H26: =LN($B$3)-LN(G26) -> 0.98097942 | I26: 0.98097942 | V26: =V25+1 -> 24 | W26: =$F$2*(1+$B$7)^(V26-1) -> 80868.945 | X26: =$B$5*MAX(0,W26-$B$6) -> 4821.655 | Y26: =AB25 -> 0 | Z26: =IF(Y26<=0,0,MIN(X26,Y26)) -> 0 | AA26: =Z26/(1+$B$8)^V26 -> 0 | AB26: =MAX(0,Y26-Z26) -> 0
D27: Sweden | E27: 46525 | F27: =E27*$B$4 -> 40011.5 | G27: =MAX(SUM(AN207:AN236),1) -> 8202.1973 | H27: =LN($B$3)-LN(G27) -> 0.99569021 | I27: 0.99569021 | V27: =V26+1 -> 25 | W27: =$F$2*(1+$B$7)^(V27-1) -> 82486.324 | X27: =$B$5*MAX(0,W27-$B$6) -> 4967.2191 | Y27: =AB26 -> 0 | Z27: =IF(Y27<=0,0,MIN(X27,Y27)) -> 0 | AA27: =Z27/(1+$B$8)^V27 -> 0 | AB27: =MAX(0,Y27-Z27) -> 0
V28: =V27+1 -> 26 | W28: =$F$2*(1+$B$7)^(V28-1) -> 84136.05 | X28: =$B$5*MAX(0,W28-$B$6) -> 5115.6945 | Y28: =AB27 -> 0 | Z28: =IF(Y28<=0,0,MIN(X28,Y28)) -> 0 | AA28: =Z28/(1+$B$8)^V28 -> 0 | AB28: =MAX(0,Y28-Z28) -> 0
V29: =V28+1 -> 27 | W29: =$F$2*(1+$B$7)^(V29-1) -> 85818.771 | X29: =$B$5*MAX(0,W29-$B$6) -> 5267.1394 | Y29: =AB28 -> 0 | Z29: =IF(Y29<=0,0,MIN(X29,Y29)) -> 0 | AA29: =Z29/(1+$B$8)^V29 -> 0 | AB29: =MAX(0,Y29-Z29) -> 0
V30: =V29+1 -> 28 | W30: =$F$2*(1+$B$7)^(V30-1) -> 87535.147 | X30: =$B$5*MAX(0,W30-$B$6) -> 5421.6132 | Y30: =AB29 -> 0 | Z30: =IF(Y30<=0,0,MIN(X30,Y30)) -> 0 | AA30: =Z30/(1+$B$8)^V30 -> 0 | AB30: =MAX(0,Y30-Z30) -> 0
V31: =V30+1 -> 29 | W31: =$F$2*(1+$B$7)^(V31-1) -> 89285.85 | X31: =$B$5*MAX(0,W31-$B$6) -> 5579.1765 | Y31: =AB30 -> 0 | Z31: =IF(Y31<=0,0,MIN(X31,Y31)) -> 0 | AA31: =Z31/(1+$B$8)^V31 -> 0 | AB31: =MAX(0,Y31-Z31) -> 0
V32: =V31+1 -> 30 | W32: =$F$2*(1+$B$7)^(V32-1) -> 91071.567 | X32: =$B$5*MAX(0,W32-$B$6) -> 5739.891 | Y32: =AB31 -> 0 | Z32: =IF(Y32<=0,0,MIN(X32,Y32)) -> 0 | AA32: =Z32/(1+$B$8)^V32 -> 0 | AB32: =MAX(0,Y32-Z32) -> 0
K35: Repayment schedule for Bulgaria | S35: Repayment schedule for Denmark | AA35: Repayment schedule for Germany | AI35: Repayment schedule for Estonia
K36: Year | L36: Income | M36: raw repayment | N36: Opening balance | O36: actual repayment | P36: discounted payment | Q36: Closing balance | S36: Year | T36: Income | U36: raw repayment | V36: Opening balance | W36: actual repayment | X36: discounted payment | Y36: Closing balance | AA36: Year | AB36: Income | AC36: raw repayment | AD36: Opening balance | AE36: actual repayment | AF36: discounted payment | AG36: Closing balance | AI36: Year | AJ36: Income | AK36: raw repayment | AL36: Opening balance | AM36: actual repayment | AN36: discounted payment | AO36: Closing balance
K37: 1 | L37: =$F$3*(1+$B$7)^(K37-1) -> 13232.82 | M37: =$B$5*MAX(0,L37-$B$6) -> 0 | N37: =$B$2 -> 9250 | O37: =MIN(M37,N37) -> 0 | P37: =O37/(1+$B$8)^K37 -> 0 | Q37: =N37-O37 -> 9250 | S37: 1 | T37: =$F$5*(1+$B$7)^(S37-1) -> 61545.9 | U37: =$B$5*MAX(0,T37-$B$6) -> 3082.581 | V37: =$B$2 -> 9250 | W37: =MIN(U37,V37) -> 3082.581 | X37: =W37/(1+$B$8)^S37 -> 2992.7971 | Y37: =V37-W37 -> 6167.419 | AA37: 1 | AB37: =$F$6*(1+$B$7)^(AA37-1) -> 46260.26 | AC37: =$B$5*MAX(0,AB37-$B$6) -> 1706.8734 | AD37: =$B$2 -> 9250 | AE37: =MIN(AC37,AD37) -> 1706.8734 | AF37: =AE37/(1+$B$8)^AA37 -> 1657.1586 | AG37: =AD37-AE37 -> 7543.1266 | AI37: 1 | AJ37: =$F$7*(1+$B$7)^(AI37-1) -> 22829.56 | AK37: =$B$5*MAX(0,AJ37-$B$6) -> 0 | AL37: =$B$2 -> 9250 | AM37: =MIN(AK37,AL37) -> 0 | AN37: =AM37/(1+$B$8)^AI37 -> 0 | AO37: =AL37-AM37 -> 9250
K38: =K37+1 -> 2 | L38: =$F$3*(1+$B$7)^(K38-1) -> 13497.476 | M38: =$B$5*MAX(0,L38-$B$6) -> 0 | N38: =Q37 -> 9250 | O38: =IF(N38<=0,0,MIN(M38,N38)) -> 0 | P38: =O38/(1+$B$8)^K38 -> 0 | Q38: =MAX(0,N38-O38) -> 9250 | S38: =S37+1 -> 2 | T38: =$F$5*(1+$B$7)^(S38-1) -> 62776.818 | U38: =$B$5*MAX(0,T38-$B$6) -> 3193.3636 | V38: =Y37 -> 6167.419 | W38: =IF(V38<=0,0,MIN(U38,V38)) -> 3193.3636 | X38: =W38/(1+$B$8)^S38 -> 3010.0515 | Y38: =MAX(0,V38-W38) -> 2974.0554 | AA38: =AA37+1 -> 2 | AB38: =$F$6*(1+$B$7)^(AA38-1) -> 47185.465 | AC38: =$B$5*MAX(0,AB38-$B$6) -> 1790.1419 | AD38: =AG37 -> 7543.1266 | AE38: =IF(AD38<=0,0,MIN(AC38,AD38)) -> 1790.1419 | AF38: =AE38/(1+$B$8)^AA38 -> 1687.3804 | AG38: =MAX(0,AD38-AE38) -> 5752.9847 | AI38: =AI37+1 -> 2 | AJ38: =$F$7*(1+$B$7)^(AI38-1) -> 23286.151 | AK38: =$B$5*MAX(0,AJ38-$B$6) -> 0 | AL38: =AO37 -> 9250 | AM38: =IF(AL38<=0,0,MIN(AK38,AL38)) -> 0 | AN38: =AM38/(1+$B$8)^AI38 -> 0 | AO38: =MAX(0,AL38-AM38) -> 9250
K39: =K38+1 -> 3 | L39: =$F$3*(1+$B$7)^(K39-1) -> 13767.426 | M39: =$B$5*MAX(0,L39-$B$6) -> 0 | N39: =Q38 -> 9250 | O39: =IF(N39<=0,0,MIN(M39,N39)) -> 0 | P39: =O39/(1+$B$8)^K39 -> 0 | Q39: =MAX(0,N39-O39) -> 9250 | S39: =S38+1 -> 3 | T39: =$F$5*(1+$B$7)^(S39-1) -> 64032.354 | U39: =$B$5*MAX(0,T39-$B$6) -> 3306.3619 | V39: =Y38 -> 2974.0554 | W39: =IF(V39<=0,0,MIN(U39,V39)) -> 2974.0554 | X39: =W39/(1+$B$8)^S39 -> 2721.682 | Y39: =MAX(0,V39-W39) -> 0 | AA39: =AA38+1 -> 3 | AB39: =$F$6*(1+$B$7)^(AA39-1) -> 48129.175 | AC39: =$B$5*MAX(0,AB39-$B$6) -> 1875.0757 | AD39: =AG38 -> 5752.9847 | AE39: =IF(AD39<=0,0,MIN(AC39,AD39)) -> 1875.0757 | AF39: =AE39/(1+$B$8)^AA39 -> 1715.9599 | AG39: =MAX(0,AD39-AE39) -> 3877.909 | AI39: =AI38+1 -> 3 | AJ39: =$F$7*(1+$B$7)^(AI39-1) -> 23751.874 | AK39: =$B$5*MAX(0,AJ39-$B$6) -> 0 | AL39: =AO38 -> 9250 | AM39: =IF(AL39<=0,0,MIN(AK39,AL39)) -> 0 | AN39: =AM39/(1+$B$8)^AI39 -> 0 | AO39: =MAX(0,AL39-AM39) -> 9250
K40: =K39+1 -> 4 | L40: =$F$3*(1+$B$7)^(K40-1) -> 14042.774 | M40: =$B$5*MAX(0,L40-$B$6) -> 0 | N40: =Q39 -> 9250 | O40: =IF(N40<=0,0,MIN(M40,N40)) -> 0 | P40: =O40/(1+$B$8)^K40 -> 0 | Q40: =MAX(0,N40-O40) -> 9250 | S40: =S39+1 -> 4 | T40: =$F$5*(1+$B$7)^(S40-1) -> 65313.001 | U40: =$B$5*MAX(0,T40-$B$6) -> 3421.6201 | V40: =Y39 -> 0 | W40: =IF(V40<=0,0,MIN(U40,V40)) -> 0 | X40: =W40/(1+$B$8)^S40 -> 0 | Y40: =MAX(0,V40-W40) -> 0 | AA40: =AA39+1 -> 4 | AB40: =$F$6*(1+$B$7)^(AA40-1) -> 49091.758 | AC40: =$B$5*MAX(0,AB40-$B$6) -> 1961.7082 | AD40: =AG39 -> 3877.909 | AE40: =IF(AD40<=0,0,MIN(AC40,AD40)) -> 1961.7082 | AF40: =AE40/(1+$B$8)^AA40 -> 1742.9523 | AG40: =MAX(0,AD40-AE40) -> 1916.2008 | AI40: =AI39+1 -> 4 | AJ40: =$F$7*(1+$B$7)^(AI40-1) -> 24226.912 | AK40: =$B$5*MAX(0,AJ40-$B$6) -> 0 | AL40: =AO39 -> 9250 | AM40: =IF(AL40<=0,0,MIN(AK40,AL40)) -> 0 | AN40: =AM40/(1+$B$8)^AI40 -> 0 | AO40: =MAX(0,AL40-AM40) -> 9250
K41: =K40+1 -> 5 | L41: =$F$3*(1+$B$7)^(K41-1) -> 14323.63 | M41: =$B$5*MAX(0,L41-$B$6) -> 0 | N41: =Q40 -> 9250 | O41: =IF(N41<=0,0,MIN(M41,N41)) -> 0 | P41: =O41/(1+$B$8)^K41 -> 0 | Q41: =MAX(0,N41-O41) -> 9250 | S41: =S40+1 -> 5 | T41: =$F$5*(1+$B$7)^(S41-1) -> 66619.261 | U41: =$B$5*MAX(0,T41-$B$6) -> 3539.1835 | V41: =Y40 -> 0 | W41: =IF(V41<=0,0,MIN(U41,V41)) -> 0 | X41: =W41/(1+$B$8)^S41 -> 0 | Y41: =MAX(0,V41-W41) -> 0 | AA41: =AA40+1 -> 5 | AB41: =$F$6*(1+$B$7)^(AA41-1) -> 50073.593 | AC41: =$B$5*MAX(0,AB41-$B$6) -> 2050.0734 | AD41: =AG40 -> 1916.2008 | AE41: =IF(AD41<=0,0,MIN(AC41,AD41)) -> 1916.2008 | AF41: =AE41/(1+$B$8)^AA41 -> 1652.9316 | AG41: =MAX(0,AD41-AE41) -> 0 | AI41: =AI40+1 -> 5 | AJ41: =$F$7*(1+$B$7)^(AI41-1) -> 24711.45 | AK41: =$B$5*MAX(0,AJ41-$B$6) -> 0 | AL41: =AO40 -> 9250 | AM41: =IF(AL41<=0,0,MIN(AK41,AL41)) -> 0 | AN41: =AM41/(1+$B$8)^AI41 -> 0 | AO41: =MAX(0,AL41-AM41) -> 9250
K42: =K41+1 -> 6 | L42: =$F$3*(1+$B$7)^(K42-1) -> 14610.103 | M42: =$B$5*MAX(0,L42-$B$6) -> 0 | N42: =Q41 -> 9250 | O42: =IF(N42<=0,0,MIN(M42,N42)) -> 0 | P42: =O42/(1+$B$8)^K42 -> 0 | Q42: =MAX(0,N42-O42) -> 9250 | S42: =S41+1 -> 6 | T42: =$F$5*(1+$B$7)^(S42-1) -> 67951.647 | U42: =$B$5*MAX(0,T42-$B$6) -> 3659.0982 | V42: =Y41 -> 0 | W42: =IF(V42<=0,0,MIN(U42,V42)) -> 0 | X42: =W42/(1+$B$8)^S42 -> 0 | Y42: =MAX(0,V42-W42) -> 0 | AA42: =AA41+1 -> 6 | AB42: =$F$6*(1+$B$7)^(AA42-1) -> 51075.065 | AC42: =$B$5*MAX(0,AB42-$B$6) -> 2140.2059 | AD42: =AG41 -> 0 | AE42: =IF(AD42<=0,0,MIN(AC42,AD42)) -> 0 | AF42: =AE42/(1+$B$8)^AA42 -> 0 | AG42: =MAX(0,AD42-AE42) -> 0 | AI42: =AI41+1 -> 6 | AJ42: =$F$7*(1+$B$7)^(AI42-1) -> 25205.679 | AK42: =$B$5*MAX(0,AJ42-$B$6) -> 0 | AL42: =AO41 -> 9250 | AM42: =IF(AL42<=0,0,MIN(AK42,AL42)) -> 0 | AN42: =AM42/(1+$B$8)^AI42 -> 0 | AO42: =MAX(0,AL42-AM42) -> 9250
K43: =K42+1 -> 7 | L43: =$F$3*(1+$B$7)^(K43-1) -> 14902.305 | M43: =$B$5*MAX(0,L43-$B$6) -> 0 | N43: =Q42 -> 9250 | O43: =IF(N43<=0,0,MIN(M43,N43)) -> 0 | P43: =O43/(1+$B$8)^K43 -> 0 | Q43: =MAX(0,N43-O43) -> 9250 | S43: =S42+1 -> 7 | T43: =$F$5*(1+$B$7)^(S43-1) -> 69310.68 | U43: =$B$5*MAX(0,T43-$B$6) -> 3781.4112 | V43: =Y42 -> 0 | W43: =IF(V43<=0,0,MIN(U43,V43)) -> 0 | X43: =W43/(1+$B$8)^S43 -> 0 | Y43: =MAX(0,V43-W43) -> 0 | AA43: =AA42+1 -> 7 | AB43: =$F$6*(1+$B$7)^(AA43-1) -> 52096.566 | AC43: =$B$5*MAX(0,AB43-$B$6) -> 2232.141 | AD43: =AG42 -> 0 | AE43: =IF(AD43<=0,0,MIN(AC43,AD43)) -> 0 | AF43: =AE43/(1+$B$8)^AA43 -> 0 | AG43: =MAX(0,AD43-AE43) -> 0 | AI43: =AI42+1 -> 7 | AJ43: =$F$7*(1+$B$7)^(AI43-1) -> 25709.793 | AK43: =$B$5*MAX(0,AJ43-$B$6) -> 0 | AL43: =AO42 -> 9250 | AM43: =IF(AL43<=0,0,MIN(AK43,AL43)) -> 0 | AN43: =AM43/(1+$B$8)^AI43 -> 0 | AO43: =MAX(0,AL43-AM43) -> 9250
K44: =K43+1 -> 8 | L44: =$F$3*(1+$B$7)^(K44-1) -> 15200.351 | M44: =$B$5*MAX(0,L44-$B$6) -> 0 | N44: =Q43 -> 9250 | O44: =IF(N44<=0,0,MIN(M44,N44)) -> 0 | P44: =O44/(1+$B$8)^K44 -> 0 | Q44: =MAX(0,N44-O44) -> 9250 | S44: =S43+1 -> 8 | T44: =$F$5*(1+$B$7)^(S44-1) -> 70696.893 | U44: =$B$5*MAX(0,T44-$B$6) -> 3906.1704 | V44: =Y43 -> 0 | W44: =IF(V44<=0,0,MIN(U44,V44)) -> 0 | X44: =W44/(1+$B$8)^S44 -> 0 | Y44: =MAX(0,V44-W44) -> 0 | AA44: =AA43+1 -> 8 | AB44: =$F$6*(1+$B$7)^(AA44-1) -> 53138.498 | AC44: =$B$5*MAX(0,AB44-$B$6) -> 2325.9148 | AD44: =AG43 -> 0 | AE44: =IF(AD44<=0,0,MIN(AC44,AD44)) -> 0 | AF44: =AE44/(1+$B$8)^AA44 -> 0 | AG44: =MAX(0,AD44-AE44) -> 0 | AI44: =AI43+1 -> 8 | AJ44: =$F$7*(1+$B$7)^(AI44-1) -> 26223.988 | AK44: =$B$5*MAX(0,AJ44-$B$6) -> 0 | AL44: =AO43 -> 9250 | AM44: =IF(AL44<=0,0,MIN(AK44,AL44)) -> 0 | AN44: =AM44/(1+$B$8)^AI44 -> 0 | AO44: =MAX(0,AL44-AM44) -> 9250
K45: =K44+1 -> 9 | L45: =$F$3*(1+$B$7)^(K45-1) -> 15504.358 | M45: =$B$5*MAX(0,L45-$B$6) -> 0 | N45: =Q44 -> 9250 | O45: =IF(N45<=0,0,MIN(M45,N45)) -> 0 | P45: =O45/(1+$B$8)^K45 -> 0 | Q45: =MAX(0,N45-O45) -> 9250 | S45: =S44+1 -> 9 | T45: =$F$5*(1+$B$7)^(S45-1) -> 72110.831 | U45: =$B$5*MAX(0,T45-$B$6) -> 4033.4248 | V45: =Y44 -> 0 | W45: =IF(V45<=0,0,MIN(U45,V45)) -> 0 | X45: =W45/(1+$B$8)^S45 -> 0 | Y45: =MAX(0,V45-W45) -> 0 | AA45: =AA44+1 -> 9 | AB45: =$F$6*(1+$B$7)^(AA45-1) -> 54201.268 | AC45: =$B$5*MAX(0,AB45-$B$6) -> 2421.5641 | AD45: =AG44 -> 0 | AE45: =IF(AD45<=0,0,MIN(AC45,AD45)) -> 0 | AF45: =AE45/(1+$B$8)^AA45 -> 0 | AG45: =MAX(0,AD45-AE45) -> 0 | AI45: =AI44+1 -> 9 | AJ45: =$F$7*(1+$B$7)^(AI45-1) -> 26748.468 | AK45: =$B$5*MAX(0,AJ45-$B$6) -> 0 | AL45: =AO44 -> 9250 | AM45: =IF(AL45<=0,0,MIN(AK45,AL45)) -> 0 | AN45: =AM45/(1+$B$8)^AI45 -> 0 | AO45: =MAX(0,AL45-AM45) -> 9250
K46: =K45+1 -> 10 | L46: =$F$3*(1+$B$7)^(K46-1) -> 15814.445 | M46: =$B$5*MAX(0,L46-$B$6) -> 0 | N46: =Q45 -> 9250 | O46: =IF(N46<=0,0,MIN(M46,N46)) -> 0 | P46: =O46/(1+$B$8)^K46 -> 0 | Q46: =MAX(0,N46-O46) -> 9250 | S46: =S45+1 -> 10 | T46: =$F$5*(1+$B$7)^(S46-1) -> 73553.048 | U46: =$B$5*MAX(0,T46-$B$6) -> 4163.2243 | V46: =Y45 -> 0 | W46: =IF(V46<=0,0,MIN(U46,V46)) -> 0 | X46: =W46/(1+$B$8)^S46 -> 0 | Y46: =MAX(0,V46-W46) -> 0 | AA46: =AA45+1 -> 10 | AB46: =$F$6*(1+$B$7)^(AA46-1) -> 55285.293 | AC46: =$B$5*MAX(0,AB46-$B$6) -> 2519.1264 | AD46: =AG45 -> 0 | AE46: =IF(AD46<=0,0,MIN(AC46,AD46)) -> 0 | AF46: =AE46/(1+$B$8)^AA46 -> 0 | AG46: =MAX(0,AD46-AE46) -> 0 | AI46: =AI45+1 -> 10 | AJ46: =$F$7*(1+$B$7)^(AI46-1) -> 27283.438 | AK46: =$B$5*MAX(0,AJ46-$B$6) -> 0 | AL46: =AO45 -> 9250 | AM46: =IF(AL46<=0,0,MIN(AK46,AL46)) -> 0 | AN46: =AM46/(1+$B$8)^AI46 -> 0 | AO46: =MAX(0,AL46-AM46) -> 9250
K47: =K46+1 -> 11 | L47: =$F$3*(1+$B$7)^(K47-1) -> 16130.734 | M47: =$B$5*MAX(0,L47-$B$6) -> 0 | N47: =Q46 -> 9250 | O47: =IF(N47<=0,0,MIN(M47,N47)) -> 0 | P47: =O47/(1+$B$8)^K47 -> 0 | Q47: =MAX(0,N47-O47) -> 9250 | S47: =S46+1 -> 11 | T47: =$F$5*(1+$B$7)^(S47-1) -> 75024.109 | U47: =$B$5*MAX(0,T47-$B$6) -> 4295.6198 | V47: =Y46 -> 0 | W47: =IF(V47<=0,0,MIN(U47,V47)) -> 0 | X47: =W47/(1+$B$8)^S47 -> 0 | Y47: =MAX(0,V47-W47) -> 0 | AA47: =AA46+1 -> 11 | AB47: =$F$6*(1+$B$7)^(AA47-1) -> 56390.999 | AC47: =$B$5*MAX(0,AB47-$B$6) -> 2618.6399 | AD47: =AG46 -> 0 | AE47: =IF(AD47<=0,0,MIN(AC47,AD47)) -> 0 | AF47: =AE47/(1+$B$8)^AA47 -> 0 | AG47: =MAX(0,AD47-AE47) -> 0 | AI47: =AI46+1 -> 11 | AJ47: =$F$7*(1+$B$7)^(AI47-1) -> 27829.106 | AK47: =$B$5*MAX(0,AJ47-$B$6) -> 48.069563 | AL47: =AO46 -> 9250 | AM47: =IF(AL47<=0,0,MIN(AK47,AL47)) -> 48.069563 | AN47: =AM47/(1+$B$8)^AI47 -> 34.726475 | AO47: =MAX(0,AL47-AM47) -> 9201.9304
K48: =K47+1 -> 12 | L48: =$F$3*(1+$B$7)^(K48-1) -> 16453.348 | M48: =$B$5*MAX(0,L48-$B$6) -> 0 | N48: =Q47 -> 9250 | O48: =IF(N48<=0,0,MIN(M48,N48)) -> 0 | P48: =O48/(1+$B$8)^K48 -> 0 | Q48: =MAX(0,N48-O48) -> 9250 | S48: =S47+1 -> 12 | T48: =$F$5*(1+$B$7)^(S48-1) -> 76524.591 | U48: =$B$5*MAX(0,T48-$B$6) -> 4430.6632 | V48: =Y47 -> 0 | W48: =IF(V48<=0,0,MIN(U48,V48)) -> 0 | X48: =W48/(1+$B$8)^S48 -> 0 | Y48: =MAX(0,V48-W48) -> 0 | AA48: =AA47+1 -> 12 | AB48: =$F$6*(1+$B$7)^(AA48-1) -> 57518.819 | AC48: =$B$5*MAX(0,AB48-$B$6) -> 2720.1437 | AD48: =AG47 -> 0 | AE48: =IF(AD48<=0,0,MIN(AC48,AD48)) -> 0 | AF48: =AE48/(1+$B$8)^AA48 -> 0 | AG48: =MAX(0,AD48-AE48) -> 0 | AI48: =AI47+1 -> 12 | AJ48: =$F$7*(1+$B$7)^(AI48-1) -> 28385.688 | AK48: =$B$5*MAX(0,AJ48-$B$6) -> 98.161954 | AL48: =AO47 -> 9201.9304 | AM48: =IF(AL48<=0,0,MIN(AK48,AL48)) -> 98.161954 | AN48: =AM48/(1+$B$8)^AI48 -> 68.848819 | AO48: =MAX(0,AL48-AM48) -> 9103.7685
K49: =K48+1 -> 13 | L49: =$F$3*(1+$B$7)^(K49-1) -> 16782.415 | M49: =$B$5*MAX(0,L49-$B$6) -> 0 | N49: =Q48 -> 9250 | O49: =IF(N49<=0,0,MIN(M49,N49)) -> 0 | P49: =O49/(1+$B$8)^K49 -> 0 | Q49: =MAX(0,N49-O49) -> 9250 | S49: =S48+1 -> 13 | T49: =$F$5*(1+$B$7)^(S49-1) -> 78055.083 | U49: =$B$5*MAX(0,T49-$B$6) -> 4568.4074 | V49: =Y48 -> 0 | W49: =IF(V49<=0,0,MIN(U49,V49)) -> 0 | X49: =W49/(1+$B$8)^S49 -> 0 | Y49: =MAX(0,V49-W49) -> 0 | AA49: =AA48+1 -> 13 | AB49: =$F$6*(1+$B$7)^(AA49-1) -> 58669.195 | AC49: =$B$5*MAX(0,AB49-$B$6) -> 2823.6776 | AD49: =AG48 -> 0 | AE49: =IF(AD49<=0,0,MIN(AC49,AD49)) -> 0 | AF49: =AE49/(1+$B$8)^AA49 -> 0 | AG49: =MAX(0,AD49-AE49) -> 0 | AI49: =AI48+1 -> 13 | AJ49: =$F$7*(1+$B$7)^(AI49-1) -> 28953.402 | AK49: =$B$5*MAX(0,AJ49-$B$6) -> 149.25619 | AL49: =AO48 -> 9103.7685 | AM49: =IF(AL49<=0,0,MIN(AK49,AL49)) -> 149.25619 | AN49: =AM49/(1+$B$8)^AI49 -> 101.6362 | AO49: =MAX(0,AL49-AM49) -> 8954.5123
... K66: =K65+1 -> 30 | L66: =$F$3*(1+$B$7)^(K66-1) -> 23499.433 | M66: =$B$5*MAX(0,L66-$B$6) -> 0 | N66: =Q65 -> 9250 | O66: =IF(N66<=0,0,MIN(M66,N66)) -> 0 | P66: =O66/(1+$B$8)^K66 -> 0 | Q66: =MAX(0,N66-O66) -> 9250 | S66: =S65+1 -> 30 | T66: =$F$5*(1+$B$7)^(S66-1) -> 109295.96 | U66: =$B$5*MAX(0,T66-$B$6) -> 7380.0864 | V66: =Y65 -> 0 | W66: =IF(V66<=0,0,MIN(U66,V66)) -> 0 | X66: =W66/(1+$B$8)^S66 -> 0 | Y66: =MAX(0,V66-W66) -> 0 | AA66: =AA65+1 -> 30 | AB66: =$F$6*(1+$B$7)^(AA66-1) -> 82151.037 | AC66: =$B$5*MAX(0,AB66-$B$6) -> 4937.0433 | AD66: =AG65 -> 0 | AE66: =IF(AD66<=0,0,MIN(AC66,AD66)) -> 0 | AF66: =AE66/(1+$B$8)^AA66 -> 0 | AG66: =MAX(0,AD66-AE66) -> 0 | AI66: =AI65+1 -> 30 | AJ66: =$F$7*(1+$B$7)^(AI66-1) -> 40541.753 | AK66: =$B$5*MAX(0,AJ66-$B$6) -> 1192.2078 | AL66: =AO65 -> 0 | AM66: =IF(AL66<=0,0,MIN(AK66,AL66)) -> 0 | AN66: =AM66/(1+$B$8)^AI66 -> 0 | AO66: =MAX(0,AL66-AM66) -> 0
K69: Repayment schedule for Chezchia | S69: Repayment schedule for Greece | AA69: Repayment schedule for Spain | AI69: Repayment schedule for France
K70: Year | L70: Income | M70: raw repayment | N70: Opening balance | O70: actual repayment | P70: discounted payment | Q70: Closing balance | S70: Year | T70: Income | U70: raw repayment | V70: Opening balance | W70: actual repayment | X70: discounted payment | Y70: Closing balance | AA70: Year | AB70: Income | AC70: raw repayment | AD70: Opening balance | AE70: actual repayment | AF70: discounted payment | AG70: Closing balance | AI70: Year | AJ70: Income | AK70: raw repayment | AL70: Opening balance | AM70: actual repayment | AN70: discounted payment | AO70: Closing balance
K71: 1 | L71: =$F$4*(1+$B$7)^(K71-1) -> 20638.28 | M71: =$B$5*MAX(0,L71-$B$6) -> 0 | N71: =$B$2 -> 9250 | O71: =MIN(M71,N71) -> 0 | P71: =O71/(1+$B$8)^K71 -> 0 | Q71: =N71-O71 -> 9250 | S71: 1 | T71: =$F$9*(1+$B$7)^(S71-1) -> 15440.44 | U71: =$B$5*MAX(0,T71-$B$6) -> 0 | V71: =$B$2 -> 9250 | W71: =MIN(U71,V71) -> 0 | X71: =W71/(1+$B$8)^S71 -> 0 | Y71: =V71-W71 -> 9250 | AA71: 1 | AB71: =$F$10*(1+$B$7)^(AA71-1) -> 28982 | AC71: =$B$5*MAX(0,AB71-$B$6) -> 151.83 | AD71: =$B$2 -> 9250 | AE71: =MIN(AC71,AD71) -> 151.83 | AF71: =AE71/(1+$B$8)^AA71 -> 147.40777 | AG71: =AD71-AE71 -> 9098.17 | AI71: 1 | AJ71: =$F$11*(1+$B$7)^(AI71-1) -> 37659.4 | AK71: =$B$5*MAX(0,AJ71-$B$6) -> 932.796 | AL71: =$B$2 -> 9250 | AM71: =MIN(AK71,AL71) -> 932.796 | AN71: =AM71/(1+$B$8)^AI71 -> 905.62718 | AO71: =AL71-AM71 -> 8317.204
K72: =K71+1 -> 2 | L72: =$F$4*(1+$B$7)^(K72-1) -> 21051.046 | M72: =$B$5*MAX(0,L72-$B$6) -> 0 | N72: =Q71 -> 9250 | O72: =IF(N72<=0,0,MIN(M72,N72)) -> 0 | P72: =O72/(1+$B$8)^K72 -> 0 | Q72: =MAX(0,N72-O72) -> 9250 | S72: =S71+1 -> 2 | T72: =$F$9*(1+$B$7)^(S72-1) -> 15749.249 | U72: =$B$5*MAX(0,T72-$B$6) -> 0 | V72: =Y71 -> 9250 | W72: =IF(V72<=0,0,MIN(U72,V72)) -> 0 | X72: =W72/(1+$B$8)^S72 -> 0 | Y72: =MAX(0,V72-W72) -> 9250 | AA72: =AA71+1 -> 2 | AB72: =$F$10*(1+$B$7)^(AA72-1) -> 29561.64 | AC72: =$B$5*MAX(0,AB72-$B$6) -> 203.9976 | AD72: =AG71 -> 9098.17 | AE72: =IF(AD72<=0,0,MIN(AC72,AD72)) -> 203.9976 | AF72: =AE72/(1+$B$8)^AA72 -> 192.2873 | AG72: =MAX(0,AD72-AE72) -> 8894.1724 | AI72: =AI71+1 -> 2 | AJ72: =$F$11*(1+$B$7)^(AI72-1) -> 38412.588 | AK72: =$B$5*MAX(0,AJ72-$B$6) -> 1000.5829 | AL72: =AO71 -> 8317.204 | AM72: =IF(AL72<=0,0,MIN(AK72,AL72)) -> 1000.5829 | AN72: =AM72/(1+$B$8)^AI72 -> 943.14537 | AO72: =MAX(0,AL72-AM72) -> 7316.6211
K73: =K72+1 -> 3 | L73: =$F$4*(1+$B$7)^(K73-1) -> 21472.067 | M73: =$B$5*MAX(0,L73-$B$6) -> 0 | N73: =Q72 -> 9250 | O73: =IF(N73<=0,0,MIN(M73,N73)) -> 0 | P73: =O73/(1+$B$8)^K73 -> 0 | Q73: =MAX(0,N73-O73) -> 9250 | S73: =S72+1 -> 3 | T73: =$F$9*(1+$B$7)^(S73-1) -> 16064.234 | U73: =$B$5*MAX(0,T73-$B$6) -> 0 | V73: =Y72 -> 9250 | W73: =IF(V73<=0,0,MIN(U73,V73)) -> 0 | X73: =W73/(1+$B$8)^S73 -> 0 | Y73: =MAX(0,V73-W73) -> 9250 | AA73: =AA72+1 -> 3 | AB73: =$F$10*(1+$B$7)^(AA73-1) -> 30152.873 | AC73: =$B$5*MAX(0,AB73-$B$6) -> 257.20855 | AD73: =AG72 -> 8894.1724 | AE73: =IF(AD73<=0,0,MIN(AC73,AD73)) -> 257.20855 | AF73: =AE73/(1+$B$8)^AA73 -> 235.38226 | AG73: =MAX(0,AD73-AE73) -> 8636.9638 | AI73: =AI72+1 -> 3 | AJ73: =$F$11*(1+$B$7)^(AI73-1) -> 39180.84 | AK73: =$B$5*MAX(0,AJ73-$B$6) -> 1069.7256 | AL73: =AO72 -> 7316.6211 | AM73: =IF(AL73<=0,0,MIN(AK73,AL73)) -> 1069.7256 | AN73: =AM73/(1+$B$8)^AI73 -> 978.95044 | AO73: =MAX(0,AL73-AM73) -> 6246.8955
K74: =K73+1 -> 4 | L74: =$F$4*(1+$B$7)^(K74-1) -> 21901.508 | M74: =$B$5*MAX(0,L74-$B$6) -> 0 | N74: =Q73 -> 9250 | O74: =IF(N74<=0,0,MIN(M74,N74)) -> 0 | P74: =O74/(1+$B$8)^K74 -> 0 | Q74: =MAX(0,N74-O74) -> 9250 | S74: =S73+1 -> 4 | T74: =$F$9*(1+$B$7)^(S74-1) -> 16385.518 | U74: =$B$5*MAX(0,T74-$B$6) -> 0 | V74: =Y73 -> 9250 | W74: =IF(V74<=0,0,MIN(U74,V74)) -> 0 | X74: =W74/(1+$B$8)^S74 -> 0 | Y74: =MAX(0,V74-W74) -> 9250 | AA74: =AA73+1 -> 4 | AB74: =$F$10*(1+$B$7)^(AA74-1) -> 30755.93 | AC74: =$B$5*MAX(0,AB74-$B$6) -> 311.48372 | AD74: =AG73 -> 8636.9638 | AE74: =IF(AD74<=0,0,MIN(AC74,AD74)) -> 311.48372 | AF74: =AE74/(1+$B$8)^AA74 -> 276.74925 | AG74: =MAX(0,AD74-AE74) -> 8325.4801 | AI74: =AI73+1 -> 4 | AJ74: =$F$11*(1+$B$7)^(AI74-1) -> 39964.457 | AK74: =$B$5*MAX(0,AJ74-$B$6) -> 1140.2511 | AL74: =AO73 -> 6246.8955 | AM74: =IF(AL74<=0,0,MIN(AK74,AL74)) -> 1140.2511 | AN74: =AM74/(1+$B$8)^AI74 -> 1013.0983 | AO74: =MAX(0,AL74-AM74) -> 5106.6444
K75: =K74+1 -> 5 | L75: =$F$4*(1+$B$7)^(K75-1) -> 22339.538 | M75: =$B$5*MAX(0,L75-$B$6) -> 0 | N75: =Q74 -> 9250 | O75: =IF(N75<=0,0,MIN(M75,N75)) -> 0 | P75: =O75/(1+$B$8)^K75 -> 0 | Q75: =MAX(0,N75-O75) -> 9250 | S75: =S74+1 -> 5 | T75: =$F$9*(1+$B$7)^(S75-1) -> 16713.229 | U75: =$B$5*MAX(0,T75-$B$6) -> 0 | V75: =Y74 -> 9250 | W75: =IF(V75<=0,0,MIN(U75,V75)) -> 0 | X75: =W75/(1+$B$8)^S75 -> 0 | Y75: =MAX(0,V75-W75) -> 9250 | AA75: =AA74+1 -> 5 | AB75: =$F$10*(1+$B$7)^(AA75-1) -> 31371.049 | AC75: =$B$5*MAX(0,AB75-$B$6) -> 366.8444 | AD75: =AG74 -> 8325.4801 | AE75: =IF(AD75<=0,0,MIN(AC75,AD75)) -> 366.8444 | AF75: =AE75/(1+$B$8)^AA75 -> 316.4432 | AG75: =MAX(0,AD75-AE75) -> 7958.6357 | AI75: =AI74+1 -> 5 | AJ75: =$F$11*(1+$B$7)^(AI75-1) -> 40763.746 | AK75: =$B$5*MAX(0,AJ75-$B$6) -> 1212.1871 | AL75: =AO74 -> 5106.6444 | AM75: =IF(AL75<=0,0,MIN(AK75,AL75)) -> 1212.1871 | AN75: =AM75/(1+$B$8)^AI75 -> 1045.6433 | AO75: =MAX(0,AL75-AM75) -> 3894.4573
K76: =K75+1 -> 6 | L76: =$F$4*(1+$B$7)^(K76-1) -> 22786.329 | M76: =$B$5*MAX(0,L76-$B$6) -> 0 | N76: =Q75 -> 9250 | O76: =IF(N76<=0,0,MIN(M76,N76)) -> 0 | P76: =O76/(1+$B$8)^K76 -> 0 | Q76: =MAX(0,N76-O76) -> 9250 | S76: =S75+1 -> 6 | T76: =$F$9*(1+$B$7)^(S76-1) -> 17047.493 | U76: =$B$5*MAX(0,T76-$B$6) -> 0 | V76: =Y75 -> 9250 | W76: =IF(V76<=0,0,MIN(U76,V76)) -> 0 | X76: =W76/(1+$B$8)^S76 -> 0 | Y76: =MAX(0,V76-W76) -> 9250 | AA76: =AA75+1 -> 6 | AB76: =$F$10*(1+$B$7)^(AA76-1) -> 31998.47 | AC76: =$B$5*MAX(0,AB76-$B$6) -> 423.31229 | AD76: =AG75 -> 7958.6357 | AE76: =IF(AD76<=0,0,MIN(AC76,AD76)) -> 423.31229 | AF76: =AE76/(1+$B$8)^AA76 -> 354.51737 | AG76: =MAX(0,AD76-AE76) -> 7535.3234 | AI76: =AI75+1 -> 6 | AJ76: =$F$11*(1+$B$7)^(AI76-1) -> 41579.021 | AK76: =$B$5*MAX(0,AJ76-$B$6) -> 1285.5619 | AL76: =AO75 -> 3894.4573 | AM76: =IF(AL76<=0,0,MIN(AK76,AL76)) -> 1285.5619 | AN76: =AM76/(1+$B$8)^AI76 -> 1076.6378 | AO76: =MAX(0,AL76-AM76) -> 2608.8954
K77: =K76+1 -> 7 | L77: =$F$4*(1+$B$7)^(K77-1) -> 23242.055 | M77: =$B$5*MAX(0,L77-$B$6) -> 0 | N77: =Q76 -> 9250 | O77: =IF(N77<=0,0,MIN(M77,N77)) -> 0 | P77: =O77/(1+$B$8)^K77 -> 0 | Q77: =MAX(0,N77-O77) -> 9250 | S77: =S76+1 -> 7 | T77: =$F$9*(1+$B$7)^(S77-1) -> 17388.443 | U77: =$B$5*MAX(0,T77-$B$6) -> 0 | V77: =Y76 -> 9250 | W77: =IF(V77<=0,0,MIN(U77,V77)) -> 0 | X77: =W77/(1+$B$8)^S77 -> 0 | Y77: =MAX(0,V77-W77) -> 9250 | AA77: =AA76+1 -> 7 | AB77: =$F$10*(1+$B$7)^(AA77-1) -> 32638.439 | AC77: =$B$5*MAX(0,AB77-$B$6) -> 480.90953 | AD77: =AG76 -> 7535.3234 | AE77: =IF(AD77<=0,0,MIN(AC77,AD77)) -> 480.90953 | AF77: =AE77/(1+$B$8)^AA77 -> 391.02346 | AG77: =MAX(0,AD77-AE77) -> 7054.4139 | AI77: =AI76+1 -> 7 | AJ77: =$F$11*(1+$B$7)^(AI77-1) -> 42410.601 | AK77: =$B$5*MAX(0,AJ77-$B$6) -> 1360.4041 | AL77: =AO76 -> 2608.8954 | AM77: =IF(AL77<=0,0,MIN(AK77,AL77)) -> 1360.4041 | AN77: =AM77/(1+$B$8)^AI77 -> 1106.133 | AO77: =MAX(0,AL77-AM77) -> 1248.4914
K78: =K77+1 -> 8 | L78: =$F$4*(1+$B$7)^(K78-1) -> 23706.896 | M78: =$B$5*MAX(0,L78-$B$6) -> 0 | N78: =Q77 -> 9250 | O78: =IF(N78<=0,0,MIN(M78,N78)) -> 0 | P78: =O78/(1+$B$8)^K78 -> 0 | Q78: =MAX(0,N78-O78) -> 9250 | S78: =S77+1 -> 8 | T78: =$F$9*(1+$B$7)^(S78-1) -> 17736.212 | U78: =$B$5*MAX(0,T78-$B$6) -> 0 | V78: =Y77 -> 9250 | W78: =IF(V78<=0,0,MIN(U78,V78)) -> 0 | X78: =W78/(1+$B$8)^S78 -> 0 | Y78: =MAX(0,V78-W78) -> 9250 | AA78: =AA77+1 -> 8 | AB78: =$F$10*(1+$B$7)^(AA78-1) -> 33291.208 | AC78: =$B$5*MAX(0,AB78-$B$6) -> 539.65872 | AD78: =AG77 -> 7054.4139 | AE78: =IF(AD78<=0,0,MIN(AC78,AD78)) -> 539.65872 | AF78: =AE78/(1+$B$8)^AA78 -> 426.01158 | AG78: =MAX(0,AD78-AE78) -> 6514.7552 | AI78: =AI77+1 -> 8 | AJ78: =$F$11*(1+$B$7)^(AI78-1) -> 43258.813 | AK78: =$B$5*MAX(0,AJ78-$B$6) -> 1436.7432 | AL78: =AO77 -> 1248.4914 | AM78: =IF(AL78<=0,0,MIN(AK78,AL78)) -> 1248.4914 | AN78: =AM78/(1+$B$8)^AI78 -> 985.5706 | AO78: =MAX(0,AL78-AM78) -> 0
K79: =K78+1 -> 9 | L79: =$F$4*(1+$B$7)^(K79-1) -> 24181.034 | M79: =$B$5*MAX(0,L79-$B$6) -> 0 | N79: =Q78 -> 9250 | O79: =IF(N79<=0,0,MIN(M79,N79)) -> 0 | P79: =O79/(1+$B$8)^K79 -> 0 | Q79: =MAX(0,N79-O79) -> 9250 | S79: =S78+1 -> 9 | T79: =$F$9*(1+$B$7)^(S79-1) -> 18090.936 | U79: =$B$5*MAX(0,T79-$B$6) -> 0 | V79: =Y78 -> 9250 | W79: =IF(V79<=0,0,MIN(U79,V79)) -> 0 | X79: =W79/(1+$B$8)^S79 -> 0 | Y79: =MAX(0,V79-W79) -> 9250 | AA79: =AA78+1 -> 9 | AB79: =$F$10*(1+$B$7)^(AA79-1) -> 33957.032 | AC79: =$B$5*MAX(0,AB79-$B$6) -> 599.5829 | AD79: =AG78 -> 6514.7552 | AE79: =IF(AD79<=0,0,MIN(AC79,AD79)) -> 599.5829 | AF79: =AE79/(1+$B$8)^AA79 -> 459.53036 | AG79: =MAX(0,AD79-AE79) -> 5915.1723 | AI79: =AI78+1 -> 9 | AJ79: =$F$11*(1+$B$7)^(AI79-1) -> 44123.989 | AK79: =$B$5*MAX(0,AJ79-$B$6) -> 1514.609 | AL79: =AO78 -> 0 | AM79: =IF(AL79<=0,0,MIN(AK79,AL79)) -> 0 | AN79: =AM79/(1+$B$8)^AI79 -> 0 | AO79: =MAX(0,AL79-AM79) -> 0
K80: =K79+1 -> 10 | L80: =$F$4*(1+$B$7)^(K80-1) -> 24664.655 | M80: =$B$5*MAX(0,L80-$B$6) -> 0 | N80: =Q79 -> 9250 | O80: =IF(N80<=0,0,MIN(M80,N80)) -> 0 | P80: =O80/(1+$B$8)^K80 -> 0 | Q80: =MAX(0,N80-O80) -> 9250 | S80: =S79+1 -> 10 | T80: =$F$9*(1+$B$7)^(S80-1) -> 18452.755 | U80: =$B$5*MAX(0,T80-$B$6) -> 0 | V80: =Y79 -> 9250 | W80: =IF(V80<=0,0,MIN(U80,V80)) -> 0 | X80: =W80/(1+$B$8)^S80 -> 0 | Y80: =MAX(0,V80-W80) -> 9250 | AA80: =AA79+1 -> 10 | AB80: =$F$10*(1+$B$7)^(AA80-1) -> 34636.173 | AC80: =$B$5*MAX(0,AB80-$B$6) -> 660.70555 | AD80: =AG79 -> 5915.1723 | AE80: =IF(AD80<=0,0,MIN(AC80,AD80)) -> 660.70555 | AF80: =AE80/(1+$B$8)^AA80 -> 491.62698 | AG80: =MAX(0,AD80-AE80) -> 5254.4667 | AI80: =AI79+1 -> 10 | AJ80: =$F$11*(1+$B$7)^(AI80-1) -> 45006.469 | AK80: =$B$5*MAX(0,AJ80-$B$6) -> 1594.0322 | AL80: =AO79 -> 0 | AM80: =IF(AL80<=0,0,MIN(AK80,AL80)) -> 0 | AN80: =AM80/(1+$B$8)^AI80 -> 0 | AO80: =MAX(0,AL80-AM80) -> 0
K81: =K80+1 -> 11 | L81: =$F$4*(1+$B$7)^(K81-1) -> 25157.948 | M81: =$B$5*MAX(0,L81-$B$6) -> 0 | N81: =Q80 -> 9250 | O81: =IF(N81<=0,0,MIN(M81,N81)) -> 0 | P81: =O81/(1+$B$8)^K81 -> 0 | Q81: =MAX(0,N81-O81) -> 9250 | S81: =S80+1 -> 11 | T81: =$F$9*(1+$B$7)^(S81-1) -> 18821.81 | U81: =$B$5*MAX(0,T81-$B$6) -> 0 | V81: =Y80 -> 9250 | W81: =IF(V81<=0,0,MIN(U81,V81)) -> 0 | X81: =W81/(1+$B$8)^S81 -> 0 | Y81: =MAX(0,V81-W81) -> 9250 | AA81: =AA80+1 -> 11 | AB81: =$F$10*(1+$B$7)^(AA81-1) -> 35328.896 | AC81: =$B$5*MAX(0,AB81-$B$6) -> 723.05067 | AD81: =AG80 -> 5254.4667 | AE81: =IF(AD81<=0,0,MIN(AC81,AD81)) -> 723.05067 | AF81: =AE81/(1+$B$8)^AA81 -> 522.34718 | AG81: =MAX(0,AD81-AE81) -> 4531.4161 | AI81: =AI80+1 -> 11 | AJ81: =$F$11*(1+$B$7)^(AI81-1) -> 45906.598 | AK81: =$B$5*MAX(0,AJ81-$B$6) -> 1675.0439 | AL81: =AO80 -> 0 | AM81: =IF(AL81<=0,0,MIN(AK81,AL81)) -> 0 | AN81: =AM81/(1+$B$8)^AI81 -> 0 | AO81: =MAX(0,AL81-AM81) -> 0
K82: =K81+1 -> 12 | L82: =$F$4*(1+$B$7)^(K82-1) -> 25661.107 | M82: =$B$5*MAX(0,L82-$B$6) -> 0 | N82: =Q81 -> 9250 | O82: =IF(N82<=0,0,MIN(M82,N82)) -> 0 | P82: =O82/(1+$B$8)^K82 -> 0 | Q82: =MAX(0,N82-O82) -> 9250 | S82: =S81+1 -> 12 | T82: =$F$9*(1+$B$7)^(S82-1) -> 19198.246 | U82: =$B$5*MAX(0,T82-$B$6) -> 0 | V82: =Y81 -> 9250 | W82: =IF(V82<=0,0,MIN(U82,V82)) -> 0 | X82: =W82/(1+$B$8)^S82 -> 0 | Y82: =MAX(0,V82-W82) -> 9250 | AA82: =AA81+1 -> 12 | AB82: =$F$10*(1+$B$7)^(AA82-1) -> 36035.474 | AC82: =$B$5*MAX(0,AB82-$B$6) -> 786.64268 | AD82: =AG81 -> 4531.4161 | AE82: =IF(AD82<=0,0,MIN(AC82,AD82)) -> 786.64268 | AF82: =AE82/(1+$B$8)^AA82 -> 551.73535 | AG82: =MAX(0,AD82-AE82) -> 3744.7734 | AI82: =AI81+1 -> 12 | AJ82: =$F$11*(1+$B$7)^(AI82-1) -> 46824.73 | AK82: =$B$5*MAX(0,AJ82-$B$6) -> 1757.6757 | AL82: =AO81 -> 0 | AM82: =IF(AL82<=0,0,MIN(AK82,AL82)) -> 0 | AN82: =AM82/(1+$B$8)^AI82 -> 0 | AO82: =MAX(0,AL82-AM82) -> 0
K83: =K82+1 -> 13 | L83: =$F$4*(1+$B$7)^(K83-1) -> 26174.329 | M83: =$B$5*MAX(0,L83-$B$6) -> 0 | N83: =Q82 -> 9250 | O83: =IF(N83<=0,0,MIN(M83,N83)) -> 0 | P83: =O83/(1+$B$8)^K83 -> 0 | Q83: =MAX(0,N83-O83) -> 9250 | S83: =S82+1 -> 13 | T83: =$F$9*(1+$B$7)^(S83-1) -> 19582.211 | U83: =$B$5*MAX(0,T83-$B$6) -> 0 | V83: =Y82 -> 9250 | W83: =IF(V83<=0,0,MIN(U83,V83)) -> 0 | X83: =W83/(1+$B$8)^S83 -> 0 | Y83: =MAX(0,V83-W83) -> 9250 | AA83: =AA82+1 -> 13 | AB83: =$F$10*(1+$B$7)^(AA83-1) -> 36756.184 | AC83: =$B$5*MAX(0,AB83-$B$6) -> 851.50653 | AD83: =AG82 -> 3744.7734 | AE83: =IF(AD83<=0,0,MIN(AC83,AD83)) -> 851.50653 | AF83: =AE83/(1+$B$8)^AA83 -> 579.83451 | AG83: =MAX(0,AD83-AE83) -> 2893.2669 | AI83: =AI82+1 -> 13 | AJ83: =$F$11*(1+$B$7)^(AI83-1) -> 47761.225 | AK83: =$B$5*MAX(0,AJ83-$B$6) -> 1841.9603 | AL83: =AO82 -> 0 | AM83: =IF(AL83<=0,0,MIN(AK83,AL83)) -> 0 | AN83: =AM83/(1+$B$8)^AI83 -> 0 | AO83: =MAX(0,AL83-AM83) -> 0
... K100: =K99+1 -> 30 | L100: =$F$4*(1+$B$7)^(K100-1) -> 36650.38 | M100: =$B$5*MAX(0,L100-$B$6) -> 841.9842 | N100: =Q99 -> 3708.8244 | O100: =IF(N100<=0,0,MIN(M100,N100)) -> 841.9842 | P100: =O100/(1+$B$8)^K100 -> 346.88634 | Q100: =MAX(0,N100-O100) -> 2866.8402 | S100: =S99+1 -> 30 | T100: =$F$9*(1+$B$7)^(S100-1) -> 27419.823 | U100: =$B$5*MAX(0,T100-$B$6) -> 11.234105 | V100: =Y99 -> 9250 | W100: =IF(V100<=0,0,MIN(U100,V100)) -> 11.234105 | X100: =W100/(1+$B$8)^S100 -> 4.6283026 | Y100: =MAX(0,V100-W100) -> 9238.7659 | AA100: =AA99+1 -> 30 | AB100: =$F$10*(1+$B$7)^(AA100-1) -> 51467.531 | AC100: =$B$5*MAX(0,AB100-$B$6) -> 2175.5278 | AD100: =AG99 -> 0 | AE100: =IF(AD100<=0,0,MIN(AC100,AD100)) -> 0 | AF100: =AE100/(1+$B$8)^AA100 -> 0 | AG100: =MAX(0,AD100-AE100) -> 0 | AI100: =AI99+1 -> 30 | AJ100: =$F$11*(1+$B$7)^(AI100-1) -> 66877.246 | AK100: =$B$5*MAX(0,AJ100-$B$6) -> 3562.4021 | AL100: =AO99 -> 0 | AM100: =IF(AL100<=0,0,MIN(AK100,AL100)) -> 0 | AN100: =AM100/(1+$B$8)^AI100 -> 0 | AO100: =MAX(0,AL100-AM100) -> 0
K103: Repayment schedule for Croatia | S103: Repayment schedule for Italy | AA103: Repayment schedule for Cyrpus | AI103: Repayment schedule for Latvia
K104: Year | L104: Income | M104: raw repayment | N104: Opening balance | O104: actual repayment | P104: discounted payment | Q104: Closing balance | S104: Year | T104: Income | U104: raw repayment | V104: Opening balance | W104: actual repayment | X104: discounted payment | Y104: Closing balance | AA104: Year | AB104: Income | AC104: raw repayment | AD104: Opening balance | AE104: actual repayment | AF104: discounted payment | AG104: Closing balance | AI104: Year | AJ104: Income | AK104: raw repayment | AL104: Opening balance | AM104: actual repayment | AN104: discounted payment | AO104: Closing balance
K105: 1 | L105: =$F$12*(1+$B$7)^(K105-1) -> 20163.56 | M105: =$B$5*MAX(0,L105-$B$6) -> 0 | N105: =$B$2 -> 9250 | O105: =MIN(M105,N105) -> 0 | P105: =O105/(1+$B$8)^K105 -> 0 | Q105: =N105-O105 -> 9250 | S105: 1 | T105: =$F$13*(1+$B$7)^(S105-1) -> 28829.78 | U105: =$B$5*MAX(0,T105-$B$6) -> 138.1302 | V105: =$B$2 -> 9250 | W105: =MIN(U105,V105) -> 138.1302 | X105: =W105/(1+$B$8)^S105 -> 134.10699 | Y105: =V105-W105 -> 9111.8698 | AA105: 1 | AB105: =$F$14*(1+$B$7)^(AA105-1) -> 23745.46 | AC105: =$B$5*MAX(0,AB105-$B$6) -> 0 | AD105: =$B$2 -> 9250 | AE105: =MIN(AC105,AD105) -> 0 | AF105: =AE105/(1+$B$8)^AA105 -> 0 | AG105: =AD105-AE105 -> 9250 | AI105: 1 | AJ105: =$F$15*(1+$B$7)^(AI105-1) -> 19145.32 | AK105: =$B$5*MAX(0,AJ105-$B$6) -> 0 | AL105: =$B$2 -> 9250 | AM105: =MIN(AK105,AL105) -> 0 | AN105: =AM105/(1+$B$8)^AI105 -> 0 | AO105: =AL105-AM105 -> 9250
K106: =K105+1 -> 2 | L106: =$F$12*(1+$B$7)^(K106-1) -> 20566.831 | M106: =$B$5*MAX(0,L106-$B$6) -> 0 | N106: =Q105 -> 9250 | O106: =IF(N106<=0,0,MIN(M106,N106)) -> 0 | P106: =O106/(1+$B$8)^K106 -> 0 | Q106: =MAX(0,N106-O106) -> 9250 | S106: =S105+1 -> 2 | T106: =$F$13*(1+$B$7)^(S106-1) -> 29406.376 | U106: =$B$5*MAX(0,T106-$B$6) -> 190.0238 | V106: =Y105 -> 9111.8698 | W106: =IF(V106<=0,0,MIN(U106,V106)) -> 190.0238 | X106: =W106/(1+$B$8)^S106 -> 179.11566 | Y106: =MAX(0,V106-W106) -> 8921.846 | AA106: =AA105+1 -> 2 | AB106: =$F$14*(1+$B$7)^(AA106-1) -> 24220.369 | AC106: =$B$5*MAX(0,AB106-$B$6) -> 0 | AD106: =AG105 -> 9250 | AE106: =IF(AD106<=0,0,MIN(AC106,AD106)) -> 0 | AF106: =AE106/(1+$B$8)^AA106 -> 0 | AG106: =MAX(0,AD106-AE106) -> 9250 | AI106: =AI105+1 -> 2 | AJ106: =$F$15*(1+$B$7)^(AI106-1) -> 19528.226 | AK106: =$B$5*MAX(0,AJ106-$B$6) -> 0 | AL106: =AO105 -> 9250 | AM106: =IF(AL106<=0,0,MIN(AK106,AL106)) -> 0 | AN106: =AM106/(1+$B$8)^AI106 -> 0 | AO106: =MAX(0,AL106-AM106) -> 9250
K107: =K106+1 -> 3 | L107: =$F$12*(1+$B$7)^(K107-1) -> 20978.168 | M107: =$B$5*MAX(0,L107-$B$6) -> 0 | N107: =Q106 -> 9250 | O107: =IF(N107<=0,0,MIN(M107,N107)) -> 0 | P107: =O107/(1+$B$8)^K107 -> 0 | Q107: =MAX(0,N107-O107) -> 9250 | S107: =S106+1 -> 3 | T107: =$F$13*(1+$B$7)^(S107-1) -> 29994.503 | U107: =$B$5*MAX(0,T107-$B$6) -> 242.95528 | V107: =Y106 -> 8921.846 | W107: =IF(V107<=0,0,MIN(U107,V107)) -> 242.95528 | X107: =W107/(1+$B$8)^S107 -> 222.3385 | Y107: =MAX(0,V107-W107) -> 8678.8907 | AA107: =AA106+1 -> 3 | AB107: =$F$14*(1+$B$7)^(AA107-1) -> 24704.777 | AC107: =$B$5*MAX(0,AB107-$B$6) -> 0 | AD107: =AG106 -> 9250 | AE107: =IF(AD107<=0,0,MIN(AC107,AD107)) -> 0 | AF107: =AE107/(1+$B$8)^AA107 -> 0 | AG107: =MAX(0,AD107-AE107) -> 9250 | AI107: =AI106+1 -> 3 | AJ107: =$F$15*(1+$B$7)^(AI107-1) -> 19918.791 | AK107: =$B$5*MAX(0,AJ107-$B$6) -> 0 | AL107: =AO106 -> 9250 | AM107: =IF(AL107<=0,0,MIN(AK107,AL107)) -> 0 | AN107: =AM107/(1+$B$8)^AI107 -> 0 | AO107: =MAX(0,AL107-AM107) -> 9250
K108: =K107+1 -> 4 | L108: =$F$12*(1+$B$7)^(K108-1) -> 21397.731 | M108: =$B$5*MAX(0,L108-$B$6) -> 0 | N108: =Q107 -> 9250 | O108: =IF(N108<=0,0,MIN(M108,N108)) -> 0 | P108: =O108/(1+$B$8)^K108 -> 0 | Q108: =MAX(0,N108-O108) -> 9250 | S108: =S107+1 -> 4 | T108: =$F$13*(1+$B$7)^(S108-1) -> 30594.393 | U108: =$B$5*MAX(0,T108-$B$6) -> 296.94539 | V108: =Y107 -> 8678.8907 | W108: =IF(V108<=0,0,MIN(U108,V108)) -> 296.94539 | X108: =W108/(1+$B$8)^S108 -> 263.83213 | Y108: =MAX(0,V108-W108) -> 8381.9453 | AA108: =AA107+1 -> 4 | AB108: =$F$14*(1+$B$7)^(AA108-1) -> 25198.872 | AC108: =$B$5*MAX(0,AB108-$B$6) -> 0 | AD108: =AG107 -> 9250 | AE108: =IF(AD108<=0,0,MIN(AC108,AD108)) -> 0 | AF108: =AE108/(1+$B$8)^AA108 -> 0 | AG108: =MAX(0,AD108-AE108) -> 9250 | AI108: =AI107+1 -> 4 | AJ108: =$F$15*(1+$B$7)^(AI108-1) -> 20317.167 | AK108: =$B$5*MAX(0,AJ108-$B$6) -> 0 | AL108: =AO107 -> 9250 | AM108: =IF(AL108<=0,0,MIN(AK108,AL108)) -> 0 | AN108: =AM108/(1+$B$8)^AI108 -> 0 | AO108: =MAX(0,AL108-AM108) -> 9250
K109: =K108+1 -> 5 | L109: =$F$12*(1+$B$7)^(K109-1) -> 21825.686 | M109: =$B$5*MAX(0,L109-$B$6) -> 0 | N109: =Q108 -> 9250 | O109: =IF(N109<=0,0,MIN(M109,N109)) -> 0 | P109: =O109/(1+$B$8)^K109 -> 0 | Q109: =MAX(0,N109-O109) -> 9250 | S109: =S108+1 -> 5 | T109: =$F$13*(1+$B$7)^(S109-1) -> 31206.281 | U109: =$B$5*MAX(0,T109-$B$6) -> 352.01529 | V109: =Y108 -> 8381.9453 | W109: =IF(V109<=0,0,MIN(U109,V109)) -> 352.01529 | X109: =W109/(1+$B$8)^S109 -> 303.65148 | Y109: =MAX(0,V109-W109) -> 8029.93 | AA109: =AA108+1 -> 5 | AB109: =$F$14*(1+$B$7)^(AA109-1) -> 25702.85 | AC109: =$B$5*MAX(0,AB109-$B$6) -> 0 | AD109: =AG108 -> 9250 | AE109: =IF(AD109<=0,0,MIN(AC109,AD109)) -> 0 | AF109: =AE109/(1+$B$8)^AA109 -> 0 | AG109: =MAX(0,AD109-AE109) -> 9250 | AI109: =AI108+1 -> 5 | AJ109: =$F$15*(1+$B$7)^(AI109-1) -> 20723.51 | AK109: =$B$5*MAX(0,AJ109-$B$6) -> 0 | AL109: =AO108 -> 9250 | AM109: =IF(AL109<=0,0,MIN(AK109,AL109)) -> 0 | AN109: =AM109/(1+$B$8)^AI109 -> 0 | AO109: =MAX(0,AL109-AM109) -> 9250
K110: =K109+1 -> 6 | L110: =$F$12*(1+$B$7)^(K110-1) -> 22262.2 | M110: =$B$5*MAX(0,L110-$B$6) -> 0 | N110: =Q109 -> 9250 | O110: =IF(N110<=0,0,MIN(M110,N110)) -> 0 | P110: =O110/(1+$B$8)^K110 -> 0 | Q110: =MAX(0,N110-O110) -> 9250 | S110: =S109+1 -> 6 | T110: =$F$13*(1+$B$7)^(S110-1) -> 31830.407 | U110: =$B$5*MAX(0,T110-$B$6) -> 408.1866 | V110: =Y109 -> 8029.93 | W110: =IF(V110<=0,0,MIN(U110,V110)) -> 408.1866 | X110: =W110/(1+$B$8)^S110 -> 341.84985 | Y110: =MAX(0,V110-W110) -> 7621.7434 | AA110: =AA109+1 -> 6 | AB110: =$F$14*(1+$B$7)^(AA110-1) -> 26216.907 | AC110: =$B$5*MAX(0,AB110-$B$6) -> 0 | AD110: =AG109 -> 9250 | AE110: =IF(AD110<=0,0,MIN(AC110,AD110)) -> 0 | AF110: =AE110/(1+$B$8)^AA110 -> 0 | AG110: =MAX(0,AD110-AE110) -> 9250 | AI110: =AI109+1 -> 6 | AJ110: =$F$15*(1+$B$7)^(AI110-1) -> 21137.98 | AK110: =$B$5*MAX(0,AJ110-$B$6) -> 0 | AL110: =AO109 -> 9250 | AM110: =IF(AL110<=0,0,MIN(AK110,AL110)) -> 0 | AN110: =AM110/(1+$B$8)^AI110 -> 0 | AO110: =MAX(0,AL110-AM110) -> 9250
K111: =K110+1 -> 7 | L111: =$F$12*(1+$B$7)^(K111-1) -> 22707.444 | M111: =$B$5*MAX(0,L111-$B$6) -> 0 | N111: =Q110 -> 9250 | O111: =IF(N111<=0,0,MIN(M111,N111)) -> 0 | P111: =O111/(1+$B$8)^K111 -> 0 | Q111: =MAX(0,N111-O111) -> 9250 | S111: =S110+1 -> 7 | T111: =$F$13*(1+$B$7)^(S111-1) -> 32467.015 | U111: =$B$5*MAX(0,T111-$B$6) -> 465.48133 | V111: =Y110 -> 7621.7434 | W111: =IF(V111<=0,0,MIN(U111,V111)) -> 465.48133 | X111: =W111/(1+$B$8)^S111 -> 378.47892 | Y111: =MAX(0,V111-W111) -> 7156.2621 | AA111: =AA110+1 -> 7 | AB111: =$F$14*(1+$B$7)^(AA111-1) -> 26741.245 | AC111: =$B$5*MAX(0,AB111-$B$6) -> 0 | AD111: =AG110 -> 9250 | AE111: =IF(AD111<=0,0,MIN(AC111,AD111)) -> 0 | AF111: =AE111/(1+$B$8)^AA111 -> 0 | AG111: =MAX(0,AD111-AE111) -> 9250 | AI111: =AI110+1 -> 7 | AJ111: =$F$15*(1+$B$7)^(AI111-1) -> 21560.74 | AK111: =$B$5*MAX(0,AJ111-$B$6) -> 0 | AL111: =AO110 -> 9250 | AM111: =IF(AL111<=0,0,MIN(AK111,AL111)) -> 0 | AN111: =AM111/(1+$B$8)^AI111 -> 0 | AO111: =MAX(0,AL111-AM111) -> 9250
K112: =K111+1 -> 8 | L112: =$F$12*(1+$B$7)^(K112-1) -> 23161.592 | M112: =$B$5*MAX(0,L112-$B$6) -> 0 | N112: =Q111 -> 9250 | O112: =IF(N112<=0,0,MIN(M112,N112)) -> 0 | P112: =O112/(1+$B$8)^K112 -> 0 | Q112: =MAX(0,N112-O112) -> 9250 | S112: =S111+1 -> 8 | T112: =$F$13*(1+$B$7)^(S112-1) -> 33116.355 | U112: =$B$5*MAX(0,T112-$B$6) -> 523.92196 | V112: =Y111 -> 7156.2621 | W112: =IF(V112<=0,0,MIN(U112,V112)) -> 523.92196 | X112: =W112/(1+$B$8)^S112 -> 413.58883 | Y112: =MAX(0,V112-W112) -> 6632.3401 | AA112: =AA111+1 -> 8 | AB112: =$F$14*(1+$B$7)^(AA112-1) -> 27276.07 | AC112: =$B$5*MAX(0,AB112-$B$6) -> 0 | AD112: =AG111 -> 9250 | AE112: =IF(AD112<=0,0,MIN(AC112,AD112)) -> 0 | AF112: =AE112/(1+$B$8)^AA112 -> 0 | AG112: =MAX(0,AD112-AE112) -> 9250 | AI112: =AI111+1 -> 8 | AJ112: =$F$15*(1+$B$7)^(AI112-1) -> 21991.955 | AK112: =$B$5*MAX(0,AJ112-$B$6) -> 0 | AL112: =AO111 -> 9250 | AM112: =IF(AL112<=0,0,MIN(AK112,AL112)) -> 0 | AN112: =AM112/(1+$B$8)^AI112 -> 0 | AO112: =MAX(0,AL112-AM112) -> 9250
K113: =K112+1 -> 9 | L113: =$F$12*(1+$B$7)^(K113-1) -> 23624.824 | M113: =$B$5*MAX(0,L113-$B$6) -> 0 | N113: =Q112 -> 9250 | O113: =IF(N113<=0,0,MIN(M113,N113)) -> 0 | P113: =O113/(1+$B$8)^K113 -> 0 | Q113: =MAX(0,N113-O113) -> 9250 | S113: =S112+1 -> 9 | T113: =$F$13*(1+$B$7)^(S113-1) -> 33778.682 | U113: =$B$5*MAX(0,T113-$B$6) -> 583.5314 | V113: =Y112 -> 6632.3401 | W113: =IF(V113<=0,0,MIN(U113,V113)) -> 583.5314 | X113: =W113/(1+$B$8)^S113 -> 447.22823 | Y113: =MAX(0,V113-W113) -> 6048.8088 | AA113: =AA112+1 -> 9 | AB113: =$F$14*(1+$B$7)^(AA113-1) -> 27821.591 | AC113: =$B$5*MAX(0,AB113-$B$6) -> 47.393187 | AD113: =AG112 -> 9250 | AE113: =IF(AD113<=0,0,MIN(AC113,AD113)) -> 47.393187 | AF113: =AE113/(1+$B$8)^AA113 -> 36.322931 | AG113: =MAX(0,AD113-AE113) -> 9202.6068 | AI113: =AI112+1 -> 9 | AJ113: =$F$15*(1+$B$7)^(AI113-1) -> 22431.794 | AK113: =$B$5*MAX(0,AJ113-$B$6) -> 0 | AL113: =AO112 -> 9250 | AM113: =IF(AL113<=0,0,MIN(AK113,AL113)) -> 0 | AN113: =AM113/(1+$B$8)^AI113 -> 0 | AO113: =MAX(0,AL113-AM113) -> 9250
K114: =K113+1 -> 10 | L114: =$F$12*(1+$B$7)^(K114-1) -> 24097.321 | M114: =$B$5*MAX(0,L114-$B$6) -> 0 | N114: =Q113 -> 9250 | O114: =IF(N114<=0,0,MIN(M114,N114)) -> 0 | P114: =O114/(1+$B$8)^K114 -> 0 | Q114: =MAX(0,N114-O114) -> 9250 | S114: =S113+1 -> 10 | T114: =$F$13*(1+$B$7)^(S114-1) -> 34454.256 | U114: =$B$5*MAX(0,T114-$B$6) -> 644.33302 | V114: =Y113 -> 6048.8088 | W114: =IF(V114<=0,0,MIN(U114,V114)) -> 644.33302 | X114: =W114/(1+$B$8)^S114 -> 479.44428 | Y114: =MAX(0,V114-W114) -> 5404.4757 | AA114: =AA113+1 -> 10 | AB114: =$F$14*(1+$B$7)^(AA114-1) -> 28378.023 | AC114: =$B$5*MAX(0,AB114-$B$6) -> 97.472051 | AD114: =AG113 -> 9202.6068 | AE114: =IF(AD114<=0,0,MIN(AC114,AD114)) -> 97.472051 | AF114: =AE114/(1+$B$8)^AA114 -> 72.52836 | AG114: =MAX(0,AD114-AE114) -> 9105.1348 | AI114: =AI113+1 -> 10 | AJ114: =$F$15*(1+$B$7)^(AI114-1) -> 22880.43 | AK114: =$B$5*MAX(0,AJ114-$B$6) -> 0 | AL114: =AO113 -> 9250 | AM114: =IF(AL114<=0,0,MIN(AK114,AL114)) -> 0 | AN114: =AM114/(1+$B$8)^AI114 -> 0 | AO114: =MAX(0,AL114-AM114) -> 9250
K115: =K114+1 -> 11 | L115: =$F$12*(1+$B$7)^(K115-1) -> 24579.267 | M115: =$B$5*MAX(0,L115-$B$6) -> 0 | N115: =Q114 -> 9250 | O115: =IF(N115<=0,0,MIN(M115,N115)) -> 0 | P115: =O115/(1+$B$8)^K115 -> 0 | Q115: =MAX(0,N115-O115) -> 9250 | S115: =S114+1 -> 11 | T115: =$F$13*(1+$B$7)^(S115-1) -> 35143.341 | U115: =$B$5*MAX(0,T115-$B$6) -> 706.35069 | V115: =Y114 -> 5404.4757 | W115: =IF(V115<=0,0,MIN(U115,V115)) -> 706.35069 | X115: =W115/(1+$B$8)^S115 -> 510.28276 | Y115: =MAX(0,V115-W115) -> 4698.125 | AA115: =AA114+1 -> 11 | AB115: =$F$14*(1+$B$7)^(AA115-1) -> 28945.583 | AC115: =$B$5*MAX(0,AB115-$B$6) -> 148.55249 | AD115: =AG114 -> 9105.1348 | AE115: =IF(AD115<=0,0,MIN(AC115,AD115)) -> 148.55249 | AF115: =AE115/(1+$B$8)^AA115 -> 107.31748 | AG115: =MAX(0,AD115-AE115) -> 8956.5823 | AI115: =AI114+1 -> 11 | AJ115: =$F$15*(1+$B$7)^(AI115-1) -> 23338.038 | AK115: =$B$5*MAX(0,AJ115-$B$6) -> 0 | AL115: =AO114 -> 9250 | AM115: =IF(AL115<=0,0,MIN(AK115,AL115)) -> 0 | AN115: =AM115/(1+$B$8)^AI115 -> 0 | AO115: =MAX(0,AL115-AM115) -> 9250
K116: =K115+1 -> 12 | L116: =$F$12*(1+$B$7)^(K116-1) -> 25070.852 | M116: =$B$5*MAX(0,L116-$B$6) -> 0 | N116: =Q115 -> 9250 | O116: =IF(N116<=0,0,MIN(M116,N116)) -> 0 | P116: =O116/(1+$B$8)^K116 -> 0 | Q116: =MAX(0,N116-O116) -> 9250 | S116: =S115+1 -> 12 | T116: =$F$13*(1+$B$7)^(S116-1) -> 35846.208 | U116: =$B$5*MAX(0,T116-$B$6) -> 769.6087 | V116: =Y115 -> 4698.125 | W116: =IF(V116<=0,0,MIN(U116,V116)) -> 769.6087 | X116: =W116/(1+$B$8)^S116 -> 539.78806 | Y116: =MAX(0,V116-W116) -> 3928.5163 | AA116: =AA115+1 -> 12 | AB116: =$F$14*(1+$B$7)^(AA116-1) -> 29524.495 | AC116: =$B$5*MAX(0,AB116-$B$6) -> 200.65454 | AD116: =AG115 -> 8956.5823 | AE116: =IF(AD116<=0,0,MIN(AC116,AD116)) -> 200.65454 | AF116: =AE116/(1+$B$8)^AA116 -> 140.73506 | AG116: =MAX(0,AD116-AE116) -> 8755.9277 | AI116: =AI115+1 -> 12 | AJ116: =$F$15*(1+$B$7)^(AI116-1) -> 23804.799 | AK116: =$B$5*MAX(0,AJ116-$B$6) -> 0 | AL116: =AO115 -> 9250 | AM116: =IF(AL116<=0,0,MIN(AK116,AL116)) -> 0 | AN116: =AM116/(1+$B$8)^AI116 -> 0 | AO116: =MAX(0,AL116-AM116) -> 9250
K117: =K116+1 -> 13 | L117: =$F$12*(1+$B$7)^(K117-1) -> 25572.27 | M117: =$B$5*MAX(0,L117-$B$6) -> 0 | N117: =Q116 -> 9250 | O117: =IF(N117<=0,0,MIN(M117,N117)) -> 0 | P117: =O117/(1+$B$8)^K117 -> 0 | Q117: =MAX(0,N117-O117) -> 9250 | S117: =S116+1 -> 13 | T117: =$F$13*(1+$B$7)^(S117-1) -> 36563.132 | U117: =$B$5*MAX(0,T117-$B$6) -> 834.13187 | V117: =Y116 -> 3928.5163 | W117: =IF(V117<=0,0,MIN(U117,V117)) -> 834.13187 | X117: =W117/(1+$B$8)^S117 -> 568.00322 | Y117: =MAX(0,V117-W117) -> 3094.3845 | AA117: =AA116+1 -> 13 | AB117: =$F$14*(1+$B$7)^(AA117-1) -> 30114.985 | AC117: =$B$5*MAX(0,AB117-$B$6) -> 253.79863 | AD117: =AG116 -> 8755.9277 | AE117: =IF(AD117<=0,0,MIN(AC117,AD117)) -> 253.79863 | AF117: =AE117/(1+$B$8)^AA117 -> 172.82452 | AG117: =MAX(0,AD117-AE117) -> 8502.1291 | AI117: =AI116+1 -> 13 | AJ117: =$F$15*(1+$B$7)^(AI117-1) -> 24280.895 | AK117: =$B$5*MAX(0,AJ117-$B$6) -> 0 | AL117: =AO116 -> 9250 | AM117: =IF(AL117<=0,0,MIN(AK117,AL117)) -> 0 | AN117: =AM117/(1+$B$8)^AI117 -> 0 | AO117: =MAX(0,AL117-AM117) -> 9250
... K134: =K133+1 -> 30 | L134: =$F$12*(1+$B$7)^(K134-1) -> 35807.351 | M134: =$B$5*MAX(0,L134-$B$6) -> 766.11159 | N134: =Q133 -> 4613.1819 | O134: =IF(N134<=0,0,MIN(M134,N134)) -> 766.11159 | P134: =O134/(1+$B$8)^K134 -> 315.62783 | Q134: =MAX(0,N134-O134) -> 3847.0703 | S134: =S133+1 -> 30 | T134: =$F$13*(1+$B$7)^(S134-1) -> 51197.212 | U134: =$B$5*MAX(0,T134-$B$6) -> 2151.1991 | V134: =Y133 -> 0 | W134: =IF(V134<=0,0,MIN(U134,V134)) -> 0 | X134: =W134/(1+$B$8)^S134 -> 0 | Y134: =MAX(0,V134-W134) -> 0 | AA134: =AA133+1 -> 30 | AB134: =$F$14*(1+$B$7)^(AA134-1) -> 42168.249 | AC134: =$B$5*MAX(0,AB134-$B$6) -> 1338.5924 | AD134: =AG133 -> 0 | AE134: =IF(AD134<=0,0,MIN(AC134,AD134)) -> 0 | AF134: =AE134/(1+$B$8)^AA134 -> 0 | AG134: =MAX(0,AD134-AE134) -> 0 | AI134: =AI133+1 -> 30 | AJ134: =$F$15*(1+$B$7)^(AI134-1) -> 33999.115 | AK134: =$B$5*MAX(0,AJ134-$B$6) -> 603.37034 | AL134: =AO133 -> 6325.0746 | AM134: =IF(AL134<=0,0,MIN(AK134,AL134)) -> 603.37034 | AN134: =AM134/(1+$B$8)^AI134 -> 248.58059 | AO134: =MAX(0,AL134-AM134) -> 5721.7043
K137: Repayment schedule for Lithuania | S137: Repayment schedule for Luxembourg | AA137: Repayment schedule for Hungary | AI137: Repayment schedule fo rMalta
K138: Year | L138: Income | M138: raw repayment | N138: Opening balance | O138: actual repayment | P138: discounted payment | Q138: Closing balance | S138: Year | T138: Income | U138: raw repayment | V138: Opening balance | W138: actual repayment | X138: discounted payment | Y138: Closing balance | AA138: Year | AB138: Income | AC138: raw repayment | AD138: Opening balance | AE138: actual repayment | AF138: discounted payment | AG138: Closing balance | AI138: Year | AJ138: Income | AK138: raw repayment | AL138: Opening balance | AM138: actual repayment | AN138: discounted payment | AO138: Closing balance
K139: 1 | L139: =$F$16*(1+$B$7)^(K139-1) -> 25029.44 | M139: =$B$5*MAX(0,L139-$B$6) -> 0 | N139: =$B$2 -> 9250 | O139: =MIN(M139,N139) -> 0 | P139: =O139/(1+$B$8)^K139 -> 0 | Q139: =N139-O139 -> 9250 | S139: 1 | T139: =$F$17*(1+$B$7)^(S139-1) -> 71353.34 | U139: =$B$5*MAX(0,T139-$B$6) -> 3965.2506 | V139: =$B$2 -> 9250 | W139: =MIN(U139,V139) -> 3965.2506 | X139: =W139/(1+$B$8)^S139 -> 3849.7579 | Y139: =V139-W139 -> 5284.7494 | AA139: 1 | AB139: =$F$18*(1+$B$7)^(AA139-1) -> 15876.46 | AC139: =$B$5*MAX(0,AB139-$B$6) -> 0 | AD139: =$B$2 -> 9250 | AE139: =MIN(AC139,AD139) -> 0 | AF139: =AE139/(1+$B$8)^AA139 -> 0 | AG139: =AD139-AE139 -> 9250 | AI139: 1 | AJ139: =$F$19*(1+$B$7)^(AI139-1) -> 28809.14 | AK139: =$B$5*MAX(0,AJ139-$B$6) -> 136.2726 | AL139: =$B$2 -> 9250 | AM139: =MIN(AK139,AL139) -> 136.2726 | AN139: =AM139/(1+$B$8)^AI139 -> 132.3035 | AO139: =AL139-AM139 -> 9113.7274
K140: =K139+1 -> 2 | L140: =$F$16*(1+$B$7)^(K140-1) -> 25530.029 | M140: =$B$5*MAX(0,L140-$B$6) -> 0 | N140: =Q139 -> 9250 | O140: =IF(N140<=0,0,MIN(M140,N140)) -> 0 | P140: =O140/(1+$B$8)^K140 -> 0 | Q140: =MAX(0,N140-O140) -> 9250 | S140: =S139+1 -> 2 | T140: =$F$17*(1+$B$7)^(S140-1) -> 72780.407 | U140: =$B$5*MAX(0,T140-$B$6) -> 4093.6866 | V140: =Y139 -> 5284.7494 | W140: =IF(V140<=0,0,MIN(U140,V140)) -> 4093.6866 | X140: =W140/(1+$B$8)^S140 -> 3858.6923 | Y140: =MAX(0,V140-W140) -> 1191.0628 | AA140: =AA139+1 -> 2 | AB140: =$F$18*(1+$B$7)^(AA140-1) -> 16193.989 | AC140: =$B$5*MAX(0,AB140-$B$6) -> 0 | AD140: =AG139 -> 9250 | AE140: =IF(AD140<=0,0,MIN(AC140,AD140)) -> 0 | AF140: =AE140/(1+$B$8)^AA140 -> 0 | AG140: =MAX(0,AD140-AE140) -> 9250 | AI140: =AI139+1 -> 2 | AJ140: =$F$19*(1+$B$7)^(AI140-1) -> 29385.323 | AK140: =$B$5*MAX(0,AJ140-$B$6) -> 188.12905 | AL140: =AO139 -> 9113.7274 | AM140: =IF(AL140<=0,0,MIN(AK140,AL140)) -> 188.12905 | AN140: =AM140/(1+$B$8)^AI140 -> 177.32967 | AO140: =MAX(0,AL140-AM140) -> 8925.5983
K141: =K140+1 -> 3 | L141: =$F$16*(1+$B$7)^(K141-1) -> 26040.629 | M141: =$B$5*MAX(0,L141-$B$6) -> 0 | N141: =Q140 -> 9250 | O141: =IF(N141<=0,0,MIN(M141,N141)) -> 0 | P141: =O141/(1+$B$8)^K141 -> 0 | Q141: =MAX(0,N141-O141) -> 9250 | S141: =S140+1 -> 3 | T141: =$F$17*(1+$B$7)^(S141-1) -> 74236.015 | U141: =$B$5*MAX(0,T141-$B$6) -> 4224.6913 | V141: =Y140 -> 1191.0628 | W141: =IF(V141<=0,0,MIN(U141,V141)) -> 1191.0628 | X141: =W141/(1+$B$8)^S141 -> 1089.9912 | Y141: =MAX(0,V141-W141) -> 0 | AA141: =AA140+1 -> 3 | AB141: =$F$18*(1+$B$7)^(AA141-1) -> 16517.869 | AC141: =$B$5*MAX(0,AB141-$B$6) -> 0 | AD141: =AG140 -> 9250 | AE141: =IF(AD141<=0,0,MIN(AC141,AD141)) -> 0 | AF141: =AE141/(1+$B$8)^AA141 -> 0 | AG141: =MAX(0,AD141-AE141) -> 9250 | AI141: =AI140+1 -> 3 | AJ141: =$F$19*(1+$B$7)^(AI141-1) -> 29973.029 | AK141: =$B$5*MAX(0,AJ141-$B$6) -> 241.02263 | AL141: =AO140 -> 8925.5983 | AM141: =IF(AL141<=0,0,MIN(AK141,AL141)) -> 241.02263 | AN141: =AM141/(1+$B$8)^AI141 -> 220.56985 | AO141: =MAX(0,AL141-AM141) -> 8684.5757
K142: =K141+1 -> 4 | L142: =$F$16*(1+$B$7)^(K142-1) -> 26561.442 | M142: =$B$5*MAX(0,L142-$B$6) -> 0 | N142: =Q141 -> 9250 | O142: =IF(N142<=0,0,MIN(M142,N142)) -> 0 | P142: =O142/(1+$B$8)^K142 -> 0 | Q142: =MAX(0,N142-O142) -> 9250 | S142: =S141+1 -> 4 | T142: =$F$17*(1+$B$7)^(S142-1) -> 75720.735 | U142: =$B$5*MAX(0,T142-$B$6) -> 4358.3162 | V142: =Y141 -> 0 | W142: =IF(V142<=0,0,MIN(U142,V142)) -> 0 | X142: =W142/(1+$B$8)^S142 -> 0 | Y142: =MAX(0,V142-W142) -> 0 | AA142: =AA141+1 -> 4 | AB142: =$F$18*(1+$B$7)^(AA142-1) -> 16848.226 | AC142: =$B$5*MAX(0,AB142-$B$6) -> 0 | AD142: =AG141 -> 9250 | AE142: =IF(AD142<=0,0,MIN(AC142,AD142)) -> 0 | AF142: =AE142/(1+$B$8)^AA142 -> 0 | AG142: =MAX(0,AD142-AE142) -> 9250 | AI142: =AI141+1 -> 4 | AJ142: =$F$19*(1+$B$7)^(AI142-1) -> 30572.49 | AK142: =$B$5*MAX(0,AJ142-$B$6) -> 294.97409 | AL142: =AO141 -> 8684.5757 | AM142: =IF(AL142<=0,0,MIN(AK142,AL142)) -> 294.97409 | AN142: =AM142/(1+$B$8)^AI142 -> 262.08065 | AO142: =MAX(0,AL142-AM142) -> 8389.6016
K143: =K142+1 -> 5 | L143: =$F$16*(1+$B$7)^(K143-1) -> 27092.671 | M143: =$B$5*MAX(0,L143-$B$6) -> 0 | N143: =Q142 -> 9250 | O143: =IF(N143<=0,0,MIN(M143,N143)) -> 0 | P143: =O143/(1+$B$8)^K143 -> 0 | Q143: =MAX(0,N143-O143) -> 9250 | S143: =S142+1 -> 5 | T143: =$F$17*(1+$B$7)^(S143-1) -> 77235.15 | U143: =$B$5*MAX(0,T143-$B$6) -> 4494.6135 | V143: =Y142 -> 0 | W143: =IF(V143<=0,0,MIN(U143,V143)) -> 0 | X143: =W143/(1+$B$8)^S143 -> 0 | Y143: =MAX(0,V143-W143) -> 0 | AA143: =AA142+1 -> 5 | AB143: =$F$18*(1+$B$7)^(AA143-1) -> 17185.191 | AC143: =$B$5*MAX(0,AB143-$B$6) -> 0 | AD143: =AG142 -> 9250 | AE143: =IF(AD143<=0,0,MIN(AC143,AD143)) -> 0 | AF143: =AE143/(1+$B$8)^AA143 -> 0 | AG143: =MAX(0,AD143-AE143) -> 9250 | AI143: =AI142+1 -> 5 | AJ143: =$F$19*(1+$B$7)^(AI143-1) -> 31183.94 | AK143: =$B$5*MAX(0,AJ143-$B$6) -> 350.00457 | AL143: =AO142 -> 8389.6016 | AM143: =IF(AL143<=0,0,MIN(AK143,AL143)) -> 350.00457 | AN143: =AM143/(1+$B$8)^AI143 -> 301.91701 | AO143: =MAX(0,AL143-AM143) -> 8039.5971
K144: =K143+1 -> 6 | L144: =$F$16*(1+$B$7)^(K144-1) -> 27634.524 | M144: =$B$5*MAX(0,L144-$B$6) -> 30.55718 | N144: =Q143 -> 9250 | O144: =IF(N144<=0,0,MIN(M144,N144)) -> 30.55718 | P144: =O144/(1+$B$8)^K144 -> 25.591157 | Q144: =MAX(0,N144-O144) -> 9219.4428 | S144: =S143+1 -> 6 | T144: =$F$17*(1+$B$7)^(S144-1) -> 78779.853 | U144: =$B$5*MAX(0,T144-$B$6) -> 4633.6368 | V144: =Y143 -> 0 | W144: =IF(V144<=0,0,MIN(U144,V144)) -> 0 | X144: =W144/(1+$B$8)^S144 -> 0 | Y144: =MAX(0,V144-W144) -> 0 | AA144: =AA143+1 -> 6 | AB144: =$F$18*(1+$B$7)^(AA144-1) -> 17528.895 | AC144: =$B$5*MAX(0,AB144-$B$6) -> 0 | AD144: =AG143 -> 9250 | AE144: =IF(AD144<=0,0,MIN(AC144,AD144)) -> 0 | AF144: =AE144/(1+$B$8)^AA144 -> 0 | AG144: =MAX(0,AD144-AE144) -> 9250 | AI144: =AI143+1 -> 6 | AJ144: =$F$19*(1+$B$7)^(AI144-1) -> 31807.618 | AK144: =$B$5*MAX(0,AJ144-$B$6) -> 406.13566 | AL144: =AO143 -> 8039.5971 | AM144: =IF(AL144<=0,0,MIN(AK144,AL144)) -> 406.13566 | AN144: =AM144/(1+$B$8)^AI144 -> 340.13222 | AO144: =MAX(0,AL144-AM144) -> 7633.4614
K145: =K144+1 -> 7 | L145: =$F$16*(1+$B$7)^(K145-1) -> 28187.215 | M145: =$B$5*MAX(0,L145-$B$6) -> 80.299323 | N145: =Q144 -> 9219.4428 | O145: =IF(N145<=0,0,MIN(M145,N145)) -> 80.299323 | P145: =O145/(1+$B$8)^K145 -> 65.290698 | Q145: =MAX(0,N145-O145) -> 9139.1435 | S145: =S144+1 -> 7 | T145: =$F$17*(1+$B$7)^(S145-1) -> 80355.45 | U145: =$B$5*MAX(0,T145-$B$6) -> 4775.4405 | V145: =Y144 -> 0 | W145: =IF(V145<=0,0,MIN(U145,V145)) -> 0 | X145: =W145/(1+$B$8)^S145 -> 0 | Y145: =MAX(0,V145-W145) -> 0 | AA145: =AA144+1 -> 7 | AB145: =$F$18*(1+$B$7)^(AA145-1) -> 17879.473 | AC145: =$B$5*MAX(0,AB145-$B$6) -> 0 | AD145: =AG144 -> 9250 | AE145: =IF(AD145<=0,0,MIN(AC145,AD145)) -> 0 | AF145: =AE145/(1+$B$8)^AA145 -> 0 | AG145: =MAX(0,AD145-AE145) -> 9250 | AI145: =AI144+1 -> 7 | AJ145: =$F$19*(1+$B$7)^(AI145-1) -> 32443.771 | AK145: =$B$5*MAX(0,AJ145-$B$6) -> 463.38937 | AL145: =AO144 -> 7633.4614 | AM145: =IF(AL145<=0,0,MIN(AK145,AL145)) -> 463.38937 | AN145: =AM145/(1+$B$8)^AI145 -> 376.77796 | AO145: =MAX(0,AL145-AM145) -> 7170.072
K146: =K145+1 -> 8 | L146: =$F$16*(1+$B$7)^(K146-1) -> 28750.959 | M146: =$B$5*MAX(0,L146-$B$6) -> 131.03631 | N146: =Q145 -> 9139.1435 | O146: =IF(N146<=0,0,MIN(M146,N146)) -> 131.03631 | P146: =O146/(1+$B$8)^K146 -> 103.44127 | Q146: =MAX(0,N146-O146) -> 9008.1072 | S146: =S145+1 -> 8 | T146: =$F$17*(1+$B$7)^(S146-1) -> 81962.559 | U146: =$B$5*MAX(0,T146-$B$6) -> 4920.0803 | V146: =Y145 -> 0 | W146: =IF(V146<=0,0,MIN(U146,V146)) -> 0 | X146: =W146/(1+$B$8)^S146 -> 0 | Y146: =MAX(0,V146-W146) -> 0 | AA146: =AA145+1 -> 8 | AB146: =$F$18*(1+$B$7)^(AA146-1) -> 18237.062 | AC146: =$B$5*MAX(0,AB146-$B$6) -> 0 | AD146: =AG145 -> 9250 | AE146: =IF(AD146<=0,0,MIN(AC146,AD146)) -> 0 | AF146: =AE146/(1+$B$8)^AA146 -> 0 | AG146: =MAX(0,AD146-AE146) -> 9250 | AI146: =AI145+1 -> 8 | AJ146: =$F$19*(1+$B$7)^(AI146-1) -> 33092.646 | AK146: =$B$5*MAX(0,AJ146-$B$6) -> 521.78816 | AL146: =AO145 -> 7170.072 | AM146: =IF(AL146<=0,0,MIN(AK146,AL146)) -> 521.78816 | AN146: =AM146/(1+$B$8)^AI146 -> 411.90439 | AO146: =MAX(0,AL146-AM146) -> 6648.2839
K147: =K146+1 -> 9 | L147: =$F$16*(1+$B$7)^(K147-1) -> 29325.978 | M147: =$B$5*MAX(0,L147-$B$6) -> 182.78804 | N147: =Q146 -> 9008.1072 | O147: =IF(N147<=0,0,MIN(M147,N147)) -> 182.78804 | P147: =O147/(1+$B$8)^K147 -> 140.09181 | Q147: =MAX(0,N147-O147) -> 8825.3192 | S147: =S146+1 -> 9 | T147: =$F$17*(1+$B$7)^(S147-1) -> 83601.81 | U147: =$B$5*MAX(0,T147-$B$6) -> 5067.6129 | V147: =Y146 -> 0 | W147: =IF(V147<=0,0,MIN(U147,V147)) -> 0 | X147: =W147/(1+$B$8)^S147 -> 0 | Y147: =MAX(0,V147-W147) -> 0 | AA147: =AA146+1 -> 9 | AB147: =$F$18*(1+$B$7)^(AA147-1) -> 18601.803 | AC147: =$B$5*MAX(0,AB147-$B$6) -> 0 | AD147: =AG146 -> 9250 | AE147: =IF(AD147<=0,0,MIN(AC147,AD147)) -> 0 | AF147: =AE147/(1+$B$8)^AA147 -> 0 | AG147: =MAX(0,AD147-AE147) -> 9250 | AI147: =AI146+1 -> 9 | AJ147: =$F$19*(1+$B$7)^(AI147-1) -> 33754.499 | AK147: =$B$5*MAX(0,AJ147-$B$6) -> 581.35492 | AL147: =AO146 -> 6648.2839 | AM147: =IF(AL147<=0,0,MIN(AK147,AL147)) -> 581.35492 | AN147: =AM147/(1+$B$8)^AI147 -> 445.56014 | AO147: =MAX(0,AL147-AM147) -> 6066.9289
K148: =K147+1 -> 10 | L148: =$F$16*(1+$B$7)^(K148-1) -> 29912.498 | M148: =$B$5*MAX(0,L148-$B$6) -> 235.5748 | N148: =Q147 -> 8825.3192 | O148: =IF(N148<=0,0,MIN(M148,N148)) -> 235.5748 | P148: =O148/(1+$B$8)^K148 -> 175.28977 | Q148: =MAX(0,N148-O148) -> 8589.7444 | S148: =S147+1 -> 10 | T148: =$F$17*(1+$B$7)^(S148-1) -> 85273.846 | U148: =$B$5*MAX(0,T148-$B$6) -> 5218.0962 | V148: =Y147 -> 0 | W148: =IF(V148<=0,0,MIN(U148,V148)) -> 0 | X148: =W148/(1+$B$8)^S148 -> 0 | Y148: =MAX(0,V148-W148) -> 0 | AA148: =AA147+1 -> 10 | AB148: =$F$18*(1+$B$7)^(AA148-1) -> 18973.839 | AC148: =$B$5*MAX(0,AB148-$B$6) -> 0 | AD148: =AG147 -> 9250 | AE148: =IF(AD148<=0,0,MIN(AC148,AD148)) -> 0 | AF148: =AE148/(1+$B$8)^AA148 -> 0 | AG148: =MAX(0,AD148-AE148) -> 9250 | AI148: =AI147+1 -> 10 | AJ148: =$F$19*(1+$B$7)^(AI148-1) -> 34429.589 | AK148: =$B$5*MAX(0,AJ148-$B$6) -> 642.11302 | AL148: =AO147 -> 6066.9289 | AM148: =IF(AL148<=0,0,MIN(AK148,AL148)) -> 642.11302 | AN148: =AM148/(1+$B$8)^AI148 -> 477.79239 | AO148: =MAX(0,AL148-AM148) -> 5424.8159
K149: =K148+1 -> 11 | L149: =$F$16*(1+$B$7)^(K149-1) -> 30510.748 | M149: =$B$5*MAX(0,L149-$B$6) -> 289.41729 | N149: =Q148 -> 8589.7444 | O149: =IF(N149<=0,0,MIN(M149,N149)) -> 289.41729 | P149: =O149/(1+$B$8)^K149 -> 209.08121 | Q149: =MAX(0,N149-O149) -> 8300.3271 | S149: =S148+1 -> 11 | T149: =$F$17*(1+$B$7)^(S149-1) -> 86979.323 | U149: =$B$5*MAX(0,T149-$B$6) -> 5371.5891 | V149: =Y148 -> 0 | W149: =IF(V149<=0,0,MIN(U149,V149)) -> 0 | X149: =W149/(1+$B$8)^S149 -> 0 | Y149: =MAX(0,V149-W149) -> 0 | AA149: =AA148+1 -> 11 | AB149: =$F$18*(1+$B$7)^(AA149-1) -> 19353.316 | AC149: =$B$5*MAX(0,AB149-$B$6) -> 0 | AD149: =AG148 -> 9250 | AE149: =IF(AD149<=0,0,MIN(AC149,AD149)) -> 0 | AF149: =AE149/(1+$B$8)^AA149 -> 0 | AG149: =MAX(0,AD149-AE149) -> 9250 | AI149: =AI148+1 -> 11 | AJ149: =$F$19*(1+$B$7)^(AI149-1) -> 35118.181 | AK149: =$B$5*MAX(0,AJ149-$B$6) -> 704.08628 | AL149: =AO148 -> 5424.8159 | AM149: =IF(AL149<=0,0,MIN(AK149,AL149)) -> 704.08628 | AN149: =AM149/(1+$B$8)^AI149 -> 508.64691 | AO149: =MAX(0,AL149-AM149) -> 4720.7296
K150: =K149+1 -> 12 | L150: =$F$16*(1+$B$7)^(K150-1) -> 31120.963 | M150: =$B$5*MAX(0,L150-$B$6) -> 344.33664 | N150: =Q149 -> 8300.3271 | O150: =IF(N150<=0,0,MIN(M150,N150)) -> 344.33664 | P150: =O150/(1+$B$8)^K150 -> 241.51079 | Q150: =MAX(0,N150-O150) -> 7955.9904 | S150: =S149+1 -> 12 | T150: =$F$17*(1+$B$7)^(S150-1) -> 88718.91 | U150: =$B$5*MAX(0,T150-$B$6) -> 5528.1519 | V150: =Y149 -> 0 | W150: =IF(V150<=0,0,MIN(U150,V150)) -> 0 | X150: =W150/(1+$B$8)^S150 -> 0 | Y150: =MAX(0,V150-W150) -> 0 | AA150: =AA149+1 -> 12 | AB150: =$F$18*(1+$B$7)^(AA150-1) -> 19740.382 | AC150: =$B$5*MAX(0,AB150-$B$6) -> 0 | AD150: =AG149 -> 9250 | AE150: =IF(AD150<=0,0,MIN(AC150,AD150)) -> 0 | AF150: =AE150/(1+$B$8)^AA150 -> 0 | AG150: =MAX(0,AD150-AE150) -> 9250 | AI150: =AI149+1 -> 12 | AJ150: =$F$19*(1+$B$7)^(AI150-1) -> 35820.545 | AK150: =$B$5*MAX(0,AJ150-$B$6) -> 767.29901 | AL150: =AO149 -> 4720.7296 | AM150: =IF(AL150<=0,0,MIN(AK150,AL150)) -> 767.29901 | AN150: =AM150/(1+$B$8)^AI150 -> 538.16809 | AO150: =MAX(0,AL150-AM150) -> 3953.4306
K151: =K150+1 -> 13 | L151: =$F$16*(1+$B$7)^(K151-1) -> 31743.382 | M151: =$B$5*MAX(0,L151-$B$6) -> 400.35437 | N151: =Q150 -> 7955.9904 | O151: =IF(N151<=0,0,MIN(M151,N151)) -> 400.35437 | P151: =O151/(1+$B$8)^K151 -> 272.62185 | Q151: =MAX(0,N151-O151) -> 7555.6361 | S151: =S150+1 -> 13 | T151: =$F$17*(1+$B$7)^(S151-1) -> 90493.288 | U151: =$B$5*MAX(0,T151-$B$6) -> 5687.8459 | V151: =Y150 -> 0 | W151: =IF(V151<=0,0,MIN(U151,V151)) -> 0 | X151: =W151/(1+$B$8)^S151 -> 0 | Y151: =MAX(0,V151-W151) -> 0 | AA151: =AA150+1 -> 13 | AB151: =$F$18*(1+$B$7)^(AA151-1) -> 20135.19 | AC151: =$B$5*MAX(0,AB151-$B$6) -> 0 | AD151: =AG150 -> 9250 | AE151: =IF(AD151<=0,0,MIN(AC151,AD151)) -> 0 | AF151: =AE151/(1+$B$8)^AA151 -> 0 | AG151: =MAX(0,AD151-AE151) -> 9250 | AI151: =AI150+1 -> 13 | AJ151: =$F$19*(1+$B$7)^(AI151-1) -> 36536.955 | AK151: =$B$5*MAX(0,AJ151-$B$6) -> 831.77599 | AL151: =AO150 -> 3953.4306 | AM151: =IF(AL151<=0,0,MIN(AK151,AL151)) -> 831.77599 | AN151: =AM151/(1+$B$8)^AI151 -> 566.39897 | AO151: =MAX(0,AL151-AM151) -> 3121.6547
... K167: =K166+1 -> 29 | L167: =$F$16*(1+$B$7)^(K167-1) -> 43576.861 | M167: =$B$5*MAX(0,L167-$B$6) -> 1465.3675 | N167: =Q166 -> 0 | O167: =IF(N167<=0,0,MIN(M167,N167)) -> 0 | P167: =O167/(1+$B$8)^K167 -> 0 | Q167: =MAX(0,N167-O167) -> 0 | S167: =S166+1 -> 29 | T167: =$F$17*(1+$B$7)^(S167-1) -> 124227.89 | U167: =$B$5*MAX(0,T167-$B$6) -> 8723.9603 | V167: =Y166 -> 0 | W167: =IF(V167<=0,0,MIN(U167,V167)) -> 0 | X167: =W167/(1+$B$8)^S167 -> 0 | Y167: =MAX(0,V167-W167) -> 0 | AA167: =AA166+1 -> 29 | AB167: =$F$18*(1+$B$7)^(AA167-1) -> 27641.301 | AC167: =$B$5*MAX(0,AB167-$B$6) -> 31.167105 | AD167: =AG166 -> 9250 | AE167: =IF(AD167<=0,0,MIN(AC167,AD167)) -> 31.167105 | AF167: =AE167/(1+$B$8)^AA167 -> 13.225648 | AG167: =MAX(0,AD167-AE167) -> 9218.8329 | AI167: =AI166+1 -> 29 | AJ167: =$F$19*(1+$B$7)^(AI167-1) -> 50157.41 | AK167: =$B$5*MAX(0,AJ167-$B$6) -> 2057.6169 | AL167: =AO166 -> 0 | AM167: =IF(AL167<=0,0,MIN(AK167,AL167)) -> 0 | AN167: =AM167/(1+$B$8)^AI167 -> 0 | AO167: =MAX(0,AL167-AM167) -> 0
K168: =K167+1 -> 30 | L168: =$F$16*(1+$B$7)^(K168-1) -> 44448.398 | M168: =$B$5*MAX(0,L168-$B$6) -> 1543.8058 | N168: =Q167 -> 0 | O168: =IF(N168<=0,0,MIN(M168,N168)) -> 0 | P168: =O168/(1+$B$8)^K168 -> 0 | Q168: =MAX(0,N168-O168) -> 0 | S168: =S167+1 -> 30 | T168: =$F$9*(1+$B$7)^(S168-1) -> 27419.823 | U168: =$B$5*MAX(0,T168-$B$6) -> 11.234105 | V168: =Y167 -> 0 | W168: =IF(V168<=0,0,MIN(U168,V168)) -> 0 | X168: =W168/(1+$B$8)^S168 -> 0 | Y168: =MAX(0,V168-W168) -> 0 | AA168: =AA167+1 -> 30 | AB168: =$F$18*(1+$B$7)^(AA168-1) -> 28194.127 | AC168: =$B$5*MAX(0,AB168-$B$6) -> 80.921447 | AD168: =AG167 -> 9218.8329 | AE168: =IF(AD168<=0,0,MIN(AC168,AD168)) -> 80.921447 | AF168: =AE168/(1+$B$8)^AA168 -> 33.338565 | AG168: =MAX(0,AD168-AE168) -> 9137.9114 | AI168: =AI167+1 -> 30 | AJ168: =$F$19*(1+$B$7)^(AI168-1) -> 51160.558 | AK168: =$B$5*MAX(0,AJ168-$B$6) -> 2147.9002 | AL168: =AO167 -> 0 | AM168: =IF(AL168<=0,0,MIN(AK168,AL168)) -> 0 | AN168: =AM168/(1+$B$8)^AI168 -> 0 | AO168: =MAX(0,AL168-AM168) -> 0
K172: Year | L172: Income | M172: raw repayment | N172: Opening balance | O172: actual repayment | P172: discounted payment | Q172: Closing balance | S172: Year | T172: Income | U172: raw repayment | V172: Opening balance | W172: actual repayment | X172: discounted payment | Y172: Closing balance | AA172: Year | AB172: Income | AC172: raw repayment | AD172: Opening balance | AE172: actual repayment | AF172: discounted payment | AG172: Closing balance | AI172: Year | AJ172: Income | AK172: raw repayment | AL172: Opening balance | AM172: actual repayment | AN172: discounted payment | AO172: Closing balance
K173: 1 | L173: =$F$20*(1+$B$7)^(K173-1) -> 50396 | M173: =$B$5*MAX(0,L173-$B$6) -> 2079.09 | N173: =$B$2 -> 9250 | O173: =MIN(M173,N173) -> 2079.09 | P173: =O173/(1+$B$8)^K173 -> 2018.534 | Q173: =N173-O173 -> 7170.91 | S173: 1 | T173: =$F$21*(1+$B$7)^(S173-1) -> 18271.56 | U173: =$B$5*MAX(0,T173-$B$6) -> 0 | V173: =$B$2 -> 9250 | W173: =MIN(U173,V173) -> 0 | X173: =W173/(1+$B$8)^S173 -> 0 | Y173: =V173-W173 -> 9250 | AA173: 1 | AB173: =$F$22*(1+$B$7)^(AA173-1) -> 21343.48 | AC173: =$B$5*MAX(0,AB173-$B$6) -> 0 | AD173: =$B$2 -> 9250 | AE173: =MIN(AC173,AD173) -> 0 | AF173: =AE173/(1+$B$8)^AA173 -> 0 | AG173: =AD173-AE173 -> 9250 | AI173: 1 | AJ173: =$F$23*(1+$B$7)^(AI173-1) -> 18152.88 | AK173: =$B$5*MAX(0,AJ173-$B$6) -> 0 | AL173: =$B$2 -> 9250 | AM173: =MIN(AK173,AL173) -> 0 | AN173: =AM173/(1+$B$8)^AI173 -> 0 | AO173: =AL173-AM173 -> 9250
K174: =K173+1 -> 2 | L174: =$F$20*(1+$B$7)^(K174-1) -> 51403.92 | M174: =$B$5*MAX(0,L174-$B$6) -> 2169.8028 | N174: =Q173 -> 7170.91 | O174: =IF(N174<=0,0,MIN(M174,N174)) -> 2169.8028 | P174: =O174/(1+$B$8)^K174 -> 2045.2472 | Q174: =MAX(0,N174-O174) -> 5001.1072 | S174: =S173+1 -> 2 | T174: =$F$21*(1+$B$7)^(S174-1) -> 18636.991 | U174: =$B$5*MAX(0,T174-$B$6) -> 0 | V174: =Y173 -> 9250 | W174: =IF(V174<=0,0,MIN(U174,V174)) -> 0 | X174: =W174/(1+$B$8)^S174 -> 0 | Y174: =MAX(0,V174-W174) -> 9250 | AA174: =AA173+1 -> 2 | AB174: =$F$22*(1+$B$7)^(AA174-1) -> 21770.35 | AC174: =$B$5*MAX(0,AB174-$B$6) -> 0 | AD174: =AG173 -> 9250 | AE174: =IF(AD174<=0,0,MIN(AC174,AD174)) -> 0 | AF174: =AE174/(1+$B$8)^AA174 -> 0 | AG174: =MAX(0,AD174-AE174) -> 9250 | AI174: =AI173+1 -> 2 | AJ174: =$F$23*(1+$B$7)^(AI174-1) -> 18515.938 | AK174: =$B$5*MAX(0,AJ174-$B$6) -> 0 | AL174: =AO173 -> 9250 | AM174: =IF(AL174<=0,0,MIN(AK174,AL174)) -> 0 | AN174: =AM174/(1+$B$8)^AI174 -> 0 | AO174: =MAX(0,AL174-AM174) -> 9250
...

Sheet Elasticities
A1: betas from models | G1: k_j s | M1: Elasticities
A2: Country | B2: Estimate_TWFE | C2: Estimate_controls | D2: Estimate_Pooled | G2: =Country_PV!D1 -> Country | H2: =Country_PV!E1 -> Wage_EURO | I2: =Country_PV!F1 -> wage_gbp | J2: =Country_PV!G1 -> PV_loan | K2: =Country_PV!H1 -> k_i | M2: Country | N2: Estimate_TWFE | O2: Estimate_controls | P2: Estimate_Pooled | Q2: k_i | R2: elasticity_TWFE_new | S2: elasticity_controls_new | T2: elasticity_Pooled_new | U2: elasticity_TWFE_old | V2: elasticity_controls_old | W2: elasticity_Pooled_old
A3: Austria | B3: -0.548534 | C3: -0.502849 | D3: -0.96075537 | G3: =Country_PV!D2 -> Belgium | H3: =Country_PV!E2 -> 59632 | I3: =Country_PV!F2 -> 51283.52 | J3: =Country_PV!G2 -> 8579.3385 | K3: =Country_PV!H2 -> 0.95073548 | M3: Belgium | N3: =INDEX($B$3:$B$28,MATCH(M3,$A$3:$A$28,0)) -> -0.602657 | O3: =INDEX($C$3:$C$28,MATCH(M3,$A$3:$A$28,0)) -> -0.575323 | P3: =INDEX($D$3:$D$28,MATCH(M3,$A$3:$A$28,0)) -> -0.43381198 | Q3: =INDEX($K$3:$K$28,MATCH(M3,$G$3:$G$28,0)) -> 0.95073548 | R3: =N3/Q3 -> -0.63388504 | S3: =O3/Q3 -> -0.60513467 | T3: =P3/Q3 -> -0.45629094 | U3: =N3/(LN(22200)-LN(9250)) -> -0.68838209 | V3: =O3/(LN(22200)-LN(9250)) -> -0.65715996 | W3: =P3/(LN(22200)-LN(9250)) -> -0.49551967
A4: Belgium | B4: -0.602657 | C4: -0.575323 | D4: -0.43381198 | G4: =Country_PV!D3 -> Bulgaria | H4: =Country_PV!E3 -> 15387 | I4: =Country_PV!F3 -> 13232.82 | J4: =Country_PV!G3 -> 1 | K4: =Country_PV!H3 -> 10.007848 | M4: Bulgaria | N4: =INDEX($B$3:$B$28,MATCH(M4,$A$3:$A$28,0)) -> -1.887146 | O4: =INDEX($C$3:$C$28,MATCH(M4,$A$3:$A$28,0)) -> -1.785586 | P4: =INDEX($D$3:$D$28,MATCH(M4,$A$3:$A$28,0)) -> -1.0063262 | Q4: =INDEX($K$3:$K$28,MATCH(M4,$G$3:$G$28,0)) -> 10.007848 | R4: =N4/Q4 -> -0.18856662 | S4: =O4/Q4 -> -0.17841858 | T4: =P4/Q4 -> -0.10055371 | U4: =N4/(LN(22200)-LN(9250)) -> -2.1555835 | V4: =O4/(LN(22200)-LN(9250)) -> -2.0395771 | W4: =P4/(LN(22200)-LN(9250)) -> -1.1494713
A5: Bulgaria | B5: -1.887146 | C5: -1.785586 | D5: -1.0063262 | G5: =Country_PV!D4 -> Czechia | H5: =Country_PV!E4 -> 23998 | I5: =Country_PV!F4 -> 20638.28 | J5: =Country_PV!G4 -> 3021.0957 | K5: =Country_PV!H4 -> 1.9944727 | M5: Czechia | N5: =INDEX($B$3:$B$28,MATCH(M5,$A$3:$A$28,0)) -> -1.137201 | O5: =INDEX($C$3:$C$28,MATCH(M5,$A$3:$A$28,0)) -> -1.075068 | P5: =INDEX($D$3:$D$28,MATCH(M5,$A$3:$A$28,0)) -> -0.90086981 | Q5: =INDEX($K$3:$K$28,MATCH(M5,$G$3:$G$28,0)) -> 1.9944727 | R5: =N5/Q5 -> -0.57017626 | S5: =O5/Q5 -> -0.53902367 | T5: =P5/Q5 -> -0.4516832 | U5: =N5/(LN(22200)-LN(9250)) -> -1.2989624 | V5: =O5/(LN(22200)-LN(9250)) -> -1.2279913 | W5: =P5/(LN(22200)-LN(9250)) -> -1.0290143
A6: Croatia | B6: -1.654745 | C6: -1.53452 | D6: -2.5720774 | G6: =Country_PV!D5 -> Denmark | H6: =Country_PV!E5 -> 71565 | I6: =Country_PV!F5 -> 61545.9 | J6: =Country_PV!G5 -> 8724.5305 | K6: =Country_PV!H5 -> 0.93395363 | M6: Denmark | N6: =INDEX($B$3:$B$28,MATCH(M6,$A$3:$A$28,0)) -> -1.046503 | O6: =INDEX($C$3:$C$28,MATCH(M6,$A$3:$A$28,0)) -> -1.029858 | P6: =INDEX($D$3:$D$28,MATCH(M6,$A$3:$A$28,0)) -> -1.6091993 | Q6: =INDEX($K$3:$K$28,MATCH(M6,$G$3:$G$28,0)) -> 0.93395363 | R6: =N6/Q6 -> -1.1205085 | S6: =O6/Q6 -> -1.1026864 | T6: =P6/Q6 -> -1.722997 | U6: =N6/(LN(22200)-LN(9250)) -> -1.1953631 | V6: =O6/(LN(22200)-LN(9250)) -> -1.1763504 | W6: =P6/(LN(22200)-LN(9250)) -> -1.8381002
A7: Cyprus | B7: -0.902163 | C7: -0.946609 | D7: 0.25508166 | G7: =Country_PV!D6 -> Germany | H7: =Country_PV!E6 -> 53791 | I7: =Country_PV!F6 -> 46260.26 | J7: =Country_PV!G6 -> 8456.3829 | K7: =Country_PV!H6 -> 0.96517076 | M7: Germany | N7: =INDEX($B$3:$B$28,MATCH(M7,$A$3:$A$28,0)) -> -0.6815 | O7: =INDEX($C$3:$C$28,MATCH(M7,$A$3:$A$28,0)) -> -0.581445 | P7: =INDEX($D$3:$D$28,MATCH(M7,$A$3:$A$28,0)) -> 0.65222662 | Q7: =INDEX($K$3:$K$28,MATCH(M7,$G$3:$G$28,0)) -> 0.96517076 | R7: =N7/Q7 -> -0.70609267 | S7: =O7/Q7 -> -0.60242708 | T7: =P7/Q7 -> 0.67576294 | U7: =N7/(LN(22200)-LN(9250)) -> -0.77844013 | V7: =O7/(LN(22200)-LN(9250)) -> -0.66415278 | W7: =P7/(LN(22200)-LN(9250)) -> 0.74500276
A8: Czechia | B8: -1.137201 | C8: -1.075068 | D8: -0.90086981 | G8: =Country_PV!D7 -> Estonia | H8: =Country_PV!E7 -> 26546 | I8: =Country_PV!F7 -> 22829.56 | J8: =Country_PV!G7 -> 4804.714 | K8: =Country_PV!H7 -> 1.5304948 | M8: Estonia | N8: =INDEX($B$3:$B$28,MATCH(M8,$A$3:$A$28,0)) -> -1.447445 | O8: =INDEX($C$3:$C$28,MATCH(M8,$A$3:$A$28,0)) -> -1.407405 | P8: =INDEX($D$3:$D$28,MATCH(M8,$A$3:$A$28,0)) -> -2.2370894 | Q8: =INDEX($K$3:$K$28,MATCH(M8,$G$3:$G$28,0)) -> 1.5304948 | R8: =N8/Q8 -> -0.94573665 | S8: =O8/Q8 -> -0.91957517 | T8: =P8/Q8 -> -1.4616773 | U8: =N8/(LN(22200)-LN(9250)) -> -1.6533372 | V8: =O8/(LN(22200)-LN(9250)) -> -1.6076017 | W8: =P8/(LN(22200)-LN(9250)) -> -2.5553048
A9: Denmark | B9: -1.046503 | C9: -1.029858 | D9: -1.6091993 | G9: =Country_PV!D8 -> Ireland | H9: =Country_PV!E8 -> 61051 | I9: =Country_PV!F8 -> 52503.86 | J9: =Country_PV!G8 -> N/a | K9: =Country_PV!H8 -> N/a | M9: Ireland | N9: =INDEX($B$3:$B$28,MATCH(M9,$A$3:$A$28,0)) -> #N/A | O9: =INDEX($C$3:$C$28,MATCH(M9,$A$3:$A$28,0)) -> #N/A | P9: =INDEX($D$3:$D$28,MATCH(M9,$A$3:$A$28,0)) -> #N/A | Q9: =INDEX($K$3:$K$28,MATCH(M9,$G$3:$G$28,0)) -> N/a | R9: =N9/Q9 -> #N/A | S9: =O9/Q9 -> #N/A | T9: =P9/Q9 -> #N/A | U9: =N9/(LN(22200)-LN(9250)) -> #N/A | V9: =O9/(LN(22200)-LN(9250)) -> #N/A | W9: =P9/(LN(22200)-LN(9250)) -> #N/A
A10: Estonia | B10: -1.447445 | C10: -1.407405 | D10: -2.2370894 | G10: =Country_PV!D9 -> Greece | H10: =Country_PV!E9 -> 17954 | I10: =Country_PV!F9 -> 15440.44 | J10: =Country_PV!G9 -> 4.6283026 | K10: =Country_PV!H9 -> 8.4756574 | M10: Greece | N10: =INDEX($B$3:$B$28,MATCH(M10,$A$3:$A$28,0)) -> -0.86575 | O10: =INDEX($C$3:$C$28,MATCH(M10,$A$3:$A$28,0)) -> -0.718908 | P10: =INDEX($D$3:$D$28,MATCH(M10,$A$3:$A$28,0)) -> 0.10535878 | Q10: =INDEX($K$3:$K$28,MATCH(M10,$G$3:$G$28,0)) -> 8.4756574 | R10: =N10/Q10 -> -0.10214547 | S10: =O10/Q10 -> -0.084820323 | T10: =P10/Q10 -> 0.01243075 | U10: =N10/(LN(22200)-LN(9250)) -> -0.98889882 | V10: =O10/(LN(22200)-LN(9250)) -> -0.82116924 | W10: =P10/(LN(22200)-LN(9250)) -> 0.12034556
A11: Finland | B11: -1.756347 | C11: -1.620129 | D11: -1.8170332 | G11: =Country_PV!D10 -> Spain | H11: =Country_PV!E10 -> 33700 | I11: =Country_PV!F10 -> 28982 | J11: =Country_PV!G10 -> 6801.1286 | K11: =Country_PV!H10 -> 1.1830037 | M11: Spain | N11: =INDEX($B$3:$B$28,MATCH(M11,$A$3:$A$28,0)) -> -0.507701 | O11: =INDEX($C$3:$C$28,MATCH(M11,$A$3:$A$28,0)) -> -0.473719 | P11: =INDEX($D$3:$D$28,MATCH(M11,$A$3:$A$28,0)) -> 0.96454423 | Q11: =INDEX($K$3:$K$28,MATCH(M11,$G$3:$G$28,0)) -> 1.1830037 | R11: =N11/Q11 -> -0.42916264 | S11: =O11/Q11 -> -0.40043745 | T11: =P11/Q11 -> 0.8153349 | U11: =N11/(LN(22200)-LN(9250)) -> -0.57991905 | V11: =O11/(LN(22200)-LN(9250)) -> -0.54110327 | W11: =P11/(LN(22200)-LN(9250)) -> 1.1017461
A12: France | B12: -0.597106 | C12: -0.535495 | D12: 1.178993 | G12: =Country_PV!D11 -> France | H12: =Country_PV!E11 -> 43790 | I12: =Country_PV!F11 -> 37659.4 | J12: =Country_PV!G11 -> 8054.806 | K12: =Country_PV!H11 -> 1.0138234 | M12: France | N12: =INDEX($B$3:$B$28,MATCH(M12,$A$3:$A$28,0)) -> -0.597106 | O12: =INDEX($C$3:$C$28,MATCH(M12,$A$3:$A$28,0)) -> -0.535495 | P12: =INDEX($D$3:$D$28,MATCH(M12,$A$3:$A$28,0)) -> 1.178993 | Q12: =INDEX($K$3:$K$28,MATCH(M12,$G$3:$G$28,0)) -> 1.0138234 | R12: =N12/Q12 -> -0.58896453 | S12: =O12/Q12 -> -0.52819359 | T12: =P12/Q12 -> 1.1629175 | U12: =N12/(LN(22200)-LN(9250)) -> -0.68204149 | V12: =O12/(LN(22200)-LN(9250)) -> -0.61166662 | W12: =P12/(LN(22200)-LN(9250)) -> 1.3466991
A13: Germany | B13: -0.6815 | C13: -0.581445 | D13: 0.65222662 | G13: =Country_PV!D12 -> Croatia | H13: =Country_PV!E12 -> 23446 | I13: =Country_PV!F12 -> 20163.56 | J13: =Country_PV!G12 -> 2527.4656 | K13: =Country_PV!H12 -> 2.1728752 | M13: Croatia | N13: =INDEX($B$3:$B$28,MATCH(M13,$A$3:$A$28,0)) -> -1.654745 | O13: =INDEX($C$3:$C$28,MATCH(M13,$A$3:$A$28,0)) -> -1.53452 | P13: =INDEX($D$3:$D$28,MATCH(M13,$A$3:$A$28,0)) -> -2.5720774 | Q13: =INDEX($K$3:$K$28,MATCH(M13,$G$3:$G$28,0)) -> 2.1728752 | R13: =N13/Q13 -> -0.76154626 | S13: =O13/Q13 -> -0.70621634 | T13: =P13/Q13 -> -1.1837207 | U13: =N13/(LN(22200)-LN(9250)) -> -1.8901246 | V13: =O13/(LN(22200)-LN(9250)) -> -1.7527982 | W13: =P13/(LN(22200)-LN(9250)) -> -2.9379431
A14: Greece | B14: -0.86575 | C14: -0.718908 | D14: 0.10535878 | G14: =Country_PV!D13 -> Italy | H14: =Country_PV!E13 -> 33523 | I14: =Country_PV!F13 -> 28829.78 | J14: =Country_PV!G13 -> 6758.7787 | K14: =Country_PV!H13 -> 1.1892501 | M14: Italy | N14: =INDEX($B$3:$B$28,MATCH(M14,$A$3:$A$28,0)) -> -0.925037 | O14: =INDEX($C$3:$C$28,MATCH(M14,$A$3:$A$28,0)) -> -0.808428 | P14: =INDEX($D$3:$D$28,MATCH(M14,$A$3:$A$28,0)) -> 0.67669479 | Q14: =INDEX($K$3:$K$28,MATCH(M14,$G$3:$G$28,0)) -> 1.1892501 | R14: =N14/Q14 -> -0.77783219 | S14: =O14/Q14 -> -0.67977964 | T14: =P14/Q14 -> 0.56900966 | U14: =N14/(LN(22200)-LN(9250)) -> -1.0566191 | V14: =O14/(LN(22200)-LN(9250)) -> -0.92342304 | W14: =P14/(LN(22200)-LN(9250)) -> 0.7729514
... A28: Sweden | B28: -0.966849 | C28: -0.927258 | D28: -0.62943314 | G28: =Country_PV!D27 -> Sweden | H28: =Country_PV!E27 -> 46525 | I28: =Country_PV!F27 -> 40011.5 | J28: =Country_PV!G27 -> 8202.1973 | K28: =Country_PV!H27 -> 0.99569021 | M28: Sweden | N28: =INDEX($B$3:$B$28,MATCH(M28,$A$3:$A$28,0)) -> -0.966849 | O28: =INDEX($C$3:$C$28,MATCH(M28,$A$3:$A$28,0)) -> -0.927258 | P28: =INDEX($D$3:$D$28,MATCH(M28,$A$3:$A$28,0)) -> -0.62943314 | Q28: =INDEX($K$3:$K$28,MATCH(M28,$G$3:$G$28,0)) -> 0.99569021 | R28: =N28/Q28 -> -0.97103395 | S28: =O28/Q28 -> -0.93127158 | T28: =P28/Q28 -> -0.6321576 | U28: =N28/(LN(22200)-LN(9250)) -> -1.1043787 | V28: =O28/(LN(22200)-LN(9250)) -> -1.059156 | W28: =P28/(LN(22200)-LN(9250)) -> -0.71896701

Sheet WB_correlations
A1: Link: https://data.worldbank.org/indicator/NY.GDP.PCAP.PP.KD | D1: Elasticities derived in previous sheets | N1: SUMMARY OUTPUT | P1: =E2 -> elasticity_TWFE_new | T1: SUMMARY OUTPUT | V1: =F2 -> elasticity_controls_new | Z1: SUMMARY OUTPUT | AB1: =G2 -> elasticity_Pooled_new
A2: Country Name | B2: 2022 | D2: =Elasticities!M2 -> Country | E2: =Elasticities!R2 -> elasticity_TWFE_new | F2: =Elasticities!S2 -> elasticity_controls_new | G2: =Elasticities!T2 -> elasticity_Pooled_new | H2: =Elasticities!U2 -> elasticity_TWFE_old | I2: =Elasticities!V2 -> elasticity_controls_old | J2: =Elasticities!W2 -> elasticity_Pooled_old | K2: GDP_per_cap
A3: Aruba | B3: 38979.836 | D3: =Elasticities!M3 -> Belgium | E3: =Elasticities!R3 -> -0.63388504 | F3: =Elasticities!S3 -> -0.60513467 | G3: =Elasticities!T3 -> -0.45629094 | H3: =Elasticities!U3 -> -0.68838209 | I3: =Elasticities!V3 -> -0.65715996 | J3: =Elasticities!W3 -> -0.49551967 | K3: =LN(VLOOKUP(D3,$A$3:$B$267,2,FALSE)) -> 11.04391 | N3: Regression Statistics | T3: Regression Statistics | Z3: Regression Statistics
A4: Africa Eastern and Southern | B4: 4106.5019 | D4: =Elasticities!M4 -> Bulgaria | E4: =Elasticities!R4 -> -0.18856662 | F4: =Elasticities!S4 -> -0.17841858 | G4: =Elasticities!T4 -> -0.10055371 | H4: =Elasticities!U4 -> -2.1555835 | I4: =Elasticities!V4 -> -2.0395771 | J4: =Elasticities!W4 -> -1.1494713 | K4: =LN(VLOOKUP(D4,$A$3:$B$267,2,FALSE)) -> 10.386956 | N4: Multiple R | O4: 0.25187648 | T4: Multiple R | U4: 0.30442605 | Z4: Multiple R | AA4: 0.2300947
A5: Afghanistan | B5: 1981.7102 | D5: =Elasticities!M5 -> Czechia | E5: =Elasticities!R5 -> -0.57017626 | F5: =Elasticities!S5 -> -0.53902367 | G5: =Elasticities!T5 -> -0.4516832 | H5: =Elasticities!U5 -> -1.2989624 | I5: =Elasticities!V5 -> -1.2279913 | J5: =Elasticities!W5 -> -1.0290143 | K5: =LN(VLOOKUP(D5,$A$3:$B$267,2,FALSE)) -> 10.787062 | N5: R Square | O5: 0.063441763 | T5: R Square | U5: 0.092675222 | Z5: R Square | AA5: 0.052943569
A6: Africa Western and Central | B6: 5806.1729 | D6: =Elasticities!M6 -> Denmark | E6: =Elasticities!R6 -> -1.1205085 | F6: =Elasticities!S6 -> -1.1026864 | G6: =Elasticities!T6 -> -1.722997 | H6: =Elasticities!U6 -> -1.1953631 | I6: =Elasticities!V6 -> -1.1763504 | J6: =Elasticities!W6 -> -1.8381002 | K6: =LN(VLOOKUP(D6,$A$3:$B$267,2,FALSE)) -> 11.148727 | N6: Adjusted R Square | O6: 0.02272184 | T6: Adjusted R Square | U6: 0.053226319 | Z6: Adjusted R Square | AA6: 0.011767202
A7: Angola | B7: 8950.1426 | D7: =Elasticities!M7 -> Germany | E7: =Elasticities!R7 -> -0.70609267 | F7: =Elasticities!S7 -> -0.60242708 | G7: =Elasticities!T7 -> 0.67576294 | H7: =Elasticities!U7 -> -0.77844013 | I7: =Elasticities!V7 -> -0.66415278 | J7: =Elasticities!W7 -> 0.74500276 | K7: =LN(VLOOKUP(D7,$A$3:$B$267,2,FALSE)) -> 11.061564 | N7: Standard Error | O7: 0.39374614 | T7: Standard Error | U7: 0.36775005 | Z7: Standard Error | AA7: 0.94275897
A8: Albania | B8: 19388.873 | D8: =Elasticities!M8 -> Estonia | E8: =Elasticities!R8 -> -0.94573665 | F8: =Elasticities!S8 -> -0.91957517 | G8: =Elasticities!T8 -> -1.4616773 | H8: =Elasticities!U8 -> -1.6533372 | I8: =Elasticities!V8 -> -1.6076017 | J8: =Elasticities!W8 -> -2.5553048 | K8: =LN(VLOOKUP(D8,$A$3:$B$267,2,FALSE)) -> 10.671942 | N8: Observations | O8: 25 | T8: Observations | U8: 25 | Z8: Observations | AA8: 25
A9: Andorra | B9: 63913.384 | D9: =Elasticities!M10 -> Greece | E9: =Elasticities!R10 -> -0.10214547 | F9: =Elasticities!S10 -> -0.084820323 | G9: =Elasticities!T10 -> 0.01243075 | H9: =Elasticities!U10 -> -0.98889882 | I9: =Elasticities!V10 -> -0.82116924 | J9: =Elasticities!W10 -> 0.12034556 | K9: =LN(VLOOKUP(D9,$A$3:$B$267,2,FALSE)) -> 10.486578
A10: Arab World | B10: 16905.49 | D10: =Elasticities!M11 -> Spain | E10: =Elasticities!R11 -> -0.42916264 | F10: =Elasticities!S11 -> -0.40043745 | G10: =Elasticities!T11 -> 0.8153349 | H10: =Elasticities!U11 -> -0.57991905 | I10: =Elasticities!V11 -> -0.54110327 | J10: =Elasticities!W11 -> 1.1017461 | K10: =LN(VLOOKUP(D10,$A$3:$B$267,2,FALSE)) -> 10.752216 | N10: ANOVA | T10: ANOVA | Z10: ANOVA
A11: United Arab Emirates | B11: 70075.63 | D11: =Elasticities!M12 -> France | E11: =Elasticities!R12 -> -0.58896453 | F11: =Elasticities!S12 -> -0.52819359 | G11: =Elasticities!T12 -> 1.1629175 | H11: =Elasticities!U12 -> -0.68204149 | I11: =Elasticities!V12 -> -0.61166662 | J11: =Elasticities!W12 -> 1.3466991 | K11: =LN(VLOOKUP(D11,$A$3:$B$267,2,FALSE)) -> 10.890681 | O11: df | P11: SS | Q11: MS | R11: F | S11: Significance F | U11: df | V11: SS | W11: MS | X11: F | Y11: Significance F | AA11: df | AB11: SS | AC11: MS | AD11: F | AE11: Significance F
A12: Argentina | B12: 27825.027 | D12: =Elasticities!M13 -> Croatia | E12: =Elasticities!R13 -> -0.76154626 | F12: =Elasticities!S13 -> -0.70621634 | G12: =Elasticities!T13 -> -1.1837207 | H12: =Elasticities!U13 -> -1.8901246 | I12: =Elasticities!V13 -> -1.7527982 | J12: =Elasticities!W13 -> -2.9379431 | K12: =LN(VLOOKUP(D12,$A$3:$B$267,2,FALSE)) -> 10.593229 | N12: Regression | O12: 1 | P12: 0.24154659 | Q12: 0.24154659 | R12: 1.558003 | S12: 0.22451558 | T12: Regression | U12: 1 | V12: 0.31771242 | W12: 0.31771242 | X12: 2.3492471 | Y12: 0.13898449 | Z12: Regression | AA12: 1 | AB12: 1.1427903 | AC12: 1.1427903 | AD12: 1.2857756 | AE12: 0.26850894
A13: Armenia | B13: 17886.178 | D13: =Elasticities!M14 -> Italy | E13: =Elasticities!R14 -> -0.77783219 | F13: =Elasticities!S14 -> -0.67977964 | G13: =Elasticities!T14 -> 0.56900966 | H13: =Elasticities!U14 -> -1.0566191 | I13: =Elasticities!V14 -> -0.92342304 | J13: =Elasticities!W14 -> 0.7729514 | K13: =LN(VLOOKUP(D13,$A$3:$B$267,2,FALSE)) -> 10.865389 | N13: Residual | O13: 23 | P13: 3.5658285 | Q13: 0.15503602 | T13: Residual | U13: 23 | V13: 3.1105223 | W13: 0.1352401 | Z13: Residual | AA13: 23 | AB13: 20.442273 | AC13: 0.88879447
A14: American Samoa | D14: =Elasticities!M15 -> Cyprus | E14: =Elasticities!R15 -> -0.61298791 | F14: =Elasticities!S15 -> -0.6431874 | G14: =Elasticities!T15 -> 0.17331898 | H14: =Elasticities!U15 -> -1.0304914 | I14: =Elasticities!V15 -> -1.0812596 | J14: =Elasticities!W15 -> 0.29136581 | K14: =LN(VLOOKUP(D14,$A$3:$B$267,2,FALSE)) -> 10.832177 | N14: Total | O14: 24 | P14: 3.8073751 | T14: Total | U14: 24 | V14: 3.4282348 | Z14: Total | AA14: 24 | AB14: 21.585063
A15: Antigua and Barbuda | B15: 27941.785 | D15: =Elasticities!M16 -> Latvia | E15: =Elasticities!R16 -> -0.57571916 | F15: =Elasticities!S16 -> -0.52964993 | G15: =Elasticities!T16 -> -0.73442091 | H15: =Elasticities!U16 -> -1.726522 | I15: =Elasticities!V16 -> -1.5883651 | J15: =Elasticities!W16 -> -2.202452 | K15: =LN(VLOOKUP(D15,$A$3:$B$267,2,FALSE)) -> 10.537912
A16: Australia | B16: 60029.133 | D16: =Elasticities!M17 -> Lithuania | E16: =Elasticities!R17 -> -1.5601515 | F16: =Elasticities!S17 -> -1.5558776 | G16: =Elasticities!T17 -> -1.0132439 | H16: =Elasticities!U17 -> -2.482228 | I16: =Elasticities!V17 -> -2.4754282 | J16: =Elasticities!W17 -> -1.6120886 | K16: =LN(VLOOKUP(D16,$A$3:$B$267,2,FALSE)) -> 10.750454 | O16: Coefficients | P16: Standard Error | Q16: t Stat | R16: P-value | S16: Lower 95% | U16: Coefficients | V16: Standard Error | W16: t Stat | X16: P-value | Y16: Lower 95% | AA16: Coefficients | AB16: Standard Error | AC16: t Stat | AD16: P-value | AE16: Lower 95%
A17: Austria | B17: 65694.551 | D17: =Elasticities!M18 -> Luxembourg | E17: =Elasticities!R18 -> -0.53256139 | F17: =Elasticities!S18 -> -0.62126418 | G17: =Elasticities!T18 -> -1.336135 | H17: =Elasticities!U18 -> -0.56300697 | I17: =Elasticities!V18 -> -0.65678073 | J17: =Elasticities!W18 -> -1.4125195 | K17: =LN(VLOOKUP(D17,$A$3:$B$267,2,FALSE)) -> 11.794872 | N17: Intercept | O17: 3.0501716 | P17: 2.9914068 | Q17: 1.0196445 | R17: 0.31850331 | S17: -3.1380249 | T17: Intercept | U17: 3.6290329 | V17: 2.7939068 | W17: 1.2989098 | X17: 0.20684657 | Y17: -2.1506037 | Z17: Intercept | AA17: 7.5577928 | AB17: 7.162421 | AC17: 1.0552009 | AD17: 0.30229229 | AE17: -7.258804
A18: Azerbaijan | B18: 21051.244 | D18: =Elasticities!M19 -> Hungary | E18: =Elasticities!R19 -> -0.18071432 | F18: =Elasticities!S19 -> -0.16598094 | G18: =Elasticities!T19 -> -0.16729694 | H18: =Elasticities!U19 -> -1.2729958 | I18: =Elasticities!V19 -> -1.1692102 | J18: =Elasticities!W19 -> -1.1784804 | K18: =LN(VLOOKUP(D18,$A$3:$B$267,2,FALSE)) -> 10.611794 | N18: GDP_per_cap | O18: -0.34501952 | P18: 0.27641367 | Q18: -1.2481999 | R18: 0.22451558 | S18: -0.91682477 | T18: GDP_per_cap | U18: -0.39569477 | V18: 0.25816417 | W18: -1.5327254 | X18: 0.13898449 | Y18: -0.92974803 | Z18: GDP_per_cap | AA18: -0.75045816 | AB18: 0.66182609 | AC18: -1.1339205 | AD18: 0.26850894 | AE18: -2.1195497
A19: Burundi | B19: 1031.2541 | D19: =Elasticities!M20 -> Malta | E19: =Elasticities!R20 -> -0.30390047 | F19: =Elasticities!S20 -> -0.44608238 | G19: =Elasticities!T20 -> -1.9621616 | H19: =Elasticities!U20 -> -0.41312612 | I19: =Elasticities!V20 -> -0.60641 | J19: =Elasticities!W20 -> -2.6673871 | K19: =LN(VLOOKUP(D19,$A$3:$B$267,2,FALSE)) -> 10.94803
A20: Belgium | B20: 62561.781 | D20: =Elasticities!M21 -> Austria | E20: =Elasticities!R21 -> -0.57542304 | F20: =Elasticities!S21 -> -0.52749857 | G20: =Elasticities!T21 -> -1.0078514 | H20: =Elasticities!U21 -> -0.62656035 | I20: =Elasticities!V21 -> -0.57437688 | J20: =Elasticities!W21 -> -1.0974182 | K20: =LN(VLOOKUP(D20,$A$3:$B$267,2,FALSE)) -> 11.092771
A21: Benin | B21: 3588.3252 | D21: =Elasticities!M22 -> Poland | E21: =Elasticities!R22 -> -0.53479744 | F21: =Elasticities!S22 -> -0.49020643 | G21: =Elasticities!T22 -> -0.043359174 | H21: =Elasticities!U22 -> -1.905586 | I21: =Elasticities!V22 -> -1.7466997 | J21: =Elasticities!W22 -> -0.15449707 | K21: =LN(VLOOKUP(D21,$A$3:$B$267,2,FALSE)) -> 10.67833 | N21: SUMMARY OUTPUT | P21: =H2 -> elasticity_TWFE_old | T21: SUMMARY OUTPUT | V21: =I2 -> elasticity_controls_old | Z21: SUMMARY OUTPUT | AB21: =J2 -> elasticity_Pooled_old
A22: Burkina Faso | B22: 2469.1996 | D22: =Elasticities!M23 -> Portugal | E22: =Elasticities!R23 -> -0.53496547 | F22: =Elasticities!S23 -> -0.47609226 | G22: =Elasticities!T23 -> -0.049494291 | H22: =Elasticities!U23 -> -1.0727613 | I22: =Elasticities!V23 -> -0.95470342 | J22: =Elasticities!W23 -> -0.099250445 | K22: =LN(VLOOKUP(D22,$A$3:$B$267,2,FALSE)) -> 10.623054
A23: Bangladesh | B23: 7888.1639 | D23: =Elasticities!M24 -> Romania | E23: =Elasticities!R24 -> -0.5353287 | F23: =Elasticities!S24 -> -0.50095528 | G23: =Elasticities!T24 -> -0.11355059 | H23: =Elasticities!U24 -> -1.9548762 | I23: =Elasticities!V24 -> -1.8293537 | J23: =Elasticities!W24 -> -0.41465617 | K23: =LN(VLOOKUP(D23,$A$3:$B$267,2,FALSE)) -> 10.577885 | N23: Regression Statistics | T23: Regression Statistics | Z23: Regression Statistics
A24: Bulgaria | B24: 32433.794 | D24: =Elasticities!M25 -> Slovenia | E24: =Elasticities!R25 -> -1.1222056 | F24: =Elasticities!S25 -> -1.0343878 | G24: =Elasticities!T25 -> -2.7253957 | H24: =Elasticities!U25 -> -1.4615645 | I24: =Elasticities!V25 -> -1.3471903 | J24: =Elasticities!W25 -> -3.5495649 | K24: =LN(VLOOKUP(D24,$A$3:$B$267,2,FALSE)) -> 10.758968 | N24: Multiple R | O24: 0.55897998 | T24: Multiple R | U24: 0.50575873 | Z24: Multiple R | AA24: 0.039569074
A25: Bahrain | B25: 57572.998 | D25: =Elasticities!M26 -> Slovakia | E25: =Elasticities!R26 -> -0.4053959 | F25: =Elasticities!S26 -> -0.37366231 | G25: =Elasticities!T26 -> -0.41972951 | H25: =Elasticities!U26 -> -1.7320162 | I25: =Elasticities!V26 -> -1.5964374 | J25: =Elasticities!W26 -> -1.7932552 | K25: =LN(VLOOKUP(D25,$A$3:$B$267,2,FALSE)) -> 10.562688 | N25: R Square | O25: 0.31245862 | T25: R Square | U25: 0.25579189 | Z25: R Square | AA25: 0.0015657116
A26: Bahamas, The | B26: 34342.929 | D26: =Elasticities!M27 -> Finland | E26: =Elasticities!R27 -> -1.7904015 | F26: =Elasticities!S27 -> -1.6515423 | G26: =Elasticities!T27 -> -1.8522643 | H26: =Elasticities!U27 -> -2.006179 | I26: =Elasticities!V27 -> -1.8505846 | J26: =Elasticities!W27 -> -2.0754975 | K26: =LN(VLOOKUP(D26,$A$3:$B$267,2,FALSE)) -> 10.952004 | N26: Adjusted R Square | O26: 0.28256551 | T26: Adjusted R Square | U26: 0.22343502 | Z26: Adjusted R Square | AA26: -0.041844475
A27: Bosnia and Herzegovina | B27: 19298.197 | D27: =Elasticities!M28 -> Sweden | E27: =Elasticities!R28 -> -0.97103395 | F27: =Elasticities!S28 -> -0.93127158 | G27: =Elasticities!T28 -> -0.6321576 | H27: =Elasticities!U28 -> -1.1043787 | I27: =Elasticities!V28 -> -1.059156 | J27: =Elasticities!W28 -> -0.71896701 | K27: =LN(VLOOKUP(D27,$A$3:$B$267,2,FALSE)) -> 11.052293 | N27: Standard Error | O27: 0.48750557 | T27: Standard Error | U27: 0.47442183 | Z27: Standard Error | AA27: 1.3378384
A28: Belarus | B28: 26537.508 | N28: Observations | O28: 25 | T28: Observations | U28: 25 | Z28: Observations | AA28: 25
A29: Belize | B29: 12565.365
A30: Bermuda | B30: 98145.169 | N30: ANOVA | T30: ANOVA | Z30: ANOVA
A31: Bolivia | B31: 11487.715 | O31: df | P31: SS | Q31: MS | R31: F | S31: Significance F | U31: df | V31: SS | W31: MS | X31: F | Y31: Significance F | AA31: df | AB31: SS | AC31: MS | AD31: F | AE31: Significance F
A32: Brazil | B32: 18554.046 | N32: Regression | O32: 1 | P32: 2.4841662 | Q32: 2.4841662 | R32: 10.452532 | S32: 0.0036763039 | T32: Regression | U32: 1 | V32: 1.7793015 | W32: 1.7793015 | X32: 7.9053338 | Y32: 0.0099014271 | Z32: Regression | AA32: 1 | AB32: 0.064554639 | AC32: 0.064554639 | AD32: 0.036067839 | AE32: 0.85104162
A33: Barbados | B33: 20716.285 | N33: Residual | O33: 23 | P33: 5.4662186 | Q33: 0.23766168 | T33: Residual | U33: 23 | V33: 5.1767497 | W33: 0.22507607 | Z33: Residual | AA33: 23 | AB33: 41.165669 | AC33: 1.7898117
A34: Brunei Darussalam | B34: 76357.829 | N34: Total | O34: 24 | P34: 7.9503848 | T34: Total | U34: 24 | V34: 6.9560511 | Z34: Total | AA34: 24 | AB34: 41.230223
A35: Bhutan | B35: 14061.312
A36: Botswana | B36: 18647.374 | O36: Coefficients | P36: Standard Error | Q36: t Stat | R36: P-value | S36: Lower 95% | U36: Coefficients | V36: Standard Error | W36: t Stat | X36: P-value | Y36: Lower 95% | AA36: Coefficients | AB36: Standard Error | AC36: t Stat | AD36: P-value | AE36: Lower 95%
A37: Central African Republic | B37: 1136.8017 | N37: Intercept | O37: -13.262931 | P37: 3.7037252 | Q37: -3.5809707 | R37: 0.0015820765 | S37: -20.92467 | T37: Intercept | U37: -11.352917 | V37: 3.6043241 | W37: -3.1498047 | X37: 0.0044845698 | Y37: -18.809029 | Z37: Intercept | AA37: -2.9137536 | AB37: 10.163958 | AC37: -0.28667511 | AD37: 0.7769277 | AE37: -23.939502
A38: Canada | B38: 58321.061 | N38: GDP_per_cap | O38: 1.1064545 | P38: 0.34223372 | Q38: 3.2330376 | R38: 0.0036763039 | S38: 0.39849008 | T38: GDP_per_cap | U38: 0.93641418 | V38: 0.3330488 | W38: 2.8116425 | X38: 0.0099014271 | Y38: 0.24745024 | Z38: GDP_per_cap | AA38: 0.17836389 | AB38: 0.93917578 | AC38: 0.18991535 | AD38: 0.85104162 | AE38: -1.7644692
A39: Central Europe and the Baltics | B39: 41834.725
A40: Switzerland | B40: 82777.294
A41: Channel Islands
A42: Chile | B42: 29569.478
A43: China | B43: 21499.382
A44: Cote d'Ivoire | B44: 6272.264
A45: Cameroon | B45: 4843.6504
A46: Congo, Dem. Rep. | B46: 1484.3384
A47: Congo, Rep. | B47: 6205.105
A48: Colombia | B48: 18458.721
A49: Comoros | B49: 3399.2783
A50: Cabo Verde | B50: 8850.1067
A51: Costa Rica | B51: 24831.719
A52: Caribbean small states | B52: 27046.707
A53: Cuba
A54: Curacao | B54: 26734.646
A55: Cayman Islands | B55: 76818.8
A56: Cyprus | B56: 50623.797
A57: Czechia | B57: 48390.662
A58: Germany | B58: 63676.088
A59: Djibouti | B59: 6180.68
A60: Dominica | B60: 17550.801
A61: Denmark | B61: 69475.32
A62: Dominican Republic | B62: 22986.958
A63: Algeria | B63: 14782.2
A64: East Asia & Pacific (excluding high income) | B64: 18600.021
A65: Early-demographic dividend | B65: 11378.549
... A71: Euro area | B71: 56046.748
A72: Eritrea
A73: Spain | B73: 46733.481
A74: Estonia | B74: 43128.633
A75: Ethiopia | B75: 2655.5928
A76: European Union | B76: 53777.478
A77: Finland | B77: 57068.306
A78: Fiji | B78: 12118.318
A79: France | B79: 53673.814
A80: Faroe Islands | B80: 70256.719
A81: Micronesia, Fed. Sts. | B81: 3814.9908
A82: Gabon | B82: 18662.05
A83: United Kingdom | B83: 53139.151
A84: Georgia | B84: 20966.528
A85: Ghana | B85: 6728.4541
A86: Gibraltar
A87: Guinea | B87: 3792.0107
A88: Gambia, The | B88: 2863.1805
A89: Guinea-Bissau | B89: 2603.2402
A90: Equatorial Guinea | B90: 16932.771
A91: Greece | B91: 35831.344
A92: Grenada | B92: 16376.427
A93: Greenland | B93: 70681.225
A94: Guatemala | B94: 12147.931
A95: Guam
A96: Guyana | B96: 37068.199
A97: High income | B97: 56904.446
A98: Hong Kong SAR, China | B98: 64036.645
A99: Honduras | B99: 6352.5871
A100: Heavily indebted poor countries (HIPC) | B100: 3090.2615
A101: Croatia | B101: 39864.01
A102: Haiti | B102: 3057.4284
A103: Hungary | B103: 40610.971
A104: IBRD only | B104: 17005.368
A105: IDA & IBRD total | B105: 13682.566
...

Sheet WB_R_excel_check
A1: FROM R | X1: FROM EXCEL
A2: Country | B2: Wage_EURO | C2: wage_gbp | D2: PV_loan | E2: k_i | F2: Estimate_TWFE | G2: Estimate_controls | H2: Estimate_Pooled | I2: elasticity_new_TWFE | J2: elasticity_controls_new | K2: elasticity_new_Pooled | L2: elasticity_TWFE | M2: elasticity_controls | N2: elasticity_Pooled | O2: GDP_PPP | P2: gini | Q2: youth_unemp | R2: educ_spend_gdp | S2: tertiary_enroll | T2: net_migration | U2: log_gdp | X2: =WB_correlations!D2 -> Country | Y2: =WB_correlations!E2 -> elasticity_TWFE_new | Z2: =WB_correlations!F2 -> elasticity_controls_new | AA2: =WB_correlations!G2 -> elasticity_Pooled_new | AB2: =WB_correlations!H2 -> elasticity_TWFE_old | AC2: =WB_correlations!I2 -> elasticity_controls_old | AD2: =WB_correlations!J2 -> elasticity_Pooled_old | AE2: =WB_correlations!K2 -> GDP_per_cap | AG2: CHECK (difference)
A3: Belgium | B3: 59632 | C3: 51283.52 | D3: 8579.3385 | E3: 0.95073548 | F3: -0.602657 | G3: -0.575323 | H3: -0.43381198 | I3: -0.63388504 | J3: -0.60513467 | K3: -0.45629094 | L3: -0.68838209 | M3: -0.65715996 | N3: -0.49551967 | O3: 62561.781 | P3: 26.4 | Q3: 16.41 | R3: 6.2761102 | S3: 83.573647 | T3: 118615 | U3: 11.04391 | X3: =WB_correlations!D3 -> Belgium | Y3: =WB_correlations!E3 -> -0.63388504 | Z3: =WB_correlations!F3 -> -0.60513467 | AA3: =WB_correlations!G3 -> -0.45629094 | AB3: =WB_correlations!H3 -> -0.68838209 | AC3: =WB_correlations!I3 -> -0.65715996 | AD3: =WB_correlations!J3 -> -0.49551967 | AE3: =WB_correlations!K3 -> 11.04391 | AG3: =I3-Y3 -> 0 | AH3: =J3-Z3 -> 0 | AI3: =K3-AA3 -> -2.3160174e-10 | AJ3: =L3-AB3 -> 0 | AK3: =M3-AC3 -> 0 | AL3: =N3-AD3 -> -2.5151314e-10 | AM3: =AE3-U3 -> -7.2446582e-10
A4: Bulgaria | B4: 15387 | C4: 13232.82 | D4: 1 | E4: 10.007848 | F4: -1.887146 | G4: -1.785586 | H4: -1.0063262 | I4: -0.18856662 | J4: -0.17841858 | K4: -0.10055371 | L4: -2.1555835 | M4: -2.0395771 | N4: -1.1494713 | O4: 32433.794 | P4: 38.2 | Q4: 10.582 | R4: 4.50109 | S4: 84.129356 | T4: 26498 | U4: 10.386956 | X4: =WB_correlations!D4 -> Bulgaria | Y4: =WB_correlations!E4 -> -0.18856662 | Z4: =WB_correlations!F4 -> -0.17841858 | AA4: =WB_correlations!G4 -> -0.10055371 | AB4: =WB_correlations!H4 -> -2.1555835 | AC4: =WB_correlations!I4 -> -2.0395771 | AD4: =WB_correlations!J4 -> -1.1494713 | AE4: =WB_correlations!K4 -> 10.386956 | AG4: =I4-Y4 -> 0 | AH4: =J4-Z4 -> 0 | AI4: =K4-AA4 -> 1.3289606e-11 | AJ4: =L4-AB4 -> 0 | AK4: =M4-AC4 -> 0 | AL4: =N4-AD4 -> 1.519187e-10 | AM4: =AE4-U4 -> -1.5323671e-09
A5: Czechia | B5: 23998 | C5: 20638.28 | D5: 3021.0957 | E5: 1.9944727 | F5: -1.137201 | G5: -1.075068 | H5: -0.90086981 | I5: -0.57017626 | J5: -0.53902367 | K5: -0.45168319 | L5: -1.2989624 | M5: -1.2279913 | N5: -1.0290143 | O5: 48390.662 | P5: 25.9 | Q5: 6.72 | R5: 4.3029199 | S5: 70.81459 | T5: 329739 | U5: 10.787062 | X5: =WB_correlations!D5 -> Czechia | Y5: =WB_correlations!E5 -> -0.57017626 | Z5: =WB_correlations!F5 -> -0.53902367 | AA5: =WB_correlations!G5 -> -0.4516832 | AB5: =WB_correlations!H5 -> -1.2989624 | AC5: =WB_correlations!I5 -> -1.2279913 | AD5: =WB_correlations!J5 -> -1.0290143 | AE5: =WB_correlations!K5 -> 10.787062 | AG5: =I5-Y5 -> -9.9920072e-16 | AH5: =J5-Z5 -> -8.8817842e-16 | AI5: =K5-AA5 -> 7.4892204e-11 | AJ5: =L5-AB5 -> 0 | AK5: =M5-AC5 -> 0 | AL5: =N5-AD5 -> 1.7061907e-10 | AM5: =AE5-U5 -> 4.4068571e-10
A6: Denmark | B6: 71565 | C6: 61545.9 | D6: 8724.5305 | E6: 0.93395363 | F6: -1.046503 | G6: -1.029858 | H6: -1.6091993 | I6: -1.1205085 | J6: -1.1026864 | K6: -1.722997 | L6: -1.1953631 | M6: -1.1763504 | N6: -1.8381002 | O6: 69475.32 | P6: 29.3 | Q6: 10.533 | R6: 6.3558602 | S6: 84.586609 | T6: 60219 | U6: 11.148727 | X6: =WB_correlations!D6 -> Denmark | Y6: =WB_correlations!E6 -> -1.1205085 | Z6: =WB_correlations!F6 -> -1.1026864 | AA6: =WB_correlations!G6 -> -1.722997 | AB6: =WB_correlations!H6 -> -1.1953631 | AC6: =WB_correlations!I6 -> -1.1763504 | AD6: =WB_correlations!J6 -> -1.8381002 | AE6: =WB_correlations!K6 -> 11.148727 | AG6: =I6-Y6 -> 0 | AH6: =J6-Z6 -> 0 | AI6: =K6-AA6 -> -2.5489433e-10 | AJ6: =L6-AB6 -> 0 | AK6: =M6-AC6 -> 0 | AL6: =N6-AD6 -> -2.7192271e-10 | AM6: =AE6-U6 -> 5.0251003e-10
A7: Germany | B7: 53791 | C7: 46260.26 | D7: 8456.3829 | E7: 0.96517076 | F7: -0.6815 | G7: -0.581445 | H7: 0.65222662 | I7: -0.70609267 | J7: -0.60242708 | K7: 0.67576294 | L7: -0.77844013 | M7: -0.66415278 | N7: 0.74500276 | O7: 63676.088 | P7: 33.7 | Q7: 6.049 | R7: 5.2391601 | S7: 77.3657 | T7: 981552 | U7: 11.061564 | X7: =WB_correlations!D7 -> Germany | Y7: =WB_correlations!E7 -> -0.70609267 | Z7: =WB_correlations!F7 -> -0.60242708 | AA7: =WB_correlations!G7 -> 0.67576294 | AB7: =WB_correlations!H7 -> -0.77844013 | AC7: =WB_correlations!I7 -> -0.66415278 | AD7: =WB_correlations!J7 -> 0.74500276 | AE7: =WB_correlations!K7 -> 11.061564 | AG7: =I7-Y7 -> 0 | AH7: =J7-Z7 -> 0 | AI7: =K7-AA7 -> -2.2011648e-10 | AJ7: =L7-AB7 -> 0 | AK7: =M7-AC7 -> 0 | AL7: =N7-AD7 -> -2.4266988e-10 | AM7: =AE7-U7 -> -3.4248693e-10
A8: Estonia | B8: 26546 | C8: 22829.56 | D8: 4804.714 | E8: 1.5304948 | F8: -1.447445 | G8: -1.407405 | H8: -2.2370894 | I8: -0.94573665 | J8: -0.91957517 | K8: -1.4616773 | L8: -1.6533372 | M8: -1.6076017 | N8: -2.5553048 | O8: 43128.633 | P8: 32.3 | Q8: 18.392 | R8: 5.2073398 | S8: 71.425194 | T8: 39754 | U8: 10.671942 | X8: =WB_correlations!D8 -> Estonia | Y8: =WB_correlations!E8 -> -0.94573665 | Z8: =WB_correlations!F8 -> -0.91957517 | AA8: =WB_correlations!G8 -> -1.4616773 | AB8: =WB_correlations!H8 -> -1.6533372 | AC8: =WB_correlations!I8 -> -1.6076017 | AD8: =WB_correlations!J8 -> -2.5553048 | AE8: =WB_correlations!K8 -> 10.671942 | AG8: =I8-Y8 -> 0 | AH8: =J8-Z8 -> 0 | AI8: =K8-AA8 -> 1.2974222e-10 | AJ8: =L8-AB8 -> 0 | AK8: =M8-AC8 -> 0 | AL8: =N8-AD8 -> 2.2681634e-10 | AM8: =AE8-U8 -> 6.6399863e-10
A9: Greece | B9: 17954 | C9: 15440.44 | D9: 4.6283026 | E9: 8.4756574 | F9: -0.86575 | G9: -0.718908 | H9: 0.10535878 | I9: -0.10214547 | J9: -0.084820323 | K9: 0.01243075 | L9: -0.98889882 | M9: -0.82116924 | N9: 0.12034556 | O9: 35831.344 | P9: 33.4 | Q9: 31.29 | R9: 3.3754799 | S9: 166.38956 | T9: -53997 | U9: 10.486578 | X9: =WB_correlations!D9 -> Greece | Y9: =WB_correlations!E9 -> -0.10214547 | Z9: =WB_correlations!F9 -> -0.084820323 | AA9: =WB_correlations!G9 -> 0.01243075 | AB9: =WB_correlations!H9 -> -0.98889882 | AC9: =WB_correlations!I9 -> -0.82116924 | AD9: =WB_correlations!J9 -> 0.12034556 | AE9: =WB_correlations!K9 -> 10.486578 | AG9: =I9-Y9 -> -2.0400348e-15 | AH9: =J9-Z9 -> -1.7347235e-15 | AI9: =K9-AA9 -> 1.1697756e-11 | AJ9: =L9-AB9 -> 0 | AK9: =M9-AC9 -> 0 | AL9: =N9-AD9 -> 1.1324677e-10 | AM9: =AE9-U9 -> 6.1062444e-10
A10: Spain | B10: 33700 | C10: 28982 | D10: 6801.1286 | E10: 1.1830037 | F10: -0.507701 | G10: -0.473719 | H10: 0.96454423 | I10: -0.42916264 | J10: -0.40043745 | K10: 0.8153349 | L10: -0.57991905 | M10: -0.54110327 | N10: 1.1017461 | O10: 46733.481 | P10: 33.6 | Q10: 29.713 | R10: 4.5855398 | S10: 95.027161 | T10: 299779 | U10: 10.752216 | X10: =WB_correlations!D10 -> Spain | Y10: =WB_correlations!E10 -> -0.42916264 | Z10: =WB_correlations!F10 -> -0.40043745 | AA10: =WB_correlations!G10 -> 0.8153349 | AB10: =WB_correlations!H10 -> -0.57991905 | AC10: =WB_correlations!I10 -> -0.54110327 | AD10: =WB_correlations!J10 -> 1.1017461 | AE10: =WB_correlations!K10 -> 10.752216 | AG10: =I10-Y10 -> 7.2164497e-16 | AH10: =J10-Z10 -> 6.1062266e-16 | AI10: =K10-AA10 -> 1.683913e-10 | AJ10: =L10-AB10 -> 0 | AK10: =M10-AC10 -> 0 | AL10: =N10-AD10 -> 2.2754532e-10 | AM10: =AE10-U10 -> 4.6961013e-10
A11: France | B11: 43790 | C11: 37659.4 | D11: 8054.806 | E11: 1.0138234 | F11: -0.597106 | G11: -0.535495 | H11: 1.178993 | I11: -0.58896453 | J11: -0.52819359 | K11: 1.1629175 | L11: -0.68204149 | M11: -0.61166662 | N11: 1.3466991 | O11: 53673.814 | P11: 31.2 | Q11: 17.856 | R11: 5.3243499 | S11: 71.510727 | T11: 179377 | U11: 10.890681 | X11: =WB_correlations!D11 -> France | Y11: =WB_correlations!E11 -> -0.58896453 | Z11: =WB_correlations!F11 -> -0.52819359 | AA11: =WB_correlations!G11 -> 1.1629175 | AB11: =WB_correlations!H11 -> -0.68204149 | AC11: =WB_correlations!I11 -> -0.61166662 | AD11: =WB_correlations!J11 -> 1.3466991 | AE11: =WB_correlations!K11 -> 10.890681 | AG11: =I11-Y11 -> 0 | AH11: =J11-Z11 -> 0 | AI11: =K11-AA11 -> 3.953553e-10 | AJ11: =L11-AB11 -> 0 | AK11: =M11-AC11 -> 0 | AL11: =N11-AD11 -> 4.5783466e-10 | AM11: =AE11-U11 -> -7.5720941e-10
A12: Croatia | B12: 23446 | C12: 20163.56 | D12: 2527.4656 | E12: 2.1728752 | F12: -1.654745 | G12: -1.53452 | H12: -2.5720774 | I12: -0.76154626 | J12: -0.70621634 | K12: -1.1837207 | L12: -1.8901246 | M12: -1.7527982 | N12: -2.9379431 | O12: 39864.01 | P12: 30 | Q12: 17.744 | S12: 80.762672 | T12: 11681 | U12: 10.593229 | X12: =WB_correlations!D12 -> Croatia | Y12: =WB_correlations!E12 -> -0.76154626 | Z12: =WB_correlations!F12 -> -0.70621634 | AA12: =WB_correlations!G12 -> -1.1837207 | AB12: =WB_correlations!H12 -> -1.8901246 | AC12: =WB_correlations!I12 -> -1.7527982 | AD12: =WB_correlations!J12 -> -2.9379431 | AE12: =WB_correlations!K12 -> 10.593229 | AG12: =I12-Y12 -> -1.3322676e-15 | AH12: =J12-Z12 -> -1.110223e-15 | AI12: =K12-AA12 -> -3.1038727e-11 | AJ12: =L12-AB12 -> 0 | AK12: =M12-AC12 -> 0 | AL12: =N12-AD12 -> -7.7033935e-11 | AM12: =AE12-U12 -> 3.0112624e-10
A13: Italy | B13: 33523 | C13: 28829.78 | D13: 6758.7787 | E13: 1.1892501 | F13: -0.925037 | G13: -0.808428 | H13: 0.67669479 | I13: -0.77783219 | J13: -0.67977964 | K13: 0.56900966 | L13: -1.0566191 | M13: -0.92342304 | N13: 0.7729514 | O13: 52333.327 | P13: 33.7 | Q13: 23.704 | R13: 4.06776 | S13: 73.89621 | T13: 231228 | U13: 10.865389 | X13: =WB_correlations!D13 -> Italy | Y13: =WB_correlations!E13 -> -0.77783219 | Z13: =WB_correlations!F13 -> -0.67977964 | AA13: =WB_correlations!G13 -> 0.56900966 | AB13: =WB_correlations!H13 -> -1.0566191 | AC13: =WB_correlations!I13 -> -0.92342304 | AD13: =WB_correlations!J13 -> 0.7729514 | AE13: =WB_correlations!K13 -> 10.865389 | AG13: =I13-Y13 -> 0 | AH13: =J13-Z13 -> 0 | AI13: =K13-AA13 -> 2.2063484e-10 | AJ13: =L13-AB13 -> 0 | AK13: =M13-AC13 -> 0 | AL13: =N13-AD13 -> 2.997137e-10 | AM13: =AE13-U13 -> -5.1707794e-10
A14: Cyprus | B14: 27611 | C14: 23745.46 | D14: 5095.4373 | E14: 1.4717468 | F14: -0.902163 | G14: -0.946609 | H14: 0.25508166 | I14: -0.61298791 | J14: -0.6431874 | K14: 0.17331898 | L14: -1.0304914 | M14: -1.0812596 | N14: 0.29136582 | O14: 50623.797 | P14: 31.5 | Q14: 18.707 | R14: 4.7421098 | S14: 105.38498 | T14: 9014 | U14: 10.832177 | X14: =WB_correlations!D14 -> Cyprus | Y14: =WB_correlations!E14 -> -0.61298791 | Z14: =WB_correlations!F14 -> -0.6431874 | AA14: =WB_correlations!G14 -> 0.17331898 | AB14: =WB_correlations!H14 -> -1.0304914 | AC14: =WB_correlations!I14 -> -1.0812596 | AD14: =WB_correlations!J14 -> 0.29136581 | AE14: =WB_correlations!K14 -> 10.832177 | AG14: =I14-Y14 -> 0 | AH14: =J14-Z14 -> 0 | AI14: =K14-AA14 -> 3.2651806e-10 | AJ14: =L14-AB14 -> 0 | AK14: =M14-AC14 -> 0 | AL14: =N14-AD14 -> 5.4890825e-10 | AM14: =AE14-U14 -> 4.9383786e-10
A15: Latvia | B15: 22262 | C15: 19145.32 | D15: 1607.4555 | E15: 2.6254398 | F15: -1.511516 | G15: -1.390564 | H15: -1.9281779 | I15: -0.57571916 | J15: -0.52964993 | K15: -0.73442091 | L15: -1.726522 | M15: -1.5883651 | N15: -2.202452 | O15: 37718.71 | P15: 33.7 | Q15: 15.27 | R15: 4.3196702 | S15: 91.330368 | T15: 22027 | U15: 10.537912 | X15: =WB_correlations!D15 -> Latvia | Y15: =WB_correlations!E15 -> -0.57571916 | Z15: =WB_correlations!F15 -> -0.52964993 | AA15: =WB_correlations!G15 -> -0.73442091 | AB15: =WB_correlations!H15 -> -1.726522 | AC15: =WB_correlations!I15 -> -1.5883651 | AD15: =WB_correlations!J15 -> -2.202452 | AE15: =WB_correlations!K15 -> 10.537912 | AG15: =I15-Y15 -> -8.8817842e-16 | AH15: =J15-Z15 -> -8.8817842e-16 | AI15: =K15-AA15 -> -3.9491743e-11 | AJ15: =L15-AB15 -> 0 | AK15: =M15-AC15 -> 0 | AL15: =N15-AD15 -> -1.1842749e-10 | AM15: =AE15-U15 -> 1.1038104e-10
A16: Lithuania | B16: 29104 | C16: 25029.44 | D16: 5513.5374 | E16: 1.3928859 | F16: -2.173113 | G16: -2.16716 | H16: -1.4113332 | I16: -1.5601515 | J16: -1.5558776 | K16: -1.0132439 | L16: -2.482228 | M16: -2.4754282 | N16: -1.6120886 | O16: 46651.215 | P16: 36.6 | Q16: 11.873 | R16: 4.2528501 | S16: 76.915459 | T16: 72100 | U16: 10.750454 | X16: =WB_correlations!D16 -> Lithuania | Y16: =WB_correlations!E16 -> -1.5601515 | Z16: =WB_correlations!F16 -> -1.5558776 | AA16: =WB_correlations!G16 -> -1.0132439 | AB16: =WB_correlations!H16 -> -2.482228 | AC16: =WB_correlations!I16 -> -2.4754282 | AD16: =WB_correlations!J16 -> -1.6120886 | AE16: =WB_correlations!K16 -> 10.750454 | AG16: =I16-Y16 -> 0 | AH16: =J16-Z16 -> 0 | AI16: =K16-AA16 -> 1.9735302e-10 | AJ16: =L16-AB16 -> 0 | AK16: =M16-AC16 -> 0 | AL16: =N16-AD16 -> 3.1399172e-10 | AM16: =AE16-U16 -> 4.0674308e-10
A17: Luxembourg | B17: 82969 | C17: 71353.34 | D17: 8798.4413 | E17: 0.92551771 | F17: -0.492895 | G17: -0.574991 | H17: -1.2366166 | I17: -0.53256139 | J17: -0.62126418 | K17: -1.336135 | L17: -0.56300697 | M17: -0.65678073 | N17: -1.4125195 | O17: 132570.83 | P17: 34.1 | Q17: 17.599 | R17: 3.7445199 | S17: 21.0326 | T17: 13194 | U17: 11.794872 | X17: =WB_correlations!D17 -> Luxembourg | Y17: =WB_correlations!E17 -> -0.53256139 | Z17: =WB_correlations!F17 -> -0.62126418 | AA17: =WB_correlations!G17 -> -1.336135 | AB17: =WB_correlations!H17 -> -0.56300697 | AC17: =WB_correlations!I17 -> -0.65678073 | AD17: =WB_correlations!J17 -> -1.4125195 | AE17: =WB_correlations!K17 -> 11.794872 | AG17: =I17-Y17 -> 0 | AH17: =J17-Z17 -> 0 | AI17: =K17-AA17 -> 3.1724978e-10 | AJ17: =L17-AB17 -> 0 | AK17: =M17-AC17 -> 0 | AL17: =N17-AD17 -> 3.3538572e-10 | AM17: =AE17-U17 -> -3.4956358e-09
A18: Hungary | B18: 18461 | C18: 15876.46 | D18: 46.564213 | E18: 6.1670153 | F18: -1.114468 | G18: -1.023607 | H18: -1.0317228 | I18: -0.18071432 | J18: -0.16598094 | K18: -0.16729694 | L18: -1.2729958 | M18: -1.1692102 | N18: -1.1784804 | O18: 40610.971 | Q18: 10.541 | R18: 3.8011999 | S18: 60.274681 | T18: 41871 | U18: 10.611794 | X18: =WB_correlations!D18 -> Hungary | Y18: =WB_correlations!E18 -> -0.18071432 | Z18: =WB_correlations!F18 -> -0.16598094 | AA18: =WB_correlations!G18 -> -0.16729694 | AB18: =WB_correlations!H18 -> -1.2729958 | AC18: =WB_correlations!I18 -> -1.1692102 | AD18: =WB_correlations!J18 -> -1.1784804 | AE18: =WB_correlations!K18 -> 10.611794 | AG18: =I18-Y18 -> -8.3266727e-16 | AH18: =J18-Z18 -> -8.6042284e-16 | AI18: =K18-AA18 -> -1.3300694e-11 | AJ18: =L18-AB18 -> 0 | AK18: =M18-AC18 -> 0 | AL18: =N18-AD18 -> -9.3687502e-11 | AM18: =AE18-U18 -> -9.0674135e-10
A19: Malta | B19: 33499 | C19: 28809.14 | D19: 6752.8799 | E19: 1.1901232 | F19: -0.361679 | G19: -0.530893 | H19: -2.335214 | I19: -0.30390047 | J19: -0.44608238 | K19: -1.9621616 | L19: -0.41312612 | M19: -0.60641 | N19: -2.6673871 | O19: 56841.958 | P19: 34.6 | Q19: 9.064 | R19: 4.7125802 | S19: 74.590134 | T19: 2480 | U19: 10.94803 | X19: =WB_correlations!D19 -> Malta | Y19: =WB_correlations!E19 -> -0.30390047 | Z19: =WB_correlations!F19 -> -0.44608238 | AA19: =WB_correlations!G19 -> -1.9621616 | AB19: =WB_correlations!H19 -> -0.41312612 | AC19: =WB_correlations!I19 -> -0.60641 | AD19: =WB_correlations!J19 -> -2.6673871 | AE19: =WB_correlations!K19 -> 10.94803 | AG19: =I19-Y19 -> 0 | AH19: =J19-Z19 -> 0 | AI19: =K19-AA19 -> -7.6563644e-11 | AJ19: =L19-AB19 -> 0 | AK19: =M19-AC19 -> 0 | AL19: =N19-AD19 -> -1.0408163e-10 | AM19: =AE19-U19 -> -4.5412207e-10
A20: Austria | B20: 58600 | C20: 50396 | D20: 8557.6144 | E20: 0.95327083 | F20: -0.548534 | G20: -0.502849 | H20: -0.96075537 | I20: -0.57542304 | J20: -0.52749857 | K20: -1.0078514 | L20: -0.62656035 | M20: -0.57437688 | N20: -1.0974182 | O20: 65694.551 | P20: 30.9 | Q20: 10.327 | R20: 5.2774901 | S20: 94.511688 | T20: 157365 | U20: 11.092771 | X20: =WB_correlations!D20 -> Austria | Y20: =WB_correlations!E20 -> -0.57542304 | Z20: =WB_correlations!F20 -> -0.52749857 | AA20: =WB_correlations!G20 -> -1.0078514 | AB20: =WB_correlations!H20 -> -0.62656035 | AC20: =WB_correlations!I20 -> -0.57437688 | AD20: =WB_correlations!J20 -> -1.0974182 | AE20: =WB_correlations!K20 -> 11.092771 | AG20: =I20-Y20 -> 0 | AH20: =J20-Z20 -> 0 | AI20: =K20-AA20 -> -4.4975113e-10 | AJ20: =L20-AB20 -> 0 | AK20: =M20-AC20 -> 0 | AL20: =N20-AD20 -> -4.8972049e-10 | AM20: =AE20-U20 -> -4.3726089e-10
A21: Poland | B21: 21246 | C21: 18271.56 | D21: 980.81535 | E21: 3.1194633 | F21: -1.668281 | G21: -1.529181 | H21: -0.13525735 | I21: -0.53479744 | J21: -0.49020643 | K21: -0.043359174 | L21: -1.905586 | M21: -1.7466997 | N21: -0.15449707 | O21: 43405.022 | P21: 28.9 | Q21: 10.56 | R21: 4.3137298 | S21: 75.291107 | T21: 967744 | U21: 10.67833 | X21: =WB_correlations!D21 -> Poland | Y21: =WB_correlations!E21 -> -0.53479744 | Z21: =WB_correlations!F21 -> -0.49020643 | AA21: =WB_correlations!G21 -> -0.043359174 | AB21: =WB_correlations!H21 -> -1.905586 | AC21: =WB_correlations!I21 -> -1.7466997 | AD21: =WB_correlations!J21 -> -0.15449707 | AE21: =WB_correlations!K21 -> 10.67833 | AG21: =I21-Y21 -> -1.110223e-15 | AH21: =J21-Z21 -> -1.0547119e-15 | AI21: =K21-AA21 -> -7.0805861e-11 | AJ21: =L21-AB21 -> 0 | AK21: =M21-AC21 -> 0 | AL21: =N21-AD21 -> -2.5229457e-10 | AM21: =AE21-U21 -> 4.6667559e-10
A22: Portugal | B22: 24818 | C22: 21343.48 | D22: 3836.3558 | E22: 1.7555694 | F22: -0.939169 | G22: -0.835813 | H22: -0.086890662 | I22: -0.53496547 | J22: -0.47609226 | K22: -0.049494291 | L22: -1.0727613 | M22: -0.95470342 | N22: -0.099250446 | O22: 41070.861 | P22: 36.3 | Q22: 19.183 | R22: 4.55161 | S22: 75.07148 | T22: 68696 | U22: 10.623054 | X22: =WB_correlations!D22 -> Portugal | Y22: =WB_correlations!E22 -> -0.53496547 | Z22: =WB_correlations!F22 -> -0.47609226 | AA22: =WB_correlations!G22 -> -0.049494291 | AB22: =WB_correlations!H22 -> -1.0727613 | AC22: =WB_correlations!I22 -> -0.95470342 | AD22: =WB_correlations!J22 -> -0.099250445 | AE22: =WB_correlations!K22 -> 10.623054 | AG22: =I22-Y22 -> 0 | AH22: =J22-Z22 -> -5.5511151e-16 | AI22: =K22-AA22 -> -2.5817994e-10 | AJ22: =L22-AB22 -> 0 | AK22: =M22-AC22 -> 0 | AL22: =N22-AD22 -> -5.1772577e-10 | AM22: =AE22-U22 -> 1.1449917e-09
A23: Romania | B23: 21108 | C23: 18152.88 | D23: 907.66157 | E23: 3.196976 | F23: -1.711433 | G23: -1.601542 | H23: -0.36301852 | I23: -0.5353287 | J23: -0.50095528 | K23: -0.11355059 | L23: -1.9548762 | M23: -1.8293537 | N23: -0.41465617 | O23: 39256.989 | P23: 32.3 | Q23: 22.874 | R23: 3.27882 | S23: 58.23904 | T23: 89076 | U23: 10.577885 | X23: =WB_correlations!D23 -> Romania | Y23: =WB_correlations!E23 -> -0.5353287 | Z23: =WB_correlations!F23 -> -0.50095528 | AA23: =WB_correlations!G23 -> -0.11355059 | AB23: =WB_correlations!H23 -> -1.9548762 | AC23: =WB_correlations!I23 -> -1.8293537 | AD23: =WB_correlations!J23 -> -0.41465617 | AE23: =WB_correlations!K23 -> 10.577885 | AG23: =I23-Y23 -> -8.8817842e-16 | AH23: =J23-Z23 -> -8.8817842e-16 | AI23: =K23-AA23 -> -9.6067806e-11 | AJ23: =L23-AB23 -> 0 | AK23: =M23-AC23 -> 0 | AL23: =N23-AD23 -> -3.5081321e-10 | AM23: =AE23-U23 -> 4.2322768e-10
A24: Slovenia | B24: 35133 | C24: 30214.38 | D24: 7098.4662 | E24: 1.1402136 | F24: -1.279554 | G24: -1.179423 | H24: -3.1075331 | I24: -1.1222056 | J24: -1.0343878 | K24: -2.7253957 | L24: -1.4615645 | M24: -1.3471903 | N24: -3.5495649 | O24: 47050.068 | P24: 24.3 | Q24: 10.14 | R24: 5.2806501 | S24: 82.392258 | T24: 9014 | U24: 10.758968 | X24: =WB_correlations!D24 -> Slovenia | Y24: =WB_correlations!E24 -> -1.1222056 | Z24: =WB_correlations!F24 -> -1.0343878 | AA24: =WB_correlations!G24 -> -2.7253957 | AB24: =WB_correlations!H24 -> -1.4615645 | AC24: =WB_correlations!I24 -> -1.3471903 | AD24: =WB_correlations!J24 -> -3.5495649 | AE24: =WB_correlations!K24 -> 10.758968 | AG24: =I24-Y24 -> 0 | AH24: =J24-Z24 -> 0 | AI24: =K24-AA24 -> 3.9069858e-10 | AJ24: =L24-AB24 -> 0 | AK24: =M24-AC24 -> 0 | AL24: =N24-AD24 -> 5.0884719e-10 | AM24: =AE24-U24 -> -9.386607e-10
A25: Slovakia | B25: 20287 | C25: 17446.82 | D25: 527.15205 | E25: 3.7403585 | F25: -1.516326 | G25: -1.397631 | H25: -1.5699389 | I25: -0.4053959 | J25: -0.37366231 | K25: -0.41972951 | L25: -1.7320162 | M25: -1.5964374 | N25: -1.7932552 | O25: 38664.908 | P25: 24.1 | Q25: 19.924 | R25: 4.6568899 | S25: 52.495911 | T25: 92314 | U25: 10.562688 | X25: =WB_correlations!D25 -> Slovakia | Y25: =WB_correlations!E25 -> -0.4053959 | Z25: =WB_correlations!F25 -> -0.37366231 | AA25: =WB_correlations!G25 -> -0.41972951 | AB25: =WB_correlations!H25 -> -1.7320162 | AC25: =WB_correlations!I25 -> -1.5964374 | AD25: =WB_correlations!J25 -> -1.7932552 | AE25: =WB_correlations!K25 -> 10.562688 | AG25: =I25-Y25 -> -1.110223e-15 | AH25: =J25-Z25 -> -9.9920072e-16 | AI25: =K25-AA25 -> -8.7541085e-13 | AJ25: =L25-AB25 -> 0 | AK25: =M25-AC25 -> 0 | AL25: =N25-AD25 -> -3.7354564e-12 | AM25: =AE25-U25 -> 1.2970602e-10
A26: Finland | B26: 49428 | C26: 42508.08 | D26: 8323.75 | E26: 0.98097942 | F26: -1.756347 | G26: -1.620129 | H26: -1.8170332 | I26: -1.7904015 | J26: -1.6515423 | K26: -1.8522643 | L26: -2.006179 | M26: -1.8505846 | N26: -2.0754975 | O26: 57068.306 | P26: 27.9 | Q26: 14.138 | R26: 6.3757801 | S26: 104.94422 | T26: 60353 | U26: 10.952004 | X26: =WB_correlations!D26 -> Finland | Y26: =WB_correlations!E26 -> -1.7904015 | Z26: =WB_correlations!F26 -> -1.6515423 | AA26: =WB_correlations!G26 -> -1.8522643 | AB26: =WB_correlations!H26 -> -2.006179 | AC26: =WB_correlations!I26 -> -1.8505846 | AD26: =WB_correlations!J26 -> -2.0754975 | AE26: =WB_correlations!K26 -> 10.952004 | AG26: =I26-Y26 -> 0 | AH26: =J26-Z26 -> 0 | AI26: =K26-AA26 -> -2.8576586e-10 | AJ26: =L26-AB26 -> 0 | AK26: =M26-AC26 -> 0 | AL26: =N26-AD26 -> -3.2020564e-10 | AM26: =AE26-U26 -> -8.3772278e-10
A27: Sweden | B27: 46525 | C27: 40011.5 | D27: 8202.1973 | E27: 0.99569021 | F27: -0.966849 | G27: -0.927258 | H27: -0.62943314 | I27: -0.97103395 | J27: -0.93127158 | K27: -0.6321576 | L27: -1.1043787 | M27: -1.059156 | N27: -0.71896701 | O27: 63088.424 | P27: 31.6 | Q27: 21.597 | R27: 7.3190999 | S27: 83.897614 | T27: 58955 | U27: 11.052293 | X27: =WB_correlations!D27 -> Sweden | Y27: =WB_correlations!E27 -> -0.97103395 | Z27: =WB_correlations!F27 -> -0.93127158 | AA27: =WB_correlations!G27 -> -0.6321576 | AB27: =WB_correlations!H27 -> -1.1043787 | AC27: =WB_correlations!I27 -> -1.059156 | AD27: =WB_correlations!J27 -> -0.71896701 | AE27: =WB_correlations!K27 -> 11.052293 | AG27: =I27-Y27 -> 0 | AH27: =J27-Z27 -> 0 | AI27: =K27-AA27 -> -4.2468329e-10 | AJ27: =L27-AB27 -> 0 | AK27: =M27-AC27 -> 0 | AL27: =N27-AD27 -> -4.8300186e-10 | AM27: =AE27-U27 -> 5.0922999e-10
A30: Country | B30: elasticity_new_TWFE | C30: educ_spend_gdp | F30: SUMMARY OUTPUT
A31: Belgium | B31: -0.63388504 | C31: 6.2761102
A32: Bulgaria | B32: -0.18856662 | C32: 4.50109 | F32: Regression Statistics
A33: Czechia | B33: -0.57017626 | C33: 4.3029199 | F33: Multiple R | G33: 0.53439232
A34: Denmark | B34: -1.1205085 | C34: 6.3558602 | F34: R Square | G34: 0.28557516
A35: Germany | B35: -0.70609267 | C35: 5.2391601 | F35: Adjusted R Square | G35: 0.2531013
A36: Estonia | B36: -0.94573665 | C36: 5.2073398 | F36: Standard Error | G36: 0.35132364
A37: Greece | B37: -0.10214547 | C37: 3.3754799 | F37: Observations | G37: 24
A38: Spain | B38: -0.42916264 | C38: 4.5855398
A39: France | B39: -0.58896453 | C39: 5.3243499 | F39: ANOVA
A40: Italy | B40: -0.77783219 | C40: 4.06776 | G40: df | H40: SS | I40: MS | J40: F | K40: Significance F
A41: Cyprus | B41: -0.61298791 | C41: 4.7421098 | F41: Regression | G41: 1 | H41: 1.0854287 | I41: 1.0854287 | J41: 8.7940019 | K41: 0.0071431442
A42: Latvia | B42: -0.57571916 | C42: 4.3196702 | F42: Residual | G42: 22 | H42: 2.7154226 | I42: 0.1234283
A43: Lithuania | B43: -1.5601515 | C43: 4.2528501 | F43: Total | G43: 23 | H43: 3.8008513
A44: Luxembourg | B44: -0.53256139 | C44: 3.7445199
A45: Hungary | B45: -0.18071432 | C45: 3.8011999 | G45: Coefficients | H45: Standard Error | I45: t Stat | J45: P-value | K45: Lower 95% | L45: Upper 95% | M45: Lower 95,0% | N45: Upper 95,0%
A46: Malta | B46: -0.30390047 | C46: 4.7125802 | F46: Intercept | G46: 0.37569777 | H46: 0.36285435 | I46: 1.0353955 | J46: 0.31173195 | K46: -0.37681609 | L46: 1.1282116 | M46: -0.37681609 | N46: 1.1282116
A47: Austria | B47: -0.57542304 | C47: 5.2774901 | F47: educ_spend_gdp | G47: -0.21849502 | H47: 0.073679771 | I47: -2.9654682 | J47: 0.0071431442 | K47: -0.37129751 | L47: -0.065692529 | M47: -0.37129751 | N47: -0.065692529
A48: Poland | B48: -0.53479744 | C48: 4.3137298
A49: Portugal | B49: -0.53496547 | C49: 4.55161
A50: Romania | B50: -0.5353287 | C50: 3.27882
A51: Slovenia | B51: -1.1222056 | C51: 5.2806501
A52: Slovakia | B52: -0.4053959 | C52: 4.6568899
A53: Finland | B53: -1.7904015 | C53: 6.3757801
A54: Sweden | B54: -0.97103395 | C54: 7.3190999

Sheet placebo_denominator
A1: =Elasticities!G2 -> Country | B1: =Elasticities!I2 -> wage_gbp | C1: =Elasticities!N2 -> Estimate_TWFE | D1: =Elasticities!Q2 -> k_i | E1: =Elasticities!R2 -> elasticity_TWFE_new | F1: =Elasticities!U2 -> elasticity_TWFE_old | G1: log(GDP) | H1: k_income_raw | I1: k_placebo | J1: eta_placebo | P1: SUMMARY OUTPUT | R1: =F1 -> elasticity_TWFE_old | V1: SUMMARY OUTPUT | X1: =E1 -> elasticity_TWFE_new | AB1: SUMMARY OUTPUT | AD1: =J1 -> eta_placebo
A2: =Elasticities!G3 -> Belgium | B2: =Elasticities!I3 -> 51283.52 | C2: =Elasticities!N3 -> -0.602657 | D2: =Elasticities!Q3 -> 0.95073548 | E2: =Elasticities!R3 -> -0.63388504 | F2: =Elasticities!U3 -> -0.68838209 | G2: =VLOOKUP(A2,WB_correlations!$D$2:$K$27,8,FALSE) -> 11.04391 | H2: =LN(B2) -> 10.845125 | I2: =(H2-MIN($H$2:$H$26))/(MAX($H$2:$H$26)-MIN($H$2:$H$26))*(MAX($D$2:$D$26)-MIN($D$2:$D$26))+MIN($D$2:$D$26) -> 8.2275726 | J2: =C2/I2 -> -0.073248458
A3: =Elasticities!G4 -> Bulgaria | B3: =Elasticities!I4 -> 13232.82 | C3: =Elasticities!N4 -> -1.887146 | D3: =Elasticities!Q4 -> 10.007848 | E3: =Elasticities!R4 -> -0.18856662 | F3: =Elasticities!U4 -> -2.1555835 | G3: =VLOOKUP(A3,WB_correlations!$D$2:$K$27,8,FALSE) -> 10.386956 | H3: =LN(B3) -> 9.4904554 | I3: =(H3-MIN($H$2:$H$26))/(MAX($H$2:$H$26)-MIN($H$2:$H$26))*(MAX($D$2:$D$26)-MIN($D$2:$D$26))+MIN($D$2:$D$26) -> 0.92551771 | J3: =C3/I3 -> -2.0390166 | P3: Regression Statistics
A4: =Elasticities!G5 -> Czechia | B4: =Elasticities!I5 -> 20638.28 | C4: =Elasticities!N5 -> -1.137201 | D4: =Elasticities!Q5 -> 1.9944727 | E4: =Elasticities!R5 -> -0.57017626 | F4: =Elasticities!U5 -> -1.2989624 | G4: =VLOOKUP(A4,WB_correlations!$D$2:$K$27,8,FALSE) -> 10.787062 | H4: =LN(B4) -> 9.9349029 | I4: =(H4-MIN($H$2:$H$26))/(MAX($H$2:$H$26)-MIN($H$2:$H$26))*(MAX($D$2:$D$26)-MIN($D$2:$D$26))+MIN($D$2:$D$26) -> 3.3212167 | J4: =C4/I4 -> -0.34240494 | P4: Multiple R | Q4: 0.55897998 | V4: Multiple R | W4: 0.25187648 | AB4: Multiple R | AC4: 0.62545491
A5: =Elasticities!G6 -> Denmark | B5: =Elasticities!I6 -> 61545.9 | C5: =Elasticities!N6 -> -1.046503 | D5: =Elasticities!Q6 -> 0.93395363 | E5: =Elasticities!R6 -> -1.1205085 | F5: =Elasticities!U6 -> -1.1953631 | G5: =VLOOKUP(A5,WB_correlations!$D$2:$K$27,8,FALSE) -> 11.148727 | H5: =LN(B5) -> 11.027539 | I5: =(H5-MIN($H$2:$H$26))/(MAX($H$2:$H$26)-MIN($H$2:$H$26))*(MAX($D$2:$D$26)-MIN($D$2:$D$26))+MIN($D$2:$D$26) -> 9.210835 | J5: =C5/I5 -> -0.11361652 | P5: R Square | Q5: 0.31245862 | V5: R Square | W5: 0.063441763 | AB5: R Square | AC5: 0.39119385
A6: =Elasticities!G7 -> Germany | B6: =Elasticities!I7 -> 46260.26 | C6: =Elasticities!N7 -> -0.6815 | D6: =Elasticities!Q7 -> 0.96517076 | E6: =Elasticities!R7 -> -0.70609267 | F6: =Elasticities!U7 -> -0.77844013 | G6: =VLOOKUP(A6,WB_correlations!$D$2:$K$27,8,FALSE) -> 11.061564 | H6: =LN(B6) -> 10.742039 | I6: =(H6-MIN($H$2:$H$26))/(MAX($H$2:$H$26)-MIN($H$2:$H$26))*(MAX($D$2:$D$26)-MIN($D$2:$D$26))+MIN($D$2:$D$26) -> 7.6719086 | J6: =C6/I6 -> -0.088830568 | P6: Adjusted R Square | Q6: 0.28256551 | V6: Adjusted R Square | W6: 0.02272184 | AB6: Adjusted R Square | AC6: 0.36472402
A7: =Elasticities!G8 -> Estonia | B7: =Elasticities!I8 -> 22829.56 | C7: =Elasticities!N8 -> -1.447445 | D7: =Elasticities!Q8 -> 1.5304948 | E7: =Elasticities!R8 -> -0.94573665 | F7: =Elasticities!U8 -> -1.6533372 | G7: =VLOOKUP(A7,WB_correlations!$D$2:$K$27,8,FALSE) -> 10.671942 | H7: =LN(B7) -> 10.035811 | I7: =(H7-MIN($H$2:$H$26))/(MAX($H$2:$H$26)-MIN($H$2:$H$26))*(MAX($D$2:$D$26)-MIN($D$2:$D$26))+MIN($D$2:$D$26) -> 3.8651428 | J7: =C7/I7 -> -0.37448681 | P7: Standard Error | Q7: 0.48750557 | V7: Standard Error | W7: 0.39374614 | AB7: Standard Error | AC7: 0.32300161
A8: =Elasticities!G10 -> Greece | B8: =Elasticities!I10 -> 15440.44 | C8: =Elasticities!N10 -> -0.86575 | D8: =Elasticities!Q10 -> 8.4756574 | E8: =Elasticities!R10 -> -0.10214547 | F8: =Elasticities!U10 -> -0.98889882 | G8: =VLOOKUP(A8,WB_correlations!$D$2:$K$27,8,FALSE) -> 10.486578 | H8: =LN(B8) -> 9.6447453 | I8: =(H8-MIN($H$2:$H$26))/(MAX($H$2:$H$26)-MIN($H$2:$H$26))*(MAX($D$2:$D$26)-MIN($D$2:$D$26))+MIN($D$2:$D$26) -> 1.7571845 | J8: =C8/I8 -> -0.49269156 | P8: Observations | Q8: 25 | V8: Observations | W8: 25 | AB8: Observations | AC8: 25
A9: =Elasticities!G11 -> Spain | B9: =Elasticities!I11 -> 28982 | C9: =Elasticities!N11 -> -0.507701 | D9: =Elasticities!Q11 -> 1.1830037 | E9: =Elasticities!R11 -> -0.42916264 | F9: =Elasticities!U11 -> -0.57991905 | G9: =VLOOKUP(A9,WB_correlations!$D$2:$K$27,8,FALSE) -> 10.752216 | H9: =LN(B9) -> 10.27443 | I9: =(H9-MIN($H$2:$H$26))/(MAX($H$2:$H$26)-MIN($H$2:$H$26))*(MAX($D$2:$D$26)-MIN($D$2:$D$26))+MIN($D$2:$D$26) -> 5.1513661 | J9: =C9/I9 -> -0.098556575
A10: =Elasticities!G12 -> France | B10: =Elasticities!I12 -> 37659.4 | C10: =Elasticities!N12 -> -0.597106 | D10: =Elasticities!Q12 -> 1.0138234 | E10: =Elasticities!R12 -> -0.58896453 | F10: =Elasticities!U12 -> -0.68204149 | G10: =VLOOKUP(A10,WB_correlations!$D$2:$K$27,8,FALSE) -> 10.890681 | H10: =LN(B10) -> 10.536338 | I10: =(H10-MIN($H$2:$H$26))/(MAX($H$2:$H$26)-MIN($H$2:$H$26))*(MAX($D$2:$D$26)-MIN($D$2:$D$26))+MIN($D$2:$D$26) -> 6.5631231 | J10: =C10/I10 -> -0.090978942 | P10: ANOVA | V10: ANOVA | AB10: ANOVA
A11: =Elasticities!G13 -> Croatia | B11: =Elasticities!I13 -> 20163.56 | C11: =Elasticities!N13 -> -1.654745 | D11: =Elasticities!Q13 -> 2.1728752 | E11: =Elasticities!R13 -> -0.76154626 | F11: =Elasticities!U13 -> -1.8901246 | G11: =VLOOKUP(A11,WB_correlations!$D$2:$K$27,8,FALSE) -> 10.593229 | H11: =LN(B11) -> 9.9116323 | I11: =(H11-MIN($H$2:$H$26))/(MAX($H$2:$H$26)-MIN($H$2:$H$26))*(MAX($D$2:$D$26)-MIN($D$2:$D$26))+MIN($D$2:$D$26) -> 3.1957816 | J11: =C11/I11 -> -0.51779039 | Q11: df | R11: SS | S11: MS | T11: F | U11: Significance F | W11: df | X11: SS | Y11: MS | Z11: F | AA11: Significance F | AC11: df | AD11: SS | AE11: MS | AF11: F | AG11: Significance F
A12: =Elasticities!G14 -> Italy | B12: =Elasticities!I14 -> 28829.78 | C12: =Elasticities!N14 -> -0.925037 | D12: =Elasticities!Q14 -> 1.1892501 | E12: =Elasticities!R14 -> -0.77783219 | F12: =Elasticities!U14 -> -1.0566191 | G12: =VLOOKUP(A12,WB_correlations!$D$2:$K$27,8,FALSE) -> 10.865389 | H12: =LN(B12) -> 10.269164 | I12: =(H12-MIN($H$2:$H$26))/(MAX($H$2:$H$26)-MIN($H$2:$H$26))*(MAX($D$2:$D$26)-MIN($D$2:$D$26))+MIN($D$2:$D$26) -> 5.1229805 | J12: =C12/I12 -> -0.18056618 | P12: Regression | Q12: 1 | R12: 2.4841662 | S12: 2.4841662 | T12: 10.452532 | U12: 0.0036763039 | V12: Regression | W12: 1 | X12: 0.24154659 | Y12: 0.24154659 | Z12: 1.558003 | AA12: 0.22451558 | AB12: Regression | AC12: 1 | AD12: 1.5418786 | AE12: 1.5418786 | AF12: 14.778856 | AG12: 0.00082740912
A13: =Elasticities!G15 -> Cyprus | B13: =Elasticities!I15 -> 23745.46 | C13: =Elasticities!N15 -> -0.902163 | D13: =Elasticities!Q15 -> 1.4717468 | E13: =Elasticities!R15 -> -0.61298791 | F13: =Elasticities!U15 -> -1.0304914 | G13: =VLOOKUP(A13,WB_correlations!$D$2:$K$27,8,FALSE) -> 10.832177 | H13: =LN(B13) -> 10.075147 | I13: =(H13-MIN($H$2:$H$26))/(MAX($H$2:$H$26)-MIN($H$2:$H$26))*(MAX($D$2:$D$26)-MIN($D$2:$D$26))+MIN($D$2:$D$26) -> 4.0771706 | J13: =C13/I13 -> -0.22127183 | P13: Residual | Q13: 23 | R13: 5.4662186 | S13: 0.23766168 | V13: Residual | W13: 23 | X13: 3.5658285 | Y13: 0.15503602 | AB13: Residual | AC13: 23 | AD13: 2.3995909 | AE13: 0.10433004
A14: =Elasticities!G16 -> Latvia | B14: =Elasticities!I16 -> 19145.32 | C14: =Elasticities!N16 -> -1.511516 | D14: =Elasticities!Q16 -> 2.6254398 | E14: =Elasticities!R16 -> -0.57571916 | F14: =Elasticities!U16 -> -1.726522 | G14: =VLOOKUP(A14,WB_correlations!$D$2:$K$27,8,FALSE) -> 10.537912 | H14: =LN(B14) -> 9.8598136 | I14: =(H14-MIN($H$2:$H$26))/(MAX($H$2:$H$26)-MIN($H$2:$H$26))*(MAX($D$2:$D$26)-MIN($D$2:$D$26))+MIN($D$2:$D$26) -> 2.9164639 | J14: =C14/I14 -> -0.51827009 | P14: Total | Q14: 24 | R14: 7.9503848 | V14: Total | W14: 24 | X14: 3.8073751 | AB14: Total | AC14: 24 | AD14: 3.9414695
A15: =Elasticities!G17 -> Lithuania | B15: =Elasticities!I17 -> 25029.44 | C15: =Elasticities!N17 -> -2.173113 | D15: =Elasticities!Q17 -> 1.3928859 | E15: =Elasticities!R17 -> -1.5601515 | F15: =Elasticities!U17 -> -2.482228 | G15: =VLOOKUP(A15,WB_correlations!$D$2:$K$27,8,FALSE) -> 10.750454 | H15: =LN(B15) -> 10.127808 | I15: =(H15-MIN($H$2:$H$26))/(MAX($H$2:$H$26)-MIN($H$2:$H$26))*(MAX($D$2:$D$26)-MIN($D$2:$D$26))+MIN($D$2:$D$26) -> 4.3610305 | J15: =C15/I15 -> -0.49830264
A16: =Elasticities!G18 -> Luxembourg | B16: =Elasticities!I18 -> 71353.34 | C16: =Elasticities!N18 -> -0.492895 | D16: =Elasticities!Q18 -> 0.92551771 | E16: =Elasticities!R18 -> -0.53256139 | F16: =Elasticities!U18 -> -0.56300697 | G16: =VLOOKUP(A16,WB_correlations!$D$2:$K$27,8,FALSE) -> 11.794872 | H16: =LN(B16) -> 11.175399 | I16: =(H16-MIN($H$2:$H$26))/(MAX($H$2:$H$26)-MIN($H$2:$H$26))*(MAX($D$2:$D$26)-MIN($D$2:$D$26))+MIN($D$2:$D$26) -> 10.007848 | J16: =C16/I16 -> -0.04925085 | Q16: Coefficients | R16: Standard Error | S16: t Stat | T16: P-value | W16: Coefficients | X16: Standard Error | Y16: t Stat | Z16: P-value | AC16: Coefficients | AD16: Standard Error | AE16: t Stat | AF16: P-value
A17: =Elasticities!G19 -> Hungary | B17: =Elasticities!I19 -> 15876.46 | C17: =Elasticities!N19 -> -1.114468 | D17: =Elasticities!Q19 -> 6.1670153 | E17: =Elasticities!R19 -> -0.18071432 | F17: =Elasticities!U19 -> -1.2729958 | G17: =VLOOKUP(A17,WB_correlations!$D$2:$K$27,8,FALSE) -> 10.611794 | H17: =LN(B17) -> 9.6725928 | I17: =(H17-MIN($H$2:$H$26))/(MAX($H$2:$H$26)-MIN($H$2:$H$26))*(MAX($D$2:$D$26)-MIN($D$2:$D$26))+MIN($D$2:$D$26) -> 1.9072903 | J17: =C17/I17 -> -0.58432005 | P17: Intercept | Q17: -13.262931 | R17: 3.7037252 | S17: -3.5809707 | T17: 0.0015820765 | V17: Intercept | W17: 3.0501716 | X17: 2.9914068 | Y17: 1.0196445 | Z17: 0.31850331 | AA17: -3.1380249 | AB17: Intercept | AC17: -9.7991273 | AD17: 2.4539395 | AE17: -3.9932228 | AF17: 0.00057208864
A18: =Elasticities!G20 -> Malta | B18: =Elasticities!I20 -> 28809.14 | C18: =Elasticities!N20 -> -0.361679 | D18: =Elasticities!Q20 -> 1.1901232 | E18: =Elasticities!R20 -> -0.30390047 | F18: =Elasticities!U20 -> -0.41312612 | G18: =VLOOKUP(A18,WB_correlations!$D$2:$K$27,8,FALSE) -> 10.94803 | H18: =LN(B18) -> 10.268448 | I18: =(H18-MIN($H$2:$H$26))/(MAX($H$2:$H$26)-MIN($H$2:$H$26))*(MAX($D$2:$D$26)-MIN($D$2:$D$26))+MIN($D$2:$D$26) -> 5.1191201 | J18: =C18/I18 -> -0.070652572 | P18: log(GDP) | Q18: 1.1064545 | R18: 0.34223372 | S18: 3.2330376 | T18: 0.0036763039 | V18: log(GDP) | W18: -0.34501952 | X18: 0.27641367 | Y18: -1.2481999 | Z18: 0.22451558 | AA18: -0.91682477 | AB18: log(GDP) | AC18: 0.87170253 | AD18: 0.22675031 | AE18: 3.8443278 | AF18: 0.00082740912
A19: =Elasticities!G21 -> Austria | B19: =Elasticities!I21 -> 50396 | C19: =Elasticities!N21 -> -0.548534 | D19: =Elasticities!Q21 -> 0.95327083 | E19: =Elasticities!R21 -> -0.57542304 | F19: =Elasticities!U21 -> -0.62656035 | G19: =VLOOKUP(A19,WB_correlations!$D$2:$K$27,8,FALSE) -> 11.092771 | H19: =LN(B19) -> 10.827667 | I19: =(H19-MIN($H$2:$H$26))/(MAX($H$2:$H$26)-MIN($H$2:$H$26))*(MAX($D$2:$D$26)-MIN($D$2:$D$26))+MIN($D$2:$D$26) -> 8.1334709 | J19: =C19/I19 -> -0.067441565
A20: =Elasticities!G22 -> Poland | B20: =Elasticities!I22 -> 18271.56 | C20: =Elasticities!N22 -> -1.668281 | D20: =Elasticities!Q22 -> 3.1194633 | E20: =Elasticities!R22 -> -0.53479744 | F20: =Elasticities!U22 -> -1.905586 | G20: =VLOOKUP(A20,WB_correlations!$D$2:$K$27,8,FALSE) -> 10.67833 | H20: =LN(B20) -> 9.813101 | I20: =(H20-MIN($H$2:$H$26))/(MAX($H$2:$H$26)-MIN($H$2:$H$26))*(MAX($D$2:$D$26)-MIN($D$2:$D$26))+MIN($D$2:$D$26) -> 2.6646699 | J20: =C20/I20 -> -0.62607417
A21: =Elasticities!G23 -> Portugal | B21: =Elasticities!I23 -> 21343.48 | C21: =Elasticities!N23 -> -0.939169 | D21: =Elasticities!Q23 -> 1.7555694 | E21: =Elasticities!R23 -> -0.53496547 | F21: =Elasticities!U23 -> -1.0727613 | G21: =VLOOKUP(A21,WB_correlations!$D$2:$K$27,8,FALSE) -> 10.623054 | H21: =LN(B21) -> 9.9685016 | I21: =(H21-MIN($H$2:$H$26))/(MAX($H$2:$H$26)-MIN($H$2:$H$26))*(MAX($D$2:$D$26)-MIN($D$2:$D$26))+MIN($D$2:$D$26) -> 3.5023233 | J21: =C21/I21 -> -0.268156
A22: =Elasticities!G24 -> Romania | B22: =Elasticities!I24 -> 18152.88 | C22: =Elasticities!N24 -> -1.711433 | D22: =Elasticities!Q24 -> 3.196976 | E22: =Elasticities!R24 -> -0.5353287 | F22: =Elasticities!U24 -> -1.9548762 | G22: =VLOOKUP(A22,WB_correlations!$D$2:$K$27,8,FALSE) -> 10.577885 | H22: =LN(B22) -> 9.8065845 | I22: =(H22-MIN($H$2:$H$26))/(MAX($H$2:$H$26)-MIN($H$2:$H$26))*(MAX($D$2:$D$26)-MIN($D$2:$D$26))+MIN($D$2:$D$26) -> 2.629544 | J22: =C22/I22 -> -0.65084783
A23: =Elasticities!G25 -> Slovenia | B23: =Elasticities!I25 -> 30214.38 | C23: =Elasticities!N25 -> -1.279554 | D23: =Elasticities!Q25 -> 1.1402136 | E23: =Elasticities!R25 -> -1.1222056 | F23: =Elasticities!U25 -> -1.4615645 | G23: =VLOOKUP(A23,WB_correlations!$D$2:$K$27,8,FALSE) -> 10.758968 | H23: =LN(B23) -> 10.316073 | I23: =(H23-MIN($H$2:$H$26))/(MAX($H$2:$H$26)-MIN($H$2:$H$26))*(MAX($D$2:$D$26)-MIN($D$2:$D$26))+MIN($D$2:$D$26) -> 5.3758339 | J23: =C23/I23 -> -0.23801963
A24: =Elasticities!G26 -> Slovakia | B24: =Elasticities!I26 -> 17446.82 | C24: =Elasticities!N26 -> -1.516326 | D24: =Elasticities!Q26 -> 3.7403585 | E24: =Elasticities!R26 -> -0.4053959 | F24: =Elasticities!U26 -> -1.7320162 | G24: =VLOOKUP(A24,WB_correlations!$D$2:$K$27,8,FALSE) -> 10.562688 | H24: =LN(B24) -> 9.7669127 | I24: =(H24-MIN($H$2:$H$26))/(MAX($H$2:$H$26)-MIN($H$2:$H$26))*(MAX($D$2:$D$26)-MIN($D$2:$D$26))+MIN($D$2:$D$26) -> 2.4157015 | J24: =C24/I24 -> -0.62769593
A25: =Elasticities!G27 -> Finland | B25: =Elasticities!I27 -> 42508.08 | C25: =Elasticities!N27 -> -1.756347 | D25: =Elasticities!Q27 -> 0.98097942 | E25: =Elasticities!R27 -> -1.7904015 | F25: =Elasticities!U27 -> -2.006179 | G25: =VLOOKUP(A25,WB_correlations!$D$2:$K$27,8,FALSE) -> 10.952004 | H25: =LN(B25) -> 10.657449 | I25: =(H25-MIN($H$2:$H$26))/(MAX($H$2:$H$26)-MIN($H$2:$H$26))*(MAX($D$2:$D$26)-MIN($D$2:$D$26))+MIN($D$2:$D$26) -> 7.2159492 | J25: =C25/I25 -> -0.24339792
A26: =Elasticities!G28 -> Sweden | B26: =Elasticities!I28 -> 40011.5 | C26: =Elasticities!N28 -> -0.966849 | D26: =Elasticities!Q28 -> 0.99569021 | E26: =Elasticities!R28 -> -0.97103395 | F26: =Elasticities!U28 -> -1.1043787 | G26: =VLOOKUP(A26,WB_correlations!$D$2:$K$27,8,FALSE) -> 11.052293 | H26: =LN(B26) -> 10.596922 | I26: =(H26-MIN($H$2:$H$26))/(MAX($H$2:$H$26)-MIN($H$2:$H$26))*(MAX($D$2:$D$26)-MIN($D$2:$D$26))+MIN($D$2:$D$26) -> 6.8896899 | J26: =C26/I26 -> -0.14033273
