Workbook

Sheet Bulgaria
A1: SDR=3%
A2: Label | B2: Value or formula
A3: 2024 wage in euros | B3: 15387
A4: EUR to GBP rate | B4: 0.848248
A5: Annual wage growth | B5: 0.02
A6: Years to first repayment | B6: 1
A7: 2024 wage in GBP | B7: =B3*B4 -> 13051.992
A8: First repayment-year earnings | B8: =B7*(1+B5)^B6 -> 13313.032
A9: Opening loan balance | B9: 9250
A10: Post-Brexit price | B10: 22200
A11: Repayment rate | B11: 0.09
A12: Lower threshold | B12: 11390
A13: Upper threshold | B13: 20500
A14: First RPI rate | B14: 0.043
A15: Months at first RPI rate | B15: 5
A16: Second RPI rate | B16: 0.032 | D16: monthly increase in income | E16: =-(B25-AE25)/12 -> 860.73709
A17: Months at second RPI rate | B17: 7
A18: Fixed weighted RPI | B18: =(B14*B15+B16*B17)/(B15+B17) -> 0.036583333
A19: Maximum interest spread | B19: 0.03
A20: Subjective discount rate | B20: 0.03
A21: Controlled TWFE coefficient | B21: -1.780743
A24: Repayment year | B24: 1 | C24: 2 | D24: 3 | E24: 4 | F24: 5 | G24: 6 | H24: 7 | I24: 8 | J24: 9 | K24: 10 | L24: 11 | M24: 12 | N24: 13 | O24: 14 | P24: 15 | Q24: 16 | R24: 17 | S24: 18 | T24: 19 | U24: 20 | V24: 21 | W24: 22 | X24: 23 | Y24: 24 | Z24: 25 | AA24: 26 | AB24: 27 | AC24: 28 | AD24: 29 | AE24: 30
A25: Earnings | B25: =$B$8 -> 13313.032 | C25: =$B$8*(1+$B$5)^(C$24-1) -> 13579.292 | D25: =$B$8*(1+$B$5)^(D$24-1) -> 13850.878 | E25: =$B$8*(1+$B$5)^(E$24-1) -> 14127.896 | F25: =$B$8*(1+$B$5)^(F$24-1) -> 14410.454 | G25: =$B$8*(1+$B$5)^(G$24-1) -> 14698.663 | H25: =$B$8*(1+$B$5)^(H$24-1) -> 14992.636 | I25: =$B$8*(1+$B$5)^(I$24-1) -> 15292.489 | J25: =$B$8*(1+$B$5)^(J$24-1) -> 15598.339 | ... AE25: =$B$8*(1+$B$5)^(AE$24-1) -> 23641.877
A26: Income loading | B26: =IF(B25<=$B$12,0,IF(B25<$B$13,(B25-$B$12)/($B$13-$B$12),1)) -> 0.21109021 | C26: =IF(C25<=$B$12,0,IF(C25<$B$13,(C25-$B$12)/($B$13-$B$12),1)) -> 0.2403175 | D26: =IF(D25<=$B$12,0,IF(D25<$B$13,(D25-$B$12)/($B$13-$B$12),1)) -> 0.27012934 | E26: =IF(E25<=$B$12,0,IF(E25<$B$13,(E25-$B$12)/($B$13-$B$12),1)) -> 0.30053742 | F26: =IF(F25<=$B$12,0,IF(F25<$B$13,(F25-$B$12)/($B$13-$B$12),1)) -> 0.33155365 | G26: =IF(G25<=$B$12,0,IF(G25<$B$13,(G25-$B$12)/($B$13-$B$12),1)) -> 0.36319022 | H26: =IF(H25<=$B$12,0,IF(H25<$B$13,(H25-$B$12)/($B$13-$B$12),1)) -> 0.39545951 | I26: =IF(I25<=$B$12,0,IF(I25<$B$13,(I25-$B$12)/($B$13-$B$12),1)) -> 0.42837419 | ... AE26: =IF(AE25<=$B$12,0,IF(AE25<$B$13,(AE25-$B$12)/($B$13-$B$12),1)) -> 1
A27: Interest rate | B27: =$B$18+$B$19*B26 -> 0.04291604 | C27: =$B$18+$B$19*C26 -> 0.043792858 | D27: =$B$18+$B$19*D26 -> 0.044687214 | E27: =$B$18+$B$19*E26 -> 0.045599456 | F27: =$B$18+$B$19*F26 -> 0.046529943 | G27: =$B$18+$B$19*G26 -> 0.04747904 | H27: =$B$18+$B$19*H26 -> 0.048447119 | I27: =$B$18+$B$19*I26 -> 0.049434559 | ... AE27: =$B$18+$B$19*AE26 -> 0.066583333
A28: Opening balance | B28: =$B$9 -> 9250 | C28: =B32 -> 9473.9005 | D28: =C32 -> 9691.7534 | E28: =D32 -> 9903.3718 | F28: =E32 -> 10108.55 | G28: =F32 -> 10307.059 | H28: =G32 -> 10498.649 | I28: =H32 -> 10683.041 | J28: =I32 -> 10859.928 | ... AE28: =AD32 -> 11282.922
A29: Balance after interest | B29: =B28*(1+B27) -> 9646.9734 | C29: =C28*(1+C27) -> 9888.7897 | D29: =D28*(1+D27) -> 10124.851 | E29: =E28*(1+E27) -> 10354.96 | F29: =F28*(1+F27) -> 10578.9 | G29: =G28*(1+G27) -> 10796.428 | H29: =H28*(1+H27) -> 11007.278 | I29: =I28*(1+I27) -> 11211.152 | ... AE29: =AE28*(1+AE27) -> 12034.176
A30: Scheduled repayment | B30: =$B$11*MAX(0,B25-$B$12) -> 173.07286 | C30: =$B$11*MAX(0,C25-$B$12) -> 197.03632 | D30: =$B$11*MAX(0,D25-$B$12) -> 221.47905 | E30: =$B$11*MAX(0,E25-$B$12) -> 246.41063 | F30: =$B$11*MAX(0,F25-$B$12) -> 271.84084 | G30: =$B$11*MAX(0,G25-$B$12) -> 297.77966 | H30: =$B$11*MAX(0,H25-$B$12) -> 324.23725 | I30: =$B$11*MAX(0,I25-$B$12) -> 351.224 | ... AE30: =$B$11*MAX(0,AE25-$B$12) -> 1102.6689
A31: Actual repayment | B31: =MIN(B30,B29) -> 173.07286 | C31: =MIN(C30,C29) -> 197.03632 | D31: =MIN(D30,D29) -> 221.47905 | E31: =MIN(E30,E29) -> 246.41063 | F31: =MIN(F30,F29) -> 271.84084 | G31: =MIN(G30,G29) -> 297.77966 | H31: =MIN(H30,H29) -> 324.23725 | I31: =MIN(I30,I29) -> 351.224 | ... AE31: =MIN(AE30,AE29) -> 1102.6689
A32: Closing balance | B32: =B29-B31 -> 9473.9005 | C32: =C29-C31 -> 9691.7534 | D32: =D29-D31 -> 9903.3718 | E32: =E29-E31 -> 10108.55 | F32: =F29-F31 -> 10307.059 | G32: =G29-G31 -> 10498.649 | H32: =H29-H31 -> 10683.041 | I32: =I29-I31 -> 10859.928 | ... AE32: =AE29-AE31 -> 10931.507
A33: Discount factor | B33: =1/(1+$B$20) -> 0.97087379 | C33: =1/(1+$B$20)^C$24 -> 0.94259591 | D33: =1/(1+$B$20)^D$24 -> 0.91514166 | E33: =1/(1+$B$20)^E$24 -> 0.88848705 | F33: =1/(1+$B$20)^F$24 -> 0.86260878 | G33: =1/(1+$B$20)^G$24 -> 0.83748426 | H33: =1/(1+$B$20)^H$24 -> 0.81309151 | I33: =1/(1+$B$20)^I$24 -> 0.78940923 | J33: =1/(1+$B$20)^J$24 -> 0.76641673 | ... AE33: =1/(1+$B$20)^AE$24 -> 0.41198676
A34: PV repayment | B34: =B31*B33 -> 168.03191 | C34: =C31*C33 -> 185.72563 | D34: =D31*D33 -> 202.6847 | E34: =E31*E33 -> 218.93265 | F34: =F31*F33 -> 234.4923 | G34: =G31*G33 -> 249.38578 | H34: =H31*H33 -> 263.63456 | I34: =I31*I33 -> 277.25947 | ... AE34: =AE31*AE33 -> 454.28499
A37: Loan PV at 3% | B37: =SUM(B34:AE34) -> 10310.387
A38: Log experienced price change | B38: =LN($B$10)-LN(B37) -> 0.7669405
A39: Implied elasticity | B39: =$B$21/B38 -> -2.3218789
A40: Balance written off after year 30 | B40: =AE32 -> 10931.507
A42: SDR=14.9%
A43: Label | B43: Value or formula
A44: 2024 wage in euros | B44: 15387
A45: EUR to GBP rate | B45: 0.848248
A46: Annual wage growth | B46: 0.02
A47: Years to first repayment | B47: 1
A48: 2024 wage in GBP | B48: =B44*B45 -> 13051.992
A49: First repayment-year earnings | B49: =B48*(1+B46)^B47 -> 13313.032
A50: Opening loan balance | B50: 9250
A51: Post-Brexit price | B51: 22200
A52: Repayment rate | B52: 0.09
A53: Lower threshold | B53: 11390
A54: Upper threshold | B54: 20500
A55: First RPI rate | B55: 0.043
A56: Months at first RPI rate | B56: 5
A57: Second RPI rate | B57: 0.032
A58: Months at second RPI rate | B58: 7
A59: Fixed weighted RPI | B59: =(B55*B56+B57*B58)/(B56+B58) -> 0.036583333
A60: Maximum interest spread | B60: 0.03
A61: Subjective discount rate | B61: 0.149
A62: Controlled TWFE coefficient | B62: -1.780743
A65: Repayment year | B65: 1 | C65: 2 | D65: 3 | E65: 4 | F65: 5 | G65: 6 | H65: 7 | I65: 8 | J65: 9 | K65: 10 | L65: 11 | M65: 12 | N65: 13 | O65: 14 | P65: 15 | Q65: 16 | R65: 17 | S65: 18 | T65: 19 | U65: 20 | V65: 21 | W65: 22 | X65: 23 | Y65: 24 | Z65: 25 | AA65: 26 | AB65: 27 | AC65: 28 | AD65: 29 | AE65: 30
A66: Earnings | B66: =$B$8 -> 13313.032 | C66: =$B$8*(1+$B$5)^(C$24-1) -> 13579.292 | D66: =$B$8*(1+$B$5)^(D$24-1) -> 13850.878 | E66: =$B$8*(1+$B$5)^(E$24-1) -> 14127.896 | F66: =$B$8*(1+$B$5)^(F$24-1) -> 14410.454 | G66: =$B$8*(1+$B$5)^(G$24-1) -> 14698.663 | H66: =$B$8*(1+$B$5)^(H$24-1) -> 14992.636 | I66: =$B$8*(1+$B$5)^(I$24-1) -> 15292.489 | J66: =$B$8*(1+$B$5)^(J$24-1) -> 15598.339 | ... AE66: =$B$8*(1+$B$5)^(AE$24-1) -> 23641.877
A67: Income loading | B67: =IF(B66<=$B$12,0,IF(B66<$B$13,(B66-$B$12)/($B$13-$B$12),1)) -> 0.21109021 | C67: =IF(C66<=$B$12,0,IF(C66<$B$13,(C66-$B$12)/($B$13-$B$12),1)) -> 0.2403175 | D67: =IF(D66<=$B$12,0,IF(D66<$B$13,(D66-$B$12)/($B$13-$B$12),1)) -> 0.27012934 | E67: =IF(E66<=$B$12,0,IF(E66<$B$13,(E66-$B$12)/($B$13-$B$12),1)) -> 0.30053742 | F67: =IF(F66<=$B$12,0,IF(F66<$B$13,(F66-$B$12)/($B$13-$B$12),1)) -> 0.33155365 | G67: =IF(G66<=$B$12,0,IF(G66<$B$13,(G66-$B$12)/($B$13-$B$12),1)) -> 0.36319022 | H67: =IF(H66<=$B$12,0,IF(H66<$B$13,(H66-$B$12)/($B$13-$B$12),1)) -> 0.39545951 | I67: =IF(I66<=$B$12,0,IF(I66<$B$13,(I66-$B$12)/($B$13-$B$12),1)) -> 0.42837419 | ... AE67: =IF(AE66<=$B$12,0,IF(AE66<$B$13,(AE66-$B$12)/($B$13-$B$12),1)) -> 1
A68: Interest rate | B68: =$B$18+$B$19*B67 -> 0.04291604 | C68: =$B$18+$B$19*C67 -> 0.043792858 | D68: =$B$18+$B$19*D67 -> 0.044687214 | E68: =$B$18+$B$19*E67 -> 0.045599456 | F68: =$B$18+$B$19*F67 -> 0.046529943 | G68: =$B$18+$B$19*G67 -> 0.04747904 | H68: =$B$18+$B$19*H67 -> 0.048447119 | I68: =$B$18+$B$19*I67 -> 0.049434559 | ... AE68: =$B$18+$B$19*AE67 -> 0.066583333
A69: Opening balance | B69: =$B$9 -> 9250 | C69: =B73 -> 9473.9005 | D69: =C73 -> 9691.7534 | E69: =D73 -> 9903.3718 | F69: =E73 -> 10108.55 | G69: =F73 -> 10307.059 | H69: =G73 -> 10498.649 | I69: =H73 -> 10683.041 | J69: =I73 -> 10859.928 | ... AE69: =AD73 -> 11282.922
A70: Balance after interest | B70: =B69*(1+B68) -> 9646.9734 | C70: =C69*(1+C68) -> 9888.7897 | D70: =D69*(1+D68) -> 10124.851 | E70: =E69*(1+E68) -> 10354.96 | F70: =F69*(1+F68) -> 10578.9 | G70: =G69*(1+G68) -> 10796.428 | H70: =H69*(1+H68) -> 11007.278 | I70: =I69*(1+I68) -> 11211.152 | ... AE70: =AE69*(1+AE68) -> 12034.176
A71: Scheduled repayment | B71: =$B$11*MAX(0,B66-$B$12) -> 173.07286 | C71: =$B$11*MAX(0,C66-$B$12) -> 197.03632 | D71: =$B$11*MAX(0,D66-$B$12) -> 221.47905 | E71: =$B$11*MAX(0,E66-$B$12) -> 246.41063 | F71: =$B$11*MAX(0,F66-$B$12) -> 271.84084 | G71: =$B$11*MAX(0,G66-$B$12) -> 297.77966 | H71: =$B$11*MAX(0,H66-$B$12) -> 324.23725 | I71: =$B$11*MAX(0,I66-$B$12) -> 351.224 | ... AE71: =$B$11*MAX(0,AE66-$B$12) -> 1102.6689
A72: Actual repayment | B72: =MIN(B71,B70) -> 173.07286 | C72: =MIN(C71,C70) -> 197.03632 | D72: =MIN(D71,D70) -> 221.47905 | E72: =MIN(E71,E70) -> 246.41063 | F72: =MIN(F71,F70) -> 271.84084 | G72: =MIN(G71,G70) -> 297.77966 | H72: =MIN(H71,H70) -> 324.23725 | I72: =MIN(I71,I70) -> 351.224 | ... AE72: =MIN(AE71,AE70) -> 1102.6689
A73: Closing balance | B73: =B70-B72 -> 9473.9005 | C73: =C70-C72 -> 9691.7534 | D73: =D70-D72 -> 9903.3718 | E73: =E70-E72 -> 10108.55 | F73: =F70-F72 -> 10307.059 | G73: =G70-G72 -> 10498.649 | H73: =H70-H72 -> 10683.041 | I73: =I70-I72 -> 10859.928 | ... AE73: =AE70-AE72 -> 10931.507
A74: Discount factor | B74: =1/(1+$B$61)^B65 -> 0.87032202 | C74: =1/(1+$B$61)^C65 -> 0.75746042 | D74: =1/(1+$B$61)^D65 -> 0.65923448 | E74: =1/(1+$B$61)^E65 -> 0.57374628 | F74: =1/(1+$B$61)^F65 -> 0.49934402 | G74: =1/(1+$B$61)^G65 -> 0.4345901 | H74: =1/(1+$B$61)^H65 -> 0.37823333 | I74: =1/(1+$B$61)^I65 -> 0.3291848 | ... AE74: =1/(1+$B$61)^AE65 -> 0.015502407
A75: PV repayment | B75: =B72*B74 -> 150.62912 | C75: =C72*C74 -> 149.24721 | D75: =D72*D74 -> 146.00662 | E75: =E72*E74 -> 141.37718 | F75: =F72*F74 -> 135.7421 | G75: =G72*G74 -> 129.41209 | H75: =H72*H74 -> 122.63734 | I75: =I72*I74 -> 115.6176 | ... AE75: =AE72*AE74 -> 17.094023
A78: Loan PV at 3% | B78: =SUM(B75:AE75) -> 2254.1345
A79: Log experienced price change | B79: =LN($B$10)-LN(B78) -> 2.2873262
A80: Implied elasticity | B80: =$B$21/B79 -> -0.77852604
A81: Balance written off after year 30 | B81: =AE73 -> 10931.507
A83: SDR=35.00%
A84: Label | B84: Value or formula
A85: 2024 wage in euros | B85: 15387
A86: EUR to GBP rate | B86: 0.848248
A87: Annual wage growth | B87: 0.02
A88: Years to first repayment | B88: 1
A89: 2024 wage in GBP | B89: =B85*B86 -> 13051.992
A90: First repayment-year earnings | B90: =B89*(1+B87)^B88 -> 13313.032
A91: Opening loan balance | B91: 9250
A92: Post-Brexit price | B92: 22200
A93: Repayment rate | B93: 0.09
A94: Lower threshold | B94: 11390
A95: Upper threshold | B95: 20500
A96: First RPI rate | B96: 0.043
A97: Months at first RPI rate | B97: 5
A98: Second RPI rate | B98: 0.032
A99: Months at second RPI rate | B99: 7
A100: Fixed weighted RPI | B100: =(B96*B97+B98*B99)/(B97+B99) -> 0.036583333
A101: Maximum interest spread | B101: 0.03
A102: Subjective discount rate | B102: 0.35
A103: Controlled TWFE coefficient | B103: -1.780743
A106: Repayment year | B106: 1 | C106: 2 | D106: 3 | E106: 4 | F106: 5 | G106: 6 | H106: 7 | I106: 8 | J106: 9 | K106: 10 | L106: 11 | M106: 12 | N106: 13 | O106: 14 | P106: 15 | Q106: 16 | R106: 17 | S106: 18 | T106: 19 | U106: 20 | V106: 21 | W106: 22 | X106: 23 | Y106: 24 | Z106: 25 | AA106: 26 | AB106: 27 | AC106: 28 | AD106: 29 | AE106: 30
A107: Earnings | B107: =$B$8 -> 13313.032 | C107: =$B$8*(1+$B$5)^(C$24-1) -> 13579.292 | D107: =$B$8*(1+$B$5)^(D$24-1) -> 13850.878 | E107: =$B$8*(1+$B$5)^(E$24-1) -> 14127.896 | F107: =$B$8*(1+$B$5)^(F$24-1) -> 14410.454 | G107: =$B$8*(1+$B$5)^(G$24-1) -> 14698.663 | H107: =$B$8*(1+$B$5)^(H$24-1) -> 14992.636 | I107: =$B$8*(1+$B$5)^(I$24-1) -> 15292.489 | J107: =$B$8*(1+$B$5)^(J$24-1) -> 15598.339 | ... AE107: =$B$8*(1+$B$5)^(AE$24-1) -> 23641.877
A108: Income loading | B108: =IF(B107<=$B$12,0,IF(B107<$B$13,(B107-$B$12)/($B$13-$B$12),1)) -> 0.21109021 | C108: =IF(C107<=$B$12,0,IF(C107<$B$13,(C107-$B$12)/($B$13-$B$12),1)) -> 0.2403175 | D108: =IF(D107<=$B$12,0,IF(D107<$B$13,(D107-$B$12)/($B$13-$B$12),1)) -> 0.27012934 | E108: =IF(E107<=$B$12,0,IF(E107<$B$13,(E107-$B$12)/($B$13-$B$12),1)) -> 0.30053742 | F108: =IF(F107<=$B$12,0,IF(F107<$B$13,(F107-$B$12)/($B$13-$B$12),1)) -> 0.33155365 | G108: =IF(G107<=$B$12,0,IF(G107<$B$13,(G107-$B$12)/($B$13-$B$12),1)) -> 0.36319022 | H108: =IF(H107<=$B$12,0,IF(H107<$B$13,(H107-$B$12)/($B$13-$B$12),1)) -> 0.39545951 | I108: =IF(I107<=$B$12,0,IF(I107<$B$13,(I107-$B$12)/($B$13-$B$12),1)) -> 0.42837419 | ... AE108: =IF(AE107<=$B$12,0,IF(AE107<$B$13,(AE107-$B$12)/($B$13-$B$12),1)) -> 1
A109: Interest rate | B109: =$B$18+$B$19*B108 -> 0.04291604 | C109: =$B$18+$B$19*C108 -> 0.043792858 | D109: =$B$18+$B$19*D108 -> 0.044687214 | E109: =$B$18+$B$19*E108 -> 0.045599456 | F109: =$B$18+$B$19*F108 -> 0.046529943 | G109: =$B$18+$B$19*G108 -> 0.04747904 | H109: =$B$18+$B$19*H108 -> 0.048447119 | I109: =$B$18+$B$19*I108 -> 0.049434559 | ... AE109: =$B$18+$B$19*AE108 -> 0.066583333
A110: Opening balance | B110: =$B$9 -> 9250 | C110: =B114 -> 9473.9005 | D110: =C114 -> 9691.7534 | E110: =D114 -> 9903.3718 | F110: =E114 -> 10108.55 | G110: =F114 -> 10307.059 | H110: =G114 -> 10498.649 | I110: =H114 -> 10683.041 | J110: =I114 -> 10859.928 | ... AE110: =AD114 -> 11282.922
A111: Balance after interest | B111: =B110*(1+B109) -> 9646.9734 | C111: =C110*(1+C109) -> 9888.7897 | D111: =D110*(1+D109) -> 10124.851 | E111: =E110*(1+E109) -> 10354.96 | F111: =F110*(1+F109) -> 10578.9 | G111: =G110*(1+G109) -> 10796.428 | H111: =H110*(1+H109) -> 11007.278 | I111: =I110*(1+I109) -> 11211.152 | ... AE111: =AE110*(1+AE109) -> 12034.176
A112: Scheduled repayment | B112: =$B$11*MAX(0,B107-$B$12) -> 173.07286 | C112: =$B$11*MAX(0,C107-$B$12) -> 197.03632 | D112: =$B$11*MAX(0,D107-$B$12) -> 221.47905 | E112: =$B$11*MAX(0,E107-$B$12) -> 246.41063 | F112: =$B$11*MAX(0,F107-$B$12) -> 271.84084 | G112: =$B$11*MAX(0,G107-$B$12) -> 297.77966 | H112: =$B$11*MAX(0,H107-$B$12) -> 324.23725 | I112: =$B$11*MAX(0,I107-$B$12) -> 351.224 | ... AE112: =$B$11*MAX(0,AE107-$B$12) -> 1102.6689
...

Sheet Luxemourg
A1: SDR=3%
A2: Label | B2: Value or formula
A3: 2024 wage in euros | B3: =data!J11 -> 82969
A4: EUR to GBP rate | B4: 0.848248
A5: Annual wage growth | B5: 0.02
A6: Years to first repayment | B6: 1
A7: 2024 wage in GBP | B7: =B3*B4 -> 70378.288
A8: First repayment-year earnings | B8: =B7*(1+B5)^B6 -> 71785.854
A9: Opening loan balance | B9: 9250
A10: Post-Brexit price | B10: 22200
A11: Repayment rate | B11: 0.09
A12: Lower threshold | B12: =data!D18 -> 28470
A13: Upper threshold | B13: =data!E18 -> 51245
A14: First RPI rate | B14: 0.043
A15: Months at first RPI rate | B15: 5
A16: Second RPI rate | B16: 0.032
A17: Months at second RPI rate | B17: 7
A18: Fixed weighted RPI | B18: =(B14*B15+B16*B17)/(B15+B17) -> 0.036583333
A19: Maximum interest spread | B19: 0.03
A20: Subjective discount rate | B20: 0.03
A21: Controlled TWFE coefficient | B21: -0.5771991
A24: Repayment year | B24: 1 | C24: 2 | D24: 3 | E24: 4 | F24: 5 | G24: 6 | H24: 7 | I24: 8 | J24: 9 | K24: 10 | L24: 11 | M24: 12 | N24: 13 | O24: 14 | P24: 15 | Q24: 16 | R24: 17 | S24: 18 | T24: 19 | U24: 20 | V24: 21 | W24: 22 | X24: 23 | Y24: 24 | Z24: 25 | AA24: 26 | AB24: 27 | AC24: 28 | AD24: 29 | AE24: 30
A25: Earnings | B25: =$B$8 -> 71785.854 | C25: =$B$8*(1+$B$5)^(C$24-1) -> 73221.571 | D25: =$B$8*(1+$B$5)^(D$24-1) -> 74686.003 | E25: =$B$8*(1+$B$5)^(E$24-1) -> 76179.723 | F25: =$B$8*(1+$B$5)^(F$24-1) -> 77703.317 | G25: =$B$8*(1+$B$5)^(G$24-1) -> 79257.383 | H25: =$B$8*(1+$B$5)^(H$24-1) -> 80842.531 | I25: =$B$8*(1+$B$5)^(I$24-1) -> 82459.382 | J25: =$B$8*(1+$B$5)^(J$24-1) -> 84108.569 | ... AE25: =$B$8*(1+$B$5)^(AE$24-1) -> 127480.53
A26: Income loading | B26: =IF(B25<=$B$12,0,IF(B25<$B$13,(B25-$B$12)/($B$13-$B$12),1)) -> 1 | C26: =IF(C25<=$B$12,0,IF(C25<$B$13,(C25-$B$12)/($B$13-$B$12),1)) -> 1 | D26: =IF(D25<=$B$12,0,IF(D25<$B$13,(D25-$B$12)/($B$13-$B$12),1)) -> 1 | E26: =IF(E25<=$B$12,0,IF(E25<$B$13,(E25-$B$12)/($B$13-$B$12),1)) -> 1 | F26: =IF(F25<=$B$12,0,IF(F25<$B$13,(F25-$B$12)/($B$13-$B$12),1)) -> 1 | G26: =IF(G25<=$B$12,0,IF(G25<$B$13,(G25-$B$12)/($B$13-$B$12),1)) -> 1 | H26: =IF(H25<=$B$12,0,IF(H25<$B$13,(H25-$B$12)/($B$13-$B$12),1)) -> 1 | I26: =IF(I25<=$B$12,0,IF(I25<$B$13,(I25-$B$12)/($B$13-$B$12),1)) -> 1 | ... AE26: =IF(AE25<=$B$12,0,IF(AE25<$B$13,(AE25-$B$12)/($B$13-$B$12),1)) -> 1
A27: Interest rate | B27: =$B$18+$B$19*B26 -> 0.066583333 | C27: =$B$18+$B$19*C26 -> 0.066583333 | D27: =$B$18+$B$19*D26 -> 0.066583333 | E27: =$B$18+$B$19*E26 -> 0.066583333 | F27: =$B$18+$B$19*F26 -> 0.066583333 | G27: =$B$18+$B$19*G26 -> 0.066583333 | H27: =$B$18+$B$19*H26 -> 0.066583333 | I27: =$B$18+$B$19*I26 -> 0.066583333 | ... AE27: =$B$18+$B$19*AE26 -> 0.066583333
A28: Opening balance | B28: =$B$9 -> 9250 | C28: =B32 -> 5967.469 | D28: =C32 -> 2337.1615 | E28: =D32 -> 0 | F28: =E32 -> 0 | G28: =F32 -> 0 | H28: =G32 -> 0 | I28: =H32 -> 0 | J28: =I32 -> 0 | ... AE28: =AD32 -> 0
A29: Balance after interest | B29: =B28*(1+B27) -> 9865.8958 | C29: =C28*(1+C27) -> 6364.8029 | D29: =D28*(1+D27) -> 2492.7775 | E29: =E28*(1+E27) -> 0 | F29: =F28*(1+F27) -> 0 | G29: =G28*(1+G27) -> 0 | H29: =H28*(1+H27) -> 0 | I29: =I28*(1+I27) -> 0 | ... AE29: =AE28*(1+AE27) -> 0
A30: Scheduled repayment | B30: =$B$11*MAX(0,B25-$B$12) -> 3898.4269 | C30: =$B$11*MAX(0,C25-$B$12) -> 4027.6414 | D30: =$B$11*MAX(0,D25-$B$12) -> 4159.4402 | E30: =$B$11*MAX(0,E25-$B$12) -> 4293.875 | F30: =$B$11*MAX(0,F25-$B$12) -> 4430.9985 | G30: =$B$11*MAX(0,G25-$B$12) -> 4570.8645 | H30: =$B$11*MAX(0,H25-$B$12) -> 4713.5278 | I30: =$B$11*MAX(0,I25-$B$12) -> 4859.0444 | ... AE30: =$B$11*MAX(0,AE25-$B$12) -> 8910.9475
A31: Actual repayment | B31: =MIN(B30,B29) -> 3898.4269 | C31: =MIN(C30,C29) -> 4027.6414 | D31: =MIN(D30,D29) -> 2492.7775 | E31: =MIN(E30,E29) -> 0 | F31: =MIN(F30,F29) -> 0 | G31: =MIN(G30,G29) -> 0 | H31: =MIN(H30,H29) -> 0 | I31: =MIN(I30,I29) -> 0 | ... AE31: =MIN(AE30,AE29) -> 0
A32: Closing balance | B32: =B29-B31 -> 5967.469 | C32: =C29-C31 -> 2337.1615 | D32: =D29-D31 -> 0 | E32: =E29-E31 -> 0 | F32: =F29-F31 -> 0 | G32: =G29-G31 -> 0 | H32: =H29-H31 -> 0 | I32: =I29-I31 -> 0 | ... AE32: =AE29-AE31 -> 0
A33: Discount factor | B33: =1/(1+$B$20) -> 0.97087379 | C33: =1/(1+$B$20)^C$24 -> 0.94259591 | D33: =1/(1+$B$20)^D$24 -> 0.91514166 | E33: =1/(1+$B$20)^E$24 -> 0.88848705 | F33: =1/(1+$B$20)^F$24 -> 0.86260878 | G33: =1/(1+$B$20)^G$24 -> 0.83748426 | H33: =1/(1+$B$20)^H$24 -> 0.81309151 | I33: =1/(1+$B$20)^I$24 -> 0.78940923 | J33: =1/(1+$B$20)^J$24 -> 0.76641673 | ... AE33: =1/(1+$B$20)^AE$24 -> 0.41198676
A34: PV repayment | B34: =B31*B33 -> 3784.8805 | C34: =C31*C33 -> 3796.4383 | D34: =D31*D33 -> 2281.2446 | E34: =E31*E33 -> 0 | F34: =F31*F33 -> 0 | G34: =G31*G33 -> 0 | H34: =H31*H33 -> 0 | I34: =I31*I33 -> 0 | ... AE34: =AE31*AE33 -> 0
A37: Loan PV at 3% | B37: =SUM(B34:AE34) -> 9862.5633
A38: Log experienced price change | B38: =LN($B$10)-LN(B37) -> 0.81134618
A39: Implied elasticity | B39: =$B$21/B38 -> -0.71140915
A40: Balance written off after year 30 | B40: =AE32 -> 0
A42: SDR=14.9%
A43: Label | B43: Value or formula
A44: 2024 wage in euros | B44: 82969
A45: EUR to GBP rate | B45: 0.848248
A46: Annual wage growth | B46: 0.02
A47: Years to first repayment | B47: 1
A48: 2024 wage in GBP | B48: 70378.288
A49: First repayment-year earnings | B49: 71785.854
A50: Opening loan balance | B50: 9250
A51: Post-Brexit price | B51: 22200
A52: Repayment rate | B52: 0.09
A53: Lower threshold | B53: 28470
A54: Upper threshold | B54: 51245
A55: First RPI rate | B55: 0.043
... A62: Controlled TWFE coefficient | B62: -0.5771991
A65: Repayment year | B65: 1 | C65: 2 | D65: 3 | E65: 4 | F65: 5 | G65: 6 | H65: 7 | I65: 8 | J65: 9 | K65: 10 | L65: 11 | M65: 12 | N65: 13 | O65: 14 | P65: 15 | Q65: 16 | R65: 17 | S65: 18 | T65: 19 | U65: 20 | V65: 21 | W65: 22 | X65: 23 | Y65: 24 | Z65: 25 | AA65: 26 | AB65: 27 | AC65: 28 | AD65: 29 | AE65: 30
A66: Earnings | B66: =$B$8 -> 71785.854 | C66: =$B$8*(1+$B$5)^(C$24-1) -> 73221.571 | D66: =$B$8*(1+$B$5)^(D$24-1) -> 74686.003 | E66: =$B$8*(1+$B$5)^(E$24-1) -> 76179.723 | F66: =$B$8*(1+$B$5)^(F$24-1) -> 77703.317 | G66: =$B$8*(1+$B$5)^(G$24-1) -> 79257.383 | H66: =$B$8*(1+$B$5)^(H$24-1) -> 80842.531 | I66: =$B$8*(1+$B$5)^(I$24-1) -> 82459.382 | J66: =$B$8*(1+$B$5)^(J$24-1) -> 84108.569 | ... AE66: =$B$8*(1+$B$5)^(AE$24-1) -> 127480.53
A67: Income loading | B67: =IF(B66<=$B$12,0,IF(B66<$B$13,(B66-$B$12)/($B$13-$B$12),1)) -> 1 | C67: =IF(C66<=$B$12,0,IF(C66<$B$13,(C66-$B$12)/($B$13-$B$12),1)) -> 1 | D67: =IF(D66<=$B$12,0,IF(D66<$B$13,(D66-$B$12)/($B$13-$B$12),1)) -> 1 | E67: =IF(E66<=$B$12,0,IF(E66<$B$13,(E66-$B$12)/($B$13-$B$12),1)) -> 1 | F67: =IF(F66<=$B$12,0,IF(F66<$B$13,(F66-$B$12)/($B$13-$B$12),1)) -> 1 | G67: =IF(G66<=$B$12,0,IF(G66<$B$13,(G66-$B$12)/($B$13-$B$12),1)) -> 1 | H67: =IF(H66<=$B$12,0,IF(H66<$B$13,(H66-$B$12)/($B$13-$B$12),1)) -> 1 | I67: =IF(I66<=$B$12,0,IF(I66<$B$13,(I66-$B$12)/($B$13-$B$12),1)) -> 1 | ... AE67: =IF(AE66<=$B$12,0,IF(AE66<$B$13,(AE66-$B$12)/($B$13-$B$12),1)) -> 1
A68: Interest rate | B68: =$B$18+$B$19*B67 -> 0.066583333 | C68: =$B$18+$B$19*C67 -> 0.066583333 | D68: =$B$18+$B$19*D67 -> 0.066583333 | E68: =$B$18+$B$19*E67 -> 0.066583333 | F68: =$B$18+$B$19*F67 -> 0.066583333 | G68: =$B$18+$B$19*G67 -> 0.066583333 | H68: =$B$18+$B$19*H67 -> 0.066583333 | I68: =$B$18+$B$19*I67 -> 0.066583333 | ... AE68: =$B$18+$B$19*AE67 -> 0.066583333
A69: Opening balance | B69: =$B$9 -> 9250 | C69: =B73 -> 5967.469 | D69: =C73 -> 2337.1615 | E69: =D73 -> 0 | F69: =E73 -> 0 | G69: =F73 -> 0 | H69: =G73 -> 0 | I69: =H73 -> 0 | J69: =I73 -> 0 | ... AE69: =AD73 -> 0
A70: Balance after interest | B70: =B69*(1+B68) -> 9865.8958 | C70: =C69*(1+C68) -> 6364.8029 | D70: =D69*(1+D68) -> 2492.7775 | E70: =E69*(1+E68) -> 0 | F70: =F69*(1+F68) -> 0 | G70: =G69*(1+G68) -> 0 | H70: =H69*(1+H68) -> 0 | I70: =I69*(1+I68) -> 0 | ... AE70: =AE69*(1+AE68) -> 0
A71: Scheduled repayment | B71: =$B$11*MAX(0,B66-$B$12) -> 3898.4269 | C71: =$B$11*MAX(0,C66-$B$12) -> 4027.6414 | D71: =$B$11*MAX(0,D66-$B$12) -> 4159.4402 | E71: =$B$11*MAX(0,E66-$B$12) -> 4293.875 | F71: =$B$11*MAX(0,F66-$B$12) -> 4430.9985 | G71: =$B$11*MAX(0,G66-$B$12) -> 4570.8645 | H71: =$B$11*MAX(0,H66-$B$12) -> 4713.5278 | I71: =$B$11*MAX(0,I66-$B$12) -> 4859.0444 | ... AE71: =$B$11*MAX(0,AE66-$B$12) -> 8910.9475
A72: Actual repayment | B72: =MIN(B71,B70) -> 3898.4269 | C72: =MIN(C71,C70) -> 4027.6414 | D72: =MIN(D71,D70) -> 2492.7775 | E72: =MIN(E71,E70) -> 0 | F72: =MIN(F71,F70) -> 0 | G72: =MIN(G71,G70) -> 0 | H72: =MIN(H71,H70) -> 0 | I72: =MIN(I71,I70) -> 0 | ... AE72: =MIN(AE71,AE70) -> 0
A73: Closing balance | B73: =B70-B72 -> 5967.469 | C73: =C70-C72 -> 2337.1615 | D73: =D70-D72 -> 0 | E73: =E70-E72 -> 0 | F73: =F70-F72 -> 0 | G73: =G70-G72 -> 0 | H73: =H70-H72 -> 0 | I73: =I70-I72 -> 0 | ... AE73: =AE70-AE72 -> 0
A74: Discount factor | B74: =1/(1+$B$61)^B65 -> 0.87032202 | C74: =1/(1+$B$61)^C65 -> 0.75746042 | D74: =1/(1+$B$61)^D65 -> 0.65923448 | E74: =1/(1+$B$61)^E65 -> 0.57374628 | F74: =1/(1+$B$61)^F65 -> 0.49934402 | G74: =1/(1+$B$61)^G65 -> 0.4345901 | H74: =1/(1+$B$61)^H65 -> 0.37823333 | I74: =1/(1+$B$61)^I65 -> 0.3291848 | ... AE74: =1/(1+$B$61)^AE65 -> 0.015502407
A75: PV repayment | B75: =B72*B74 -> 3392.8867 | C75: =C72*C74 -> 3050.7789 | D75: =D72*D74 -> 1643.3249 | E75: =E72*E74 -> 0 | F75: =F72*F74 -> 0 | G75: =G72*G74 -> 0 | H75: =H72*H74 -> 0 | I75: =I72*I74 -> 0 | ... AE75: =AE72*AE74 -> 0
A78: Loan PV at 14.9 | B78: =SUM(B75:AE75) -> 8086.9906
A79: Log experienced price change | B79: =LN($B$10)-LN(B78) -> 1.0098356
A80: Implied elasticity | B80: =$B$21/B79 -> -0.57157728
A81: Balance written off after year 30 | B81: =AE73 -> 0
A84: SDR=35
A85: Label | B85: Value or formula
A86: 2024 wage in euros | B86: 82969
A87: EUR to GBP rate | B87: 0.848248
A88: Annual wage growth | B88: 0.02
A89: Years to first repayment | B89: 1
A90: 2024 wage in GBP | B90: 70378.288
A91: First repayment-year earnings | B91: 71785.854
A92: Opening loan balance | B92: 9250
A93: Post-Brexit price | B93: 22200
A94: Repayment rate | B94: 0.09
A95: Lower threshold | B95: 28470
A96: Upper threshold | B96: 51245
A97: First RPI rate | B97: 0.043
... A104: Controlled TWFE coefficient | B104: -0.5771991
A107: Repayment year | B107: 1 | C107: 2 | D107: 3 | E107: 4 | F107: 5 | G107: 6 | H107: 7 | I107: 8 | J107: 9 | K107: 10 | L107: 11 | M107: 12 | N107: 13 | O107: 14 | P107: 15 | Q107: 16 | R107: 17 | S107: 18 | T107: 19 | U107: 20 | V107: 21 | W107: 22 | X107: 23 | Y107: 24 | Z107: 25 | AA107: 26 | AB107: 27 | AC107: 28 | AD107: 29 | AE107: 30
A108: Earnings | B108: =$B$8 -> 71785.854 | C108: =$B$8*(1+$B$5)^(C$24-1) -> 73221.571 | D108: =$B$8*(1+$B$5)^(D$24-1) -> 74686.003 | E108: =$B$8*(1+$B$5)^(E$24-1) -> 76179.723 | F108: =$B$8*(1+$B$5)^(F$24-1) -> 77703.317 | G108: =$B$8*(1+$B$5)^(G$24-1) -> 79257.383 | H108: =$B$8*(1+$B$5)^(H$24-1) -> 80842.531 | I108: =$B$8*(1+$B$5)^(I$24-1) -> 82459.382 | J108: =$B$8*(1+$B$5)^(J$24-1) -> 84108.569 | ... AE108: =$B$8*(1+$B$5)^(AE$24-1) -> 127480.53
A109: Income loading | B109: =IF(B108<=$B$12,0,IF(B108<$B$13,(B108-$B$12)/($B$13-$B$12),1)) -> 1 | C109: =IF(C108<=$B$12,0,IF(C108<$B$13,(C108-$B$12)/($B$13-$B$12),1)) -> 1 | D109: =IF(D108<=$B$12,0,IF(D108<$B$13,(D108-$B$12)/($B$13-$B$12),1)) -> 1 | E109: =IF(E108<=$B$12,0,IF(E108<$B$13,(E108-$B$12)/($B$13-$B$12),1)) -> 1 | F109: =IF(F108<=$B$12,0,IF(F108<$B$13,(F108-$B$12)/($B$13-$B$12),1)) -> 1 | G109: =IF(G108<=$B$12,0,IF(G108<$B$13,(G108-$B$12)/($B$13-$B$12),1)) -> 1 | H109: =IF(H108<=$B$12,0,IF(H108<$B$13,(H108-$B$12)/($B$13-$B$12),1)) -> 1 | I109: =IF(I108<=$B$12,0,IF(I108<$B$13,(I108-$B$12)/($B$13-$B$12),1)) -> 1 | ... AE109: =IF(AE108<=$B$12,0,IF(AE108<$B$13,(AE108-$B$12)/($B$13-$B$12),1)) -> 1
A110: Interest rate | B110: =$B$18+$B$19*B109 -> 0.066583333 | C110: =$B$18+$B$19*C109 -> 0.066583333 | D110: =$B$18+$B$19*D109 -> 0.066583333 | E110: =$B$18+$B$19*E109 -> 0.066583333 | F110: =$B$18+$B$19*F109 -> 0.066583333 | G110: =$B$18+$B$19*G109 -> 0.066583333 | H110: =$B$18+$B$19*H109 -> 0.066583333 | I110: =$B$18+$B$19*I109 -> 0.066583333 | ... AE110: =$B$18+$B$19*AE109 -> 0.066583333
A111: Opening balance | B111: =$B$9 -> 9250 | C111: =B115 -> 5967.469 | D111: =C115 -> 2337.1615 | E111: =D115 -> 0 | F111: =E115 -> 0 | G111: =F115 -> 0 | H111: =G115 -> 0 | I111: =H115 -> 0 | J111: =I115 -> 0 | ... AE111: =AD115 -> 0
A112: Balance after interest | B112: =B111*(1+B110) -> 9865.8958 | C112: =C111*(1+C110) -> 6364.8029 | D112: =D111*(1+D110) -> 2492.7775 | E112: =E111*(1+E110) -> 0 | F112: =F111*(1+F110) -> 0 | G112: =G111*(1+G110) -> 0 | H112: =H111*(1+H110) -> 0 | I112: =I111*(1+I110) -> 0 | ... AE112: =AE111*(1+AE110) -> 0
A113: Scheduled repayment | B113: =$B$11*MAX(0,B108-$B$12) -> 3898.4269 | C113: =$B$11*MAX(0,C108-$B$12) -> 4027.6414 | D113: =$B$11*MAX(0,D108-$B$12) -> 4159.4402 | E113: =$B$11*MAX(0,E108-$B$12) -> 4293.875 | F113: =$B$11*MAX(0,F108-$B$12) -> 4430.9985 | G113: =$B$11*MAX(0,G108-$B$12) -> 4570.8645 | H113: =$B$11*MAX(0,H108-$B$12) -> 4713.5278 | I113: =$B$11*MAX(0,I108-$B$12) -> 4859.0444 | ... AE113: =$B$11*MAX(0,AE108-$B$12) -> 8910.9475
A114: Actual repayment | B114: =MIN(B113,B112) -> 3898.4269 | C114: =MIN(C113,C112) -> 4027.6414 | D114: =MIN(D113,D112) -> 2492.7775 | E114: =MIN(E113,E112) -> 0 | F114: =MIN(F113,F112) -> 0 | G114: =MIN(G113,G112) -> 0 | H114: =MIN(H113,H112) -> 0 | I114: =MIN(I113,I112) -> 0 | ... AE114: =MIN(AE113,AE112) -> 0
A115: Closing balance | B115: =B112-B114 -> 5967.469 | C115: =C112-C114 -> 2337.1615 | D115: =D112-D114 -> 0 | E115: =E112-E114 -> 0 | F115: =F112-F114 -> 0 | G115: =G112-G114 -> 0 | H115: =H112-H114 -> 0 | I115: =I112-I114 -> 0 | ... AE115: =AE112-AE114 -> 0
A116: Discount factor | B116: =1/(1+$B$103)^B107 -> 0.74074074 | C116: =1/(1+$B$103)^C107 -> 0.54869684 | D116: =1/(1+$B$103)^D107 -> 0.40644211 | E116: =1/(1+$B$103)^E107 -> 0.30106823 | F116: =1/(1+$B$103)^F107 -> 0.2230135 | G116: =1/(1+$B$103)^G107 -> 0.16519519 | H116: =1/(1+$B$103)^H107 -> 0.1223668 | I116: =1/(1+$B$103)^I107 -> 0.090642078 | ... AE116: =1/(1+$B$103)^AE107 -> 0.00012302318
A117: PV repayment | B117: =B114*B116 -> 2887.7236 | C117: =C114*C116 -> 2209.9541 | D117: =D114*D116 -> 1013.1698 | E117: =E114*E116 -> 0 | F117: =F114*F116 -> 0 | G117: =G114*G116 -> 0 | H117: =H114*H116 -> 0 | I117: =I114*I116 -> 0 | ... AE117: =AE114*AE116 -> 0
A120: Loan PV at 35% | B120: =SUM(B117:AE117) -> 6110.8475
A121: Log experienced price change | B121: =LN($B$10)-LN(B120) -> 1.2900268
A122: Implied elasticity | B122: =$B$21/B121 -> -0.44743186
A123: Balance written off after year 30 | B123: =AE115 -> 0
A127: ctry | B127: eta_insignificant | C127: eta_neutral | D127: eta_35
A128: Austria | B128: -0.58614545 | C128: -0.45993261 | D128: -0.32894815
A129: Belgium | B129: -0.66869758 | C129: -0.52837903 | D129: -0.38008516
A130: Bulgaria | B130: -1.4144608 | C130: -0.77852612 | D130: -0.51547062
...

Sheet Portugal
A1: SDR=3%
A2: Label | B2: Value or formula
A3: 2024 wage in euros | B3: =data!J8 -> 24818
A4: EUR to GBP rate | B4: 0.848248
A5: Annual wage growth | B5: 0.02
A6: Years to first repayment | B6: 1
A7: 2024 wage in GBP | B7: =B3*B4 -> 21051.819
A8: First repayment-year earnings | B8: =B7*(1+B5)^B6 -> 21472.855
A9: Opening loan balance | B9: 9250
A10: Post-Brexit price | B10: 22200
A11: Repayment rate | B11: 0.09
A12: Lower threshold | B12: =data!D22 -> 17085
A13: Upper threshold | B13: =data!E22 -> 30750
A14: First RPI rate | B14: 0.043
A15: Months at first RPI rate | B15: 5
A16: Second RPI rate | B16: 0.032
A17: Months at second RPI rate | B17: 7
A18: Fixed weighted RPI | B18: =(B14*B15+B16*B17)/(B15+B17) -> 0.036583333
A19: Maximum interest spread | B19: 0.03
A20: Subjective discount rate | B20: 0.03
A21: Controlled TWFE coefficient | B21: -0.8357402
A24: Repayment year | B24: 1 | C24: 2 | D24: 3 | E24: 4 | F24: 5 | G24: 6 | H24: 7 | I24: 8 | J24: 9 | K24: 10 | L24: 11 | M24: 12 | N24: 13 | O24: 14 | P24: 15 | Q24: 16 | R24: 17 | S24: 18 | T24: 19 | U24: 20 | V24: 21 | W24: 22 | X24: 23 | Y24: 24 | Z24: 25 | AA24: 26 | AB24: 27 | AC24: 28 | AD24: 29 | AE24: 30
A25: Earnings | B25: =$B$8 -> 21472.855 | C25: =$B$8*(1+$B$5)^(C$24-1) -> 21902.312 | D25: =$B$8*(1+$B$5)^(D$24-1) -> 22340.359 | E25: =$B$8*(1+$B$5)^(E$24-1) -> 22787.166 | F25: =$B$8*(1+$B$5)^(F$24-1) -> 23242.909 | G25: =$B$8*(1+$B$5)^(G$24-1) -> 23707.767 | H25: =$B$8*(1+$B$5)^(H$24-1) -> 24181.923 | I25: =$B$8*(1+$B$5)^(I$24-1) -> 24665.561 | J25: =$B$8*(1+$B$5)^(J$24-1) -> 25158.872 | ... AE25: =$B$8*(1+$B$5)^(AE$24-1) -> 38132.456
A26: Income loading | B26: =IF(B25<=$B$12,0,IF(B25<$B$13,(B25-$B$12)/($B$13-$B$12),1)) -> 0.32110174 | C26: =IF(C25<=$B$12,0,IF(C25<$B$13,(C25-$B$12)/($B$13-$B$12),1)) -> 0.35252926 | D26: =IF(D25<=$B$12,0,IF(D25<$B$13,(D25-$B$12)/($B$13-$B$12),1)) -> 0.38458533 | E26: =IF(E25<=$B$12,0,IF(E25<$B$13,(E25-$B$12)/($B$13-$B$12),1)) -> 0.41728253 | F26: =IF(F25<=$B$12,0,IF(F25<$B$13,(F25-$B$12)/($B$13-$B$12),1)) -> 0.45063367 | G26: =IF(G25<=$B$12,0,IF(G25<$B$13,(G25-$B$12)/($B$13-$B$12),1)) -> 0.48465183 | H26: =IF(H25<=$B$12,0,IF(H25<$B$13,(H25-$B$12)/($B$13-$B$12),1)) -> 0.51935036 | I26: =IF(I25<=$B$12,0,IF(I25<$B$13,(I25-$B$12)/($B$13-$B$12),1)) -> 0.55474285 | ... AE26: =IF(AE25<=$B$12,0,IF(AE25<$B$13,(AE25-$B$12)/($B$13-$B$12),1)) -> 1
A27: Interest rate | B27: =$B$18+$B$19*B26 -> 0.046216385 | C27: =$B$18+$B$19*C26 -> 0.047159211 | D27: =$B$18+$B$19*D26 -> 0.048120893 | E27: =$B$18+$B$19*E26 -> 0.049101809 | F27: =$B$18+$B$19*F26 -> 0.050102343 | G27: =$B$18+$B$19*G26 -> 0.051122888 | H27: =$B$18+$B$19*H26 -> 0.052163844 | I27: =$B$18+$B$19*I26 -> 0.053225619 | ... AE27: =$B$18+$B$19*AE26 -> 0.066583333
A28: Opening balance | B28: =$B$9 -> 9250 | C28: =B32 -> 9282.5946 | D28: =C32 -> 9286.7963 | E28: =D32 -> 9260.703 | F28: =E32 -> 9202.2253 | G28: =F32 -> 9109.0666 | H28: =G32 -> 8978.6993 | I28: =H32 -> 8808.3397 | J28: =I32 -> 8594.9186 | ... AE28: =AD32 -> 0
A29: Balance after interest | B29: =B28*(1+B27) -> 9677.5016 | C29: =C28*(1+C27) -> 9720.3544 | D29: =D28*(1+D27) -> 9733.6853 | E29: =E28*(1+E27) -> 9715.4203 | F29: =F28*(1+F27) -> 9663.2784 | G29: =G28*(1+G27) -> 9574.7484 | H29: =H28*(1+H27) -> 9447.0628 | I29: =I28*(1+I27) -> 9277.1691 | ... AE29: =AE28*(1+AE27) -> 0
A30: Scheduled repayment | B30: =$B$11*MAX(0,B25-$B$12) -> 394.90697 | C30: =$B$11*MAX(0,C25-$B$12) -> 433.55811 | D30: =$B$11*MAX(0,D25-$B$12) -> 472.98227 | E30: =$B$11*MAX(0,E25-$B$12) -> 513.19492 | F30: =$B$11*MAX(0,F25-$B$12) -> 554.21182 | G30: =$B$11*MAX(0,G25-$B$12) -> 596.04905 | H30: =$B$11*MAX(0,H25-$B$12) -> 638.72303 | I30: =$B$11*MAX(0,I25-$B$12) -> 682.2505 | ... AE30: =$B$11*MAX(0,AE25-$B$12) -> 1894.271
A31: Actual repayment | B31: =MIN(B30,B29) -> 394.90697 | C31: =MIN(C30,C29) -> 433.55811 | D31: =MIN(D30,D29) -> 472.98227 | E31: =MIN(E30,E29) -> 513.19492 | F31: =MIN(F30,F29) -> 554.21182 | G31: =MIN(G30,G29) -> 596.04905 | H31: =MIN(H30,H29) -> 638.72303 | I31: =MIN(I30,I29) -> 682.2505 | ... AE31: =MIN(AE30,AE29) -> 0
A32: Closing balance | B32: =B29-B31 -> 9282.5946 | C32: =C29-C31 -> 9286.7963 | D32: =D29-D31 -> 9260.703 | E32: =E29-E31 -> 9202.2253 | F32: =F29-F31 -> 9109.0666 | G32: =G29-G31 -> 8978.6993 | H32: =H29-H31 -> 8808.3397 | I32: =I29-I31 -> 8594.9186 | ... AE32: =AE29-AE31 -> 0
A33: Discount factor | B33: =1/(1+$B$20) -> 0.97087379 | C33: =1/(1+$B$20)^C$24 -> 0.94259591 | D33: =1/(1+$B$20)^D$24 -> 0.91514166 | E33: =1/(1+$B$20)^E$24 -> 0.88848705 | F33: =1/(1+$B$20)^F$24 -> 0.86260878 | G33: =1/(1+$B$20)^G$24 -> 0.83748426 | H33: =1/(1+$B$20)^H$24 -> 0.81309151 | I33: =1/(1+$B$20)^I$24 -> 0.78940923 | J33: =1/(1+$B$20)^J$24 -> 0.76641673 | ... AE33: =1/(1+$B$20)^AE$24 -> 0.41198676
A34: PV repayment | B34: =B31*B33 -> 383.40483 | C34: =C31*C33 -> 408.6701 | D34: =D31*D33 -> 432.84578 | E34: =E31*E33 -> 455.96704 | F34: =F31*F33 -> 478.06798 | G34: =G31*G33 -> 499.1817 | H34: =H31*H33 -> 519.34028 | I34: =I31*I33 -> 538.57484 | ... AE34: =AE31*AE33 -> 0
A37: Loan PV at 3% | B37: =SUM(B34:AE34) -> 11944.227
A38: Log experienced price change | B38: =LN($B$10)-LN(B37) -> 0.6198442
A39: Implied elasticity | B39: =$B$21/B38 -> -1.3483069
A40: Balance written off after year 30 | B40: =AE32 -> 0
A42: SDR=14.9%
A43: Label | B43: Value or formula
A44: 2024 wage in euros | B44: 24818
A45: EUR to GBP rate | B45: 0.848248
A46: Annual wage growth | B46: 0.02
A47: Years to first repayment | B47: 1
A48: 2024 wage in GBP | B48: 21051.819
A49: First repayment-year earnings | B49: 21472.855
A50: Opening loan balance | B50: 9250
A51: Post-Brexit price | B51: 22200
A52: Repayment rate | B52: 0.09
A53: Lower threshold | B53: 17085
A54: Upper threshold | B54: 30750
A55: First RPI rate | B55: 0.043
... A62: Controlled TWFE coefficient | B62: -0.8357402
A65: Repayment year | B65: 1 | C65: 2 | D65: 3 | E65: 4 | F65: 5 | G65: 6 | H65: 7 | I65: 8 | J65: 9 | K65: 10 | L65: 11 | M65: 12 | N65: 13 | O65: 14 | P65: 15 | Q65: 16 | R65: 17 | S65: 18 | T65: 19 | U65: 20 | V65: 21 | W65: 22 | X65: 23 | Y65: 24 | Z65: 25 | AA65: 26 | AB65: 27 | AC65: 28 | AD65: 29 | AE65: 30
A66: Earnings | B66: =$B$8 -> 21472.855 | C66: =$B$8*(1+$B$5)^(C$24-1) -> 21902.312 | D66: =$B$8*(1+$B$5)^(D$24-1) -> 22340.359 | E66: =$B$8*(1+$B$5)^(E$24-1) -> 22787.166 | F66: =$B$8*(1+$B$5)^(F$24-1) -> 23242.909 | G66: =$B$8*(1+$B$5)^(G$24-1) -> 23707.767 | H66: =$B$8*(1+$B$5)^(H$24-1) -> 24181.923 | I66: =$B$8*(1+$B$5)^(I$24-1) -> 24665.561 | J66: =$B$8*(1+$B$5)^(J$24-1) -> 25158.872 | ... AE66: =$B$8*(1+$B$5)^(AE$24-1) -> 38132.456
A67: Income loading | B67: =IF(B66<=$B$12,0,IF(B66<$B$13,(B66-$B$12)/($B$13-$B$12),1)) -> 0.32110174 | C67: =IF(C66<=$B$12,0,IF(C66<$B$13,(C66-$B$12)/($B$13-$B$12),1)) -> 0.35252926 | D67: =IF(D66<=$B$12,0,IF(D66<$B$13,(D66-$B$12)/($B$13-$B$12),1)) -> 0.38458533 | E67: =IF(E66<=$B$12,0,IF(E66<$B$13,(E66-$B$12)/($B$13-$B$12),1)) -> 0.41728253 | F67: =IF(F66<=$B$12,0,IF(F66<$B$13,(F66-$B$12)/($B$13-$B$12),1)) -> 0.45063367 | G67: =IF(G66<=$B$12,0,IF(G66<$B$13,(G66-$B$12)/($B$13-$B$12),1)) -> 0.48465183 | H67: =IF(H66<=$B$12,0,IF(H66<$B$13,(H66-$B$12)/($B$13-$B$12),1)) -> 0.51935036 | I67: =IF(I66<=$B$12,0,IF(I66<$B$13,(I66-$B$12)/($B$13-$B$12),1)) -> 0.55474285 | ... AE67: =IF(AE66<=$B$12,0,IF(AE66<$B$13,(AE66-$B$12)/($B$13-$B$12),1)) -> 1
A68: Interest rate | B68: =$B$18+$B$19*B67 -> 0.046216385 | C68: =$B$18+$B$19*C67 -> 0.047159211 | D68: =$B$18+$B$19*D67 -> 0.048120893 | E68: =$B$18+$B$19*E67 -> 0.049101809 | F68: =$B$18+$B$19*F67 -> 0.050102343 | G68: =$B$18+$B$19*G67 -> 0.051122888 | H68: =$B$18+$B$19*H67 -> 0.052163844 | I68: =$B$18+$B$19*I67 -> 0.053225619 | ... AE68: =$B$18+$B$19*AE67 -> 0.066583333
A69: Opening balance | B69: =$B$9 -> 9250 | C69: =B73 -> 9282.5946 | D69: =C73 -> 9286.7963 | E69: =D73 -> 9260.703 | F69: =E73 -> 9202.2253 | G69: =F73 -> 9109.0666 | H69: =G73 -> 8978.6993 | I69: =H73 -> 8808.3397 | J69: =I73 -> 8594.9186 | ... AE69: =AD73 -> 0
A70: Balance after interest | B70: =B69*(1+B68) -> 9677.5016 | C70: =C69*(1+C68) -> 9720.3544 | D70: =D69*(1+D68) -> 9733.6853 | E70: =E69*(1+E68) -> 9715.4203 | F70: =F69*(1+F68) -> 9663.2784 | G70: =G69*(1+G68) -> 9574.7484 | H70: =H69*(1+H68) -> 9447.0628 | I70: =I69*(1+I68) -> 9277.1691 | ... AE70: =AE69*(1+AE68) -> 0
A71: Scheduled repayment | B71: =$B$11*MAX(0,B66-$B$12) -> 394.90697 | C71: =$B$11*MAX(0,C66-$B$12) -> 433.55811 | D71: =$B$11*MAX(0,D66-$B$12) -> 472.98227 | E71: =$B$11*MAX(0,E66-$B$12) -> 513.19492 | F71: =$B$11*MAX(0,F66-$B$12) -> 554.21182 | G71: =$B$11*MAX(0,G66-$B$12) -> 596.04905 | H71: =$B$11*MAX(0,H66-$B$12) -> 638.72303 | I71: =$B$11*MAX(0,I66-$B$12) -> 682.2505 | ... AE71: =$B$11*MAX(0,AE66-$B$12) -> 1894.271
A72: Actual repayment | B72: =MIN(B71,B70) -> 394.90697 | C72: =MIN(C71,C70) -> 433.55811 | D72: =MIN(D71,D70) -> 472.98227 | E72: =MIN(E71,E70) -> 513.19492 | F72: =MIN(F71,F70) -> 554.21182 | G72: =MIN(G71,G70) -> 596.04905 | H72: =MIN(H71,H70) -> 638.72303 | I72: =MIN(I71,I70) -> 682.2505 | ... AE72: =MIN(AE71,AE70) -> 0
A73: Closing balance | B73: =B70-B72 -> 9282.5946 | C73: =C70-C72 -> 9286.7963 | D73: =D70-D72 -> 9260.703 | E73: =E70-E72 -> 9202.2253 | F73: =F70-F72 -> 9109.0666 | G73: =G70-G72 -> 8978.6993 | H73: =H70-H72 -> 8808.3397 | I73: =I70-I72 -> 8594.9186 | ... AE73: =AE70-AE72 -> 0
A74: Discount factor | B74: =1/(1+$B$61)^B65 -> 0.87032202 | C74: =1/(1+$B$61)^C65 -> 0.75746042 | D74: =1/(1+$B$61)^D65 -> 0.65923448 | E74: =1/(1+$B$61)^E65 -> 0.57374628 | F74: =1/(1+$B$61)^F65 -> 0.49934402 | G74: =1/(1+$B$61)^G65 -> 0.4345901 | H74: =1/(1+$B$61)^H65 -> 0.37823333 | I74: =1/(1+$B$61)^I65 -> 0.3291848 | ... AE74: =1/(1+$B$61)^AE65 -> 0.015502407
A75: PV repayment | B75: =B72*B74 -> 343.69623 | C75: =C72*C74 -> 328.40311 | D75: =D72*D74 -> 311.80622 | E75: =E72*E74 -> 294.44368 | F75: =F72*F74 -> 276.74236 | G75: =G72*G74 -> 259.03702 | H75: =H72*H74 -> 241.58634 | I75: =I72*I74 -> 224.58649 | ... AE75: =AE72*AE74 -> 0
A78: Loan PV at 3% | B78: =SUM(B75:AE75) -> 3975.4873
A79: Log experienced price change | B79: =LN($B$10)-LN(B78) -> 1.719945
A80: Implied elasticity | B80: =$B$21/B79 -> -0.48591101
A81: Balance written off after year 30 | B81: =AE73 -> 0
A83: SDR=35%
A84: Label | B84: Value or formula
A85: 2024 wage in euros | B85: 24818
A86: EUR to GBP rate | B86: 0.848248
A87: Annual wage growth | B87: 0.02
A88: Years to first repayment | B88: 1
A89: 2024 wage in GBP | B89: 21051.819
A90: First repayment-year earnings | B90: 21472.855
A91: Opening loan balance | B91: 9250
A92: Post-Brexit price | B92: 22200
A93: Repayment rate | B93: 0.09
A94: Lower threshold | B94: 17085
A95: Upper threshold | B95: 30750
A96: First RPI rate | B96: 0.043
... A103: Controlled TWFE coefficient | B103: -0.8357402
A106: Repayment year | B106: 1 | C106: 2 | D106: 3 | E106: 4 | F106: 5 | G106: 6 | H106: 7 | I106: 8 | J106: 9 | K106: 10 | L106: 11 | M106: 12 | N106: 13 | O106: 14 | P106: 15 | Q106: 16 | R106: 17 | S106: 18 | T106: 19 | U106: 20 | V106: 21 | W106: 22 | X106: 23 | Y106: 24 | Z106: 25 | AA106: 26 | AB106: 27 | AC106: 28 | AD106: 29 | AE106: 30
A107: Earnings | B107: =$B$8 -> 21472.855 | C107: =$B$8*(1+$B$5)^(C$24-1) -> 21902.312 | D107: =$B$8*(1+$B$5)^(D$24-1) -> 22340.359 | E107: =$B$8*(1+$B$5)^(E$24-1) -> 22787.166 | F107: =$B$8*(1+$B$5)^(F$24-1) -> 23242.909 | G107: =$B$8*(1+$B$5)^(G$24-1) -> 23707.767 | H107: =$B$8*(1+$B$5)^(H$24-1) -> 24181.923 | I107: =$B$8*(1+$B$5)^(I$24-1) -> 24665.561 | J107: =$B$8*(1+$B$5)^(J$24-1) -> 25158.872 | ... AE107: =$B$8*(1+$B$5)^(AE$24-1) -> 38132.456
A108: Income loading | B108: =IF(B107<=$B$12,0,IF(B107<$B$13,(B107-$B$12)/($B$13-$B$12),1)) -> 0.32110174 | C108: =IF(C107<=$B$12,0,IF(C107<$B$13,(C107-$B$12)/($B$13-$B$12),1)) -> 0.35252926 | D108: =IF(D107<=$B$12,0,IF(D107<$B$13,(D107-$B$12)/($B$13-$B$12),1)) -> 0.38458533 | E108: =IF(E107<=$B$12,0,IF(E107<$B$13,(E107-$B$12)/($B$13-$B$12),1)) -> 0.41728253 | F108: =IF(F107<=$B$12,0,IF(F107<$B$13,(F107-$B$12)/($B$13-$B$12),1)) -> 0.45063367 | G108: =IF(G107<=$B$12,0,IF(G107<$B$13,(G107-$B$12)/($B$13-$B$12),1)) -> 0.48465183 | H108: =IF(H107<=$B$12,0,IF(H107<$B$13,(H107-$B$12)/($B$13-$B$12),1)) -> 0.51935036 | I108: =IF(I107<=$B$12,0,IF(I107<$B$13,(I107-$B$12)/($B$13-$B$12),1)) -> 0.55474285 | ... AE108: =IF(AE107<=$B$12,0,IF(AE107<$B$13,(AE107-$B$12)/($B$13-$B$12),1)) -> 1
A109: Interest rate | B109: =$B$18+$B$19*B108 -> 0.046216385 | C109: =$B$18+$B$19*C108 -> 0.047159211 | D109: =$B$18+$B$19*D108 -> 0.048120893 | E109: =$B$18+$B$19*E108 -> 0.049101809 | F109: =$B$18+$B$19*F108 -> 0.050102343 | G109: =$B$18+$B$19*G108 -> 0.051122888 | H109: =$B$18+$B$19*H108 -> 0.052163844 | I109: =$B$18+$B$19*I108 -> 0.053225619 | ... AE109: =$B$18+$B$19*AE108 -> 0.066583333
A110: Opening balance | B110: =$B$9 -> 9250 | C110: =B114 -> 9282.5946 | D110: =C114 -> 9286.7963 | E110: =D114 -> 9260.703 | F110: =E114 -> 9202.2253 | G110: =F114 -> 9109.0666 | H110: =G114 -> 8978.6993 | I110: =H114 -> 8808.3397 | J110: =I114 -> 8594.9186 | ... AE110: =AD114 -> 0
A111: Balance after interest | B111: =B110*(1+B109) -> 9677.5016 | C111: =C110*(1+C109) -> 9720.3544 | D111: =D110*(1+D109) -> 9733.6853 | E111: =E110*(1+E109) -> 9715.4203 | F111: =F110*(1+F109) -> 9663.2784 | G111: =G110*(1+G109) -> 9574.7484 | H111: =H110*(1+H109) -> 9447.0628 | I111: =I110*(1+I109) -> 9277.1691 | ... AE111: =AE110*(1+AE109) -> 0
A112: Scheduled repayment | B112: =$B$11*MAX(0,B107-$B$12) -> 394.90697 | C112: =$B$11*MAX(0,C107-$B$12) -> 433.55811 | D112: =$B$11*MAX(0,D107-$B$12) -> 472.98227 | E112: =$B$11*MAX(0,E107-$B$12) -> 513.19492 | F112: =$B$11*MAX(0,F107-$B$12) -> 554.21182 | G112: =$B$11*MAX(0,G107-$B$12) -> 596.04905 | H112: =$B$11*MAX(0,H107-$B$12) -> 638.72303 | I112: =$B$11*MAX(0,I107-$B$12) -> 682.2505 | ... AE112: =$B$11*MAX(0,AE107-$B$12) -> 1894.271
A113: Actual repayment | B113: =MIN(B112,B111) -> 394.90697 | C113: =MIN(C112,C111) -> 433.55811 | D113: =MIN(D112,D111) -> 472.98227 | E113: =MIN(E112,E111) -> 513.19492 | F113: =MIN(F112,F111) -> 554.21182 | G113: =MIN(G112,G111) -> 596.04905 | H113: =MIN(H112,H111) -> 638.72303 | I113: =MIN(I112,I111) -> 682.2505 | ... AE113: =MIN(AE112,AE111) -> 0
A114: Closing balance | B114: =B111-B113 -> 9282.5946 | C114: =C111-C113 -> 9286.7963 | D114: =D111-D113 -> 9260.703 | E114: =E111-E113 -> 9202.2253 | F114: =F111-F113 -> 9109.0666 | G114: =G111-G113 -> 8978.6993 | H114: =H111-H113 -> 8808.3397 | I114: =I111-I113 -> 8594.9186 | ... AE114: =AE111-AE113 -> 0
A115: Discount factor | B115: =1/(1+$B$102)^B106 -> 0.74074074 | C115: =1/(1+$B$102)^C106 -> 0.54869684 | D115: =1/(1+$B$102)^D106 -> 0.40644211 | E115: =1/(1+$B$102)^E106 -> 0.30106823 | F115: =1/(1+$B$102)^F106 -> 0.2230135 | G115: =1/(1+$B$102)^G106 -> 0.16519519 | H115: =1/(1+$B$102)^H106 -> 0.1223668 | I115: =1/(1+$B$102)^I106 -> 0.090642078 | ... AE115: =1/(1+$B$102)^AE106 -> 0.00012302318
A116: PV repayment | B116: =B113*B115 -> 292.52368 | C116: =C113*C115 -> 237.89197 | D116: =D113*D115 -> 192.23991 | E116: =E113*E115 -> 154.50668 | F116: =F113*F115 -> 123.59672 | G116: =G113*G115 -> 98.464435 | H116: =H113*H115 -> 78.158497 | I116: =I113*I115 -> 61.840602 | ... AE116: =AE113*AE115 -> 0
A119: Loan PV at 35% | B119: =SUM(B116:AE116) -> 1454.2076
A120: Log experienced price change | B120: =LN($B$10)-LN(B119) -> 2.7256312
A121: Implied elasticity | B121: =$B$21/B120 -> -0.30662263
A122: Balance written off after year 30 | B122: =AE114 -> 0

Sheet data
A1: num | B1: Country | C1: iso | D1: tau_min | E1: tau_max | I1: Country | J1: Wage_EURO
A2: 1 | B2: Austria | C2: AT | D2: 28470 | E2: 51245 | I2: All | J2: All
A3: 2 | B3: Belgium | C3: BE | D3: 28470 | E3: 51245 | H3: 28 | I3: Sweden | J3: 46525
A4: 3 | B4: Bulgaria | C4: BG | D4: 11390 | E4: 20500 | H4: 11 | I4: Spain | J4: 33700
A5: 4 | B5: Croatia | C5: HR | D5: 17085 | E5: 30750 | H5: 25 | I5: Slovenia | J5: 35133
A6: 5 | B6: Cyprus | C6: CY | D6: 22780 | E6: 41000 | H6: 26 | I6: Slovakia | J6: 20287
A7: 6 | B7: Czechia | C7: CZ | D7: 17085 | E7: 30750 | H7: 24 | I7: Romania | J7: 21108
A8: 7 | B8: Denmark | C8: DK | D8: 28470 | E8: 51245 | H8: 23 | I8: Portugal | J8: 24818
A9: 8 | B9: Estonia | C9: EE | D9: 22780 | E9: 41000 | H9: 22 | I9: Poland | J9: 21246
A10: 9 | B10: Finland | C10: FI | D10: 28470 | E10: 51245 | H10: 20 | I10: Malta | J10: 33499
A11: 10 | B11: France | C11: FR | D11: 22780 | E11: 41000 | H11: 18 | I11: Luxembourg | J11: 82969
A12: 11 | B12: Germany | C12: DE | D12: 28470 | E12: 51245 | H12: 17 | I12: Lithuania | J12: 29104
A13: 12 | B13: Greece | C13: GR | D13: 17085 | E13: 30750 | H13: 16 | I13: Latvia | J13: 22262
A14: 13 | B14: Hungary | C14: HU | D14: 17085 | E14: 30750 | H14: 14 | I14: Italy | J14: 33523
... A27: 26 | B27: Sweden | C27: SE | D27: 28470 | E27: 51245 | H27: 13 | I27: Croatia | J27: 23446
H28: 4 | I28: Bulgaria | J28: 15387
H29: 3 | I29: Belgium | J29: 59632
H30: 21 | I30: Austria | J30: 58600
